Workbook

Sheet Dashboard
B2: R5B E2A 12FP COLD T5 · REPEATER KITTING
B3: ="Contract R5B · E2A 12FP Cold T5 · 92ERP12548A++ · 12FP · Repeaters 1–"&'Kitting Plan'!$C$3&" · "&COUNT('COOIS Data'!$A$6:$A$1505)&" WOs in COOIS · latest release "&TEXT(MAX('COOIS Data'!$F$6:$F$1505),"dd-mmm-yy") -> Contract R5B · E2A 12FP Cold T5 · 92ERP12548A++ · 12FP · Repeaters 1–13 · 691 WOs in COOIS · latest release 03-Oct-26
B5: REPEATERS KITTED | D5: WORK ORDERS KITTED | E5: ISSUED (GMPS) | I5: DELIVERED (DLV) | M5: OPEN WOs
B6: =MIN(H11:H24)&" / "&'Kitting Plan'!$C$3 -> 13 / 13 | D6: =SUM(G11:G24) -> 691 | E6: =MIN(K11:K24)&" reps" -> 7 reps | I6: =MIN(M11:M24)&" reps" -> 5 reps | M6: =SUM(N11:N24) -> 277
B7: ="Every code has ≥ "&MIN(H11:H24)&" full repeater kits (WO printed in SAP)" -> Every code has ≥ 13 full repeater kits (WO printed in SAP) | D7: =SUM(F11:F24)&" needed for "&'Kitting Plan'!$C$3&" reps · "&SUM(I11:I24)&" surplus to review" -> 663 needed for 13 reps · 28 surplus to review | E7: ="components issued for all codes" -> components issued for all codes | I7: ="all 14 codes goods-receipted" -> all 14 codes goods-receipted | M7: ="kitted, not yet delivered" -> kitted, not yet delivered
B9: KITTED BY ASSY CODE | D9: Kitted = WO released and printed (PRT) in COOIS. Kits = kitted WOs ÷ qty per repeater.
B10: Sequence | C10: Assy Code | D10: Description | E10: Qty / Rep | F10: Contract Qty | G10: WOs Kitted | H10: Rep Kits | I10: Surplus WOs | J10: Issued | K10: Issued Reps | L10: Delivered | M10: Delivered Reps | N10: Open WOs | O10: Open WOs
B11: ='Kitting Plan'!A6 -> LASER ASSY | C11: ='Kitting Plan'!B6 -> 92YLS00548BAA | D11: ='Kitting Plan'!C6 -> R5B LASER ASSEMBLY 4P BOAT 1 - E2A | E11: ='Kitting Plan'!D6 -> 1 | F11: ='Kitting Plan'!E6 -> 13 | G11: =SUMIFS('COOIS Data'!$I$6:$I$1505,'COOIS Data'!$B$6:$B$1505,C11) -> 14 | H11: =IF(E11=0,0,INT(G11/E11)) -> 14 | I11: =MAX(0,G11-F11) -> 1 | J11: =SUMIFS('COOIS Data'!$J$6:$J$1505,'COOIS Data'!$B$6:$B$1505,C11) -> 10 | K11: =IF(E11=0,0,INT(J11/E11)) -> 10 | L11: =SUMIFS('COOIS Data'!$K$6:$K$1505,'COOIS Data'!$B$6:$B$1505,C11) -> 9 | M11: =IF(E11=0,0,INT(L11/E11)) -> 9 | N11: =G11-L11 -> 5
B12: ='Kitting Plan'!A7 -> LASER ASSY | C12: ='Kitting Plan'!B7 -> 92YLS00548BBA | D12: ='Kitting Plan'!C7 -> R5B LASER ASSEMBLY 4P BOAT 2/3 - E2A | E12: ='Kitting Plan'!D7 -> 2 | F12: ='Kitting Plan'!E7 -> 26 | G12: =SUMIFS('COOIS Data'!$I$6:$I$1505,'COOIS Data'!$B$6:$B$1505,C12) -> 26 | H12: =IF(E12=0,0,INT(G12/E12)) -> 13 | I12: =MAX(0,G12-F12) -> 0 | J12: =SUMIFS('COOIS Data'!$J$6:$J$1505,'COOIS Data'!$B$6:$B$1505,C12) -> 18 | K12: =IF(E12=0,0,INT(J12/E12)) -> 9 | L12: =SUMIFS('COOIS Data'!$K$6:$K$1505,'COOIS Data'!$B$6:$B$1505,C12) -> 17 | M12: =IF(E12=0,0,INT(L12/E12)) -> 8 | N12: =G12-L12 -> 9
B13: ='Kitting Plan'!A8 -> PSB ASSY | C13: ='Kitting Plan'!B8 -> 91YAF03404AAA | D13: ='Kitting Plan'!C8 -> R5B PSB SUB ASSEMBLY 4P-4FP | E13: ='Kitting Plan'!D8 -> 3 | F13: ='Kitting Plan'!E8 -> 39 | G13: =SUMIFS('COOIS Data'!$I$6:$I$1505,'COOIS Data'!$B$6:$B$1505,C13) -> 51 | H13: =IF(E13=0,0,INT(G13/E13)) -> 17 | I13: =MAX(0,G13-F13) -> 12 | J13: =SUMIFS('COOIS Data'!$J$6:$J$1505,'COOIS Data'!$B$6:$B$1505,C13) -> 38 | K13: =IF(E13=0,0,INT(J13/E13)) -> 12 | L13: =SUMIFS('COOIS Data'!$K$6:$K$1505,'COOIS Data'!$B$6:$B$1505,C13) -> 38 | M13: =IF(E13=0,0,INT(L13/E13)) -> 12 | N13: =G13-L13 -> 13
B14: ='Kitting Plan'!A9 -> OPF ASSY | C14: ='Kitting Plan'!B9 -> 92YFD04548BAA | D14: ='Kitting Plan'!C9 -> R5B OPF ASSEMBLY (4P-4FP) BOAT 1 - E2A | E14: ='Kitting Plan'!D9 -> 1 | F14: ='Kitting Plan'!E9 -> 13 | G14: =SUMIFS('COOIS Data'!$I$6:$I$1505,'COOIS Data'!$B$6:$B$1505,C14) -> 14 | H14: =IF(E14=0,0,INT(G14/E14)) -> 14 | I14: =MAX(0,G14-F14) -> 1 | J14: =SUMIFS('COOIS Data'!$J$6:$J$1505,'COOIS Data'!$B$6:$B$1505,C14) -> 9 | K14: =IF(E14=0,0,INT(J14/E14)) -> 9 | L14: =SUMIFS('COOIS Data'!$K$6:$K$1505,'COOIS Data'!$B$6:$B$1505,C14) -> 8 | M14: =IF(E14=0,0,INT(L14/E14)) -> 8 | N14: =G14-L14 -> 6
B15: ='Kitting Plan'!A10 -> OPF ASSY | C15: ='Kitting Plan'!B10 -> 92YFD04548BBA | D15: ='Kitting Plan'!C10 -> R5B OPF ASSEMBLY (4P-4FP) BOAT 2/3 - E2A | E15: ='Kitting Plan'!D10 -> 2 | F15: ='Kitting Plan'!E10 -> 26 | G15: =SUMIFS('COOIS Data'!$I$6:$I$1505,'COOIS Data'!$B$6:$B$1505,C15) -> 26 | H15: =IF(E15=0,0,INT(G15/E15)) -> 13 | I15: =MAX(0,G15-F15) -> 0 | J15: =SUMIFS('COOIS Data'!$J$6:$J$1505,'COOIS Data'!$B$6:$B$1505,C15) -> 16 | K15: =IF(E15=0,0,INT(J15/E15)) -> 8 | L15: =SUMIFS('COOIS Data'!$K$6:$K$1505,'COOIS Data'!$B$6:$B$1505,C15) -> 15 | M15: =IF(E15=0,0,INT(L15/E15)) -> 7 | N15: =G15-L15 -> 11
B16: ='Kitting Plan'!A11 -> POB ASSY | C16: ='Kitting Plan'!B11 -> 92YWS04548AAA | D16: ='Kitting Plan'!C11 -> R5B 4FP POB LUMENTUM SUB ASSEMBLY - E2A | E16: ='Kitting Plan'!D11 -> 3 | F16: ='Kitting Plan'!E11 -> 39 | G16: =SUMIFS('COOIS Data'!$I$6:$I$1505,'COOIS Data'!$B$6:$B$1505,C16) -> 39 | H16: =IF(E16=0,0,INT(G16/E16)) -> 13 | I16: =MAX(0,G16-F16) -> 0 | J16: =SUMIFS('COOIS Data'!$J$6:$J$1505,'COOIS Data'!$B$6:$B$1505,C16) -> 27 | K16: =IF(E16=0,0,INT(J16/E16)) -> 9 | L16: =SUMIFS('COOIS Data'!$K$6:$K$1505,'COOIS Data'!$B$6:$B$1505,C16) -> 27 | M16: =IF(E16=0,0,INT(L16/E16)) -> 9 | N16: =G16-L16 -> 12
B17: ='Kitting Plan'!A12 -> ERBIUM ASSY | C17: ='Kitting Plan'!B12 -> 92RRA00548AAA | D17: ='Kitting Plan'!C12 -> R5B ERBIUM SPOOL ASSEMBLY - E2A | E17: ='Kitting Plan'!D12 -> 24 | F17: ='Kitting Plan'!E12 -> 312 | G17: =SUMIFS('COOIS Data'!$I$6:$I$1505,'COOIS Data'!$B$6:$B$1505,C17) -> 322 | H17: =IF(E17=0,0,INT(G17/E17)) -> 13 | I17: =MAX(0,G17-F17) -> 10 | J17: =SUMIFS('COOIS Data'!$J$6:$J$1505,'COOIS Data'!$B$6:$B$1505,C17) -> 202 | K17: =IF(E17=0,0,INT(J17/E17)) -> 8 | L17: =SUMIFS('COOIS Data'!$K$6:$K$1505,'COOIS Data'!$B$6:$B$1505,C17) -> 202 | M17: =IF(E17=0,0,INT(L17/E17)) -> 8 | N17: =G17-L17 -> 120
B18: ='Kitting Plan'!A13 -> ERBIUM ASSY | C18: ='Kitting Plan'!B13 -> 92YRA01548AAA | D18: ='Kitting Plan'!C13 -> R5B ERBIUM ASSEMBLY POSITION 1 | E18: ='Kitting Plan'!D13 -> 3 | F18: ='Kitting Plan'!E13 -> 39 | G18: =SUMIFS('COOIS Data'!$I$6:$I$1505,'COOIS Data'!$B$6:$B$1505,C18) -> 40 | H18: =IF(E18=0,0,INT(G18/E18)) -> 13 | I18: =MAX(0,G18-F18) -> 1 | J18: =SUMIFS('COOIS Data'!$J$6:$J$1505,'COOIS Data'!$B$6:$B$1505,C18) -> 25 | K18: =IF(E18=0,0,INT(J18/E18)) -> 8 | L18: =SUMIFS('COOIS Data'!$K$6:$K$1505,'COOIS Data'!$B$6:$B$1505,C18) -> 22 | M18: =IF(E18=0,0,INT(L18/E18)) -> 7 | N18: =G18-L18 -> 18
B19: ='Kitting Plan'!A14 -> ERBIUM ASSY | C19: ='Kitting Plan'!B14 -> 92YRA02548AAA | D19: ='Kitting Plan'!C14 -> R5B ERBIUM ASSEMBLY POSITION 2 | E19: ='Kitting Plan'!D14 -> 3 | F19: ='Kitting Plan'!E14 -> 39 | G19: =SUMIFS('COOIS Data'!$I$6:$I$1505,'COOIS Data'!$B$6:$B$1505,C19) -> 39 | H19: =IF(E19=0,0,INT(G19/E19)) -> 13 | I19: =MAX(0,G19-F19) -> 0 | J19: =SUMIFS('COOIS Data'!$J$6:$J$1505,'COOIS Data'!$B$6:$B$1505,C19) -> 24 | K19: =IF(E19=0,0,INT(J19/E19)) -> 8 | L19: =SUMIFS('COOIS Data'!$K$6:$K$1505,'COOIS Data'!$B$6:$B$1505,C19) -> 20 | M19: =IF(E19=0,0,INT(L19/E19)) -> 6 | N19: =G19-L19 -> 19
B20: ='Kitting Plan'!A15 -> ERBIUM ASSY | C20: ='Kitting Plan'!B15 -> 92YRA03548AAA | D20: ='Kitting Plan'!C15 -> R5B ERBIUM ASSEMBLY POSITION 3 | E20: ='Kitting Plan'!D15 -> 3 | F20: ='Kitting Plan'!E15 -> 39 | G20: =SUMIFS('COOIS Data'!$I$6:$I$1505,'COOIS Data'!$B$6:$B$1505,C20) -> 42 | H20: =IF(E20=0,0,INT(G20/E20)) -> 14 | I20: =MAX(0,G20-F20) -> 3 | J20: =SUMIFS('COOIS Data'!$J$6:$J$1505,'COOIS Data'!$B$6:$B$1505,C20) -> 24 | K20: =IF(E20=0,0,INT(J20/E20)) -> 8 | L20: =SUMIFS('COOIS Data'!$K$6:$K$1505,'COOIS Data'!$B$6:$B$1505,C20) -> 20 | M20: =IF(E20=0,0,INT(L20/E20)) -> 6 | N20: =G20-L20 -> 22
B21: ='Kitting Plan'!A16 -> ERBIUM ASSY | C21: ='Kitting Plan'!B16 -> 92YRA04548AAA | D21: ='Kitting Plan'!C16 -> R5B ERBIUM ASSEMBLY POSITION 4 | E21: ='Kitting Plan'!D16 -> 3 | F21: ='Kitting Plan'!E16 -> 39 | G21: =SUMIFS('COOIS Data'!$I$6:$I$1505,'COOIS Data'!$B$6:$B$1505,C21) -> 39 | H21: =IF(E21=0,0,INT(G21/E21)) -> 13 | I21: =MAX(0,G21-F21) -> 0 | J21: =SUMIFS('COOIS Data'!$J$6:$J$1505,'COOIS Data'!$B$6:$B$1505,C21) -> 24 | K21: =IF(E21=0,0,INT(J21/E21)) -> 8 | L21: =SUMIFS('COOIS Data'!$K$6:$K$1505,'COOIS Data'!$B$6:$B$1505,C21) -> 20 | M21: =IF(E21=0,0,INT(L21/E21)) -> 6 | N21: =G21-L21 -> 19
B22: ='Kitting Plan'!A17 -> BOAT ASSY | C22: ='Kitting Plan'!B17 -> 92UAP04548BAA | D22: ='Kitting Plan'!C17 -> R5B BOAT 1 ASSY (4P-4FP) | E22: ='Kitting Plan'!D17 -> 1 | F22: ='Kitting Plan'!E17 -> 13 | G22: =SUMIFS('COOIS Data'!$I$6:$I$1505,'COOIS Data'!$B$6:$B$1505,C22) -> 13 | H22: =IF(E22=0,0,INT(G22/E22)) -> 13 | I22: =MAX(0,G22-F22) -> 0 | J22: =SUMIFS('COOIS Data'!$J$6:$J$1505,'COOIS Data'!$B$6:$B$1505,C22) -> 8 | K22: =IF(E22=0,0,INT(J22/E22)) -> 8 | L22: =SUMIFS('COOIS Data'!$K$6:$K$1505,'COOIS Data'!$B$6:$B$1505,C22) -> 5 | M22: =IF(E22=0,0,INT(L22/E22)) -> 5 | N22: =G22-L22 -> 8
... B24: ='Kitting Plan'!A19 -> BOAT ASSY | C24: ='Kitting Plan'!B19 -> 92UAP04548BCA | D24: ='Kitting Plan'!C19 -> R5B BOAT 3 ASSY (4P-4FP) | E24: ='Kitting Plan'!D19 -> 1 | F24: ='Kitting Plan'!E19 -> 13 | G24: =SUMIFS('COOIS Data'!$I$6:$I$1505,'COOIS Data'!$B$6:$B$1505,C24) -> 13 | H24: =IF(E24=0,0,INT(G24/E24)) -> 13 | I24: =MAX(0,G24-F24) -> 0 | J24: =SUMIFS('COOIS Data'!$J$6:$J$1505,'COOIS Data'!$B$6:$B$1505,C24) -> 7 | K24: =IF(E24=0,0,INT(J24/E24)) -> 7 | L24: =SUMIFS('COOIS Data'!$K$6:$K$1505,'COOIS Data'!$B$6:$B$1505,C24) -> 6 | M24: =IF(E24=0,0,INT(L24/E24)) -> 6 | N24: =G24-L24 -> 7
C25: TOTAL / MIN | D25: Rep kits / reps columns show the MIN — the limiting code | F25: =SUM(F11:F24) -> 663 | G25: =SUM(G11:G24) -> 691 | H25: =MIN(H11:H24) -> 13 | I25: =SUM(I11:I24) -> 28 | J25: =SUM(J11:J24) -> 440 | K25: =MIN(K11:K24) -> 7 | L25: =SUM(L11:L24) -> 414 | M25: =MIN(M11:M24) -> 5 | N25: =SUM(N11:N24) -> 277
B27: REPEATER KIT TRACKER | D27: WOs are assigned to repeaters in release order (oldest first). K = kitted · I = components issued · D = delivered · – = not kitted
B28: Sequence | C28: Assy Code | D28: Description | E28: Rep 1 | F28: Rep 2 | G28: Rep 3 | H28: Rep 4 | I28: Rep 5 | J28: Rep 6 | K28: Rep 7 | L28: Rep 8 | M28: Rep 9 | N28: Rep 10 | O28: Rep 11 | P28: Rep 12 | Q28: Rep 13
B29: =B11 -> LASER ASSY | C29: =C11 -> 92YLS00548BAA | D29: =D11 -> R5B LASER ASSEMBLY 4P BOAT 1 - E2A | E29: =IF(COUNTIFS('COOIS Data'!$B$6:$B$1505,$C29,'COOIS Data'!$N$6:$N$1505,1,'COOIS Data'!$I$6:$I$1505,">0")<$E11,"–",IF(COUNTIFS('COOIS Data'!$B$6:$B$1505,$C29,'COOIS Data'!$N$6:$N$1505,1,'COOIS Data'!$K$6:$K$1505,">0")>=$E11,"D",IF(COUNTIFS('COOIS Data'!$B$6:$B$1505,$C29,'COOIS Data'!$N$6:$N$1505,1,'COOIS Data'!$J$6:$J$1505,">0")>=$E11,"I","K"))) -> D | F29: =IF(COUNTIFS('COOIS Data'!$B$6:$B$1505,$C29,'COOIS Data'!$N$6:$N$1505,2,'COOIS Data'!$I$6:$I$1505,">0")<$E11,"–",IF(COUNTIFS('COOIS Data'!$B$6:$B$1505,$C29,'COOIS Data'!$N$6:$N$1505,2,'COOIS Data'!$K$6:$K$1505,">0")>=$E11,"D",IF(COUNTIFS('COOIS Data'!$B$6:$B$1505,$C29,'COOIS Data'!$N$6:$N$1505,2,'COOIS Data'!$J$6:$J$1505,">0")>=$E11,"I","K"))) -> D | G29: =IF(COUNTIFS('COOIS Data'!$B$6:$B$1505,$C29,'COOIS Data'!$N$6:$N$1505,3,'COOIS Data'!$I$6:$I$1505,">0")<$E11,"–",IF(COUNTIFS('COOIS Data'!$B$6:$B$1505,$C29,'COOIS Data'!$N$6:$N$1505,3,'COOIS Data'!$K$6:$K$1505,">0")>=$E11,"D",IF(COUNTIFS('COOIS Data'!$B$6:$B$1505,$C29,'COOIS Data'!$N$6:$N$1505,3,'COOIS Data'!$J$6:$J$1505,">0")>=$E11,"I","K"))) -> D | H29: =IF(COUNTIFS('COOIS Data'!$B$6:$B$1505,$C29,'COOIS Data'!$N$6:$N$1505,4,'COOIS Data'!$I$6:$I$1505,">0")<$E11,"–",IF(COUNTIFS('COOIS Data'!$B$6:$B$1505,$C29,'COOIS Data'!$N$6:$N$1505,4,'COOIS Data'!$K$6:$K$1505,">0")>=$E11,"D",IF(COUNTIFS('COOIS Data'!$B$6:$B$1505,$C29,'COOIS Data'!$N$6:$N$1505,4,'COOIS Data'!$J$6:$J$1505,">0")>=$E11,"I","K"))) -> D | I29: =IF(COUNTIFS('COOIS Data'!$B$6:$B$1505,$C29,'COOIS Data'!$N$6:$N$1505,5,'COOIS Data'!$I$6:$I$1505,">0")<$E11,"–",IF(COUNTIFS('COOIS Data'!$B$6:$B$1505,$C29,'COOIS Data'!$N$6:$N$1505,5,'COOIS Data'!$K$6:$K$1505,">0")>=$E11,"D",IF(COUNTIFS('COOIS Data'!$B$6:$B$1505,$C29,'COOIS Data'!$N$6:$N$1505,5,'COOIS Data'!$J$6:$J$1505,">0")>=$E11,"I","K"))) -> D | J29: =IF(COUNTIFS('COOIS Data'!$B$6:$B$1505,$C29,'COOIS Data'!$N$6:$N$1505,6,'COOIS Data'!$I$6:$I$1505,">0")<$E11,"–",IF(COUNTIFS('COOIS Data'!$B$6:$B$1505,$C29,'COOIS Data'!$N$6:$N$1505,6,'COOIS Data'!$K$6:$K$1505,">0")>=$E11,"D",IF(COUNTIFS('COOIS Data'!$B$6:$B$1505,$C29,'COOIS Data'!$N$6:$N$1505,6,'COOIS Data'!$J$6:$J$1505,">0")>=$E11,"I","K"))) -> D | K29: =IF(COUNTIFS('COOIS Data'!$B$6:$B$1505,$C29,'COOIS Data'!$N$6:$N$1505,7,'COOIS Data'!$I$6:$I$1505,">0")<$E11,"–",IF(COUNTIFS('COOIS Data'!$B$6:$B$1505,$C29,'COOIS Data'!$N$6:$N$1505,7,'COOIS Data'!$K$6:$K$1505,">0")>=$E11,"D",IF(COUNTIFS('COOIS Data'!$B$6:$B$1505,$C29,'COOIS Data'!$N$6:$N$1505,7,'COOIS Data'!$J$6:$J$1505,">0")>=$E11,"I","K"))) -> D | L29: =IF(COUNTIFS('COOIS Data'!$B$6:$B$1505,$C29,'COOIS Data'!$N$6:$N$1505,8,'COOIS Data'!$I$6:$I$1505,">0")<$E11,"–",IF(COUNTIFS('COOIS Data'!$B$6:$B$1505,$C29,'COOIS Data'!$N$6:$N$1505,8,'COOIS Data'!$K$6:$K$1505,">0")>=$E11,"D",IF(COUNTIFS('COOIS Data'!$B$6:$B$1505,$C29,'COOIS Data'!$N$6:$N$1505,8,'COOIS Data'!$J$6:$J$1505,">0")>=$E11,"I","K"))) -> D | M29: =IF(COUNTIFS('COOIS Data'!$B$6:$B$1505,$C29,'COOIS Data'!$N$6:$N$1505,9,'COOIS Data'!$I$6:$I$1505,">0")<$E11,"–",IF(COUNTIFS('COOIS Data'!$B$6:$B$1505,$C29,'COOIS Data'!$N$6:$N$1505,9,'COOIS Data'!$K$6:$K$1505,">0")>=$E11,"D",IF(COUNTIFS('COOIS Data'!$B$6:$B$1505,$C29,'COOIS Data'!$N$6:$N$1505,9,'COOIS Data'!$J$6:$J$1505,">0")>=$E11,"I","K"))) -> D | N29: =IF(COUNTIFS('COOIS Data'!$B$6:$B$1505,$C29,'COOIS Data'!$N$6:$N$1505,10,'COOIS Data'!$I$6:$I$1505,">0")<$E11,"–",IF(COUNTIFS('COOIS Data'!$B$6:$B$1505,$C29,'COOIS Data'!$N$6:$N$1505,10,'COOIS Data'!$K$6:$K$1505,">0")>=$E11,"D",IF(COUNTIFS('COOIS Data'!$B$6:$B$1505,$C29,'COOIS Data'!$N$6:$N$1505,10,'COOIS Data'!$J$6:$J$1505,">0")>=$E11,"I","K"))) -> I | O29: =IF(COUNTIFS('COOIS Data'!$B$6:$B$1505,$C29,'COOIS Data'!$N$6:$N$1505,11,'COOIS Data'!$I$6:$I$1505,">0")<$E11,"–",IF(COUNTIFS('COOIS Data'!$B$6:$B$1505,$C29,'COOIS Data'!$N$6:$N$1505,11,'COOIS Data'!$K$6:$K$1505,">0")>=$E11,"D",IF(COUNTIFS('COOIS Data'!$B$6:$B$1505,$C29,'COOIS Data'!$N$6:$N$1505,11,'COOIS Data'!$J$6:$J$1505,">0")>=$E11,"I","K"))) -> K | P29: =IF(COUNTIFS('COOIS Data'!$B$6:$B$1505,$C29,'COOIS Data'!$N$6:$N$1505,12,'COOIS Data'!$I$6:$I$1505,">0")<$E11,"–",IF(COUNTIFS('COOIS Data'!$B$6:$B$1505,$C29,'COOIS Data'!$N$6:$N$1505,12,'COOIS Data'!$K$6:$K$1505,">0")>=$E11,"D",IF(COUNTIFS('COOIS Data'!$B$6:$B$1505,$C29,'COOIS Data'!$N$6:$N$1505,12,'COOIS Data'!$J$6:$J$1505,">0")>=$E11,"I","K"))) -> K | Q29: =IF(COUNTIFS('COOIS Data'!$B$6:$B$1505,$C29,'COOIS Data'!$N$6:$N$1505,13,'COOIS Data'!$I$6:$I$1505,">0")<$E11,"–",IF(COUNTIFS('COOIS Data'!$B$6:$B$1505,$C29,'COOIS Data'!$N$6:$N$1505,13,'COOIS Data'!$K$6:$K$1505,">0")>=$E11,"D",IF(COUNTIFS('COOIS Data'!$B$6:$B$1505,$C29,'COOIS Data'!$N$6:$N$1505,13,'COOIS Data'!$J$6:$J$1505,">0")>=$E11,"I","K"))) -> K
B30: =B12 -> LASER ASSY | C30: =C12 -> 92YLS00548BBA | D30: =D12 -> R5B LASER ASSEMBLY 4P BOAT 2/3 - E2A | E30: =IF(COUNTIFS('COOIS Data'!$B$6:$B$1505,$C30,'COOIS Data'!$N$6:$N$1505,1,'COOIS Data'!$I$6:$I$1505,">0")<$E12,"–",IF(COUNTIFS('COOIS Data'!$B$6:$B$1505,$C30,'COOIS Data'!$N$6:$N$1505,1,'COOIS Data'!$K$6:$K$1505,">0")>=$E12,"D",IF(COUNTIFS('COOIS Data'!$B$6:$B$1505,$C30,'COOIS Data'!$N$6:$N$1505,1,'COOIS Data'!$J$6:$J$1505,">0")>=$E12,"I","K"))) -> D | F30: =IF(COUNTIFS('COOIS Data'!$B$6:$B$1505,$C30,'COOIS Data'!$N$6:$N$1505,2,'COOIS Data'!$I$6:$I$1505,">0")<$E12,"–",IF(COUNTIFS('COOIS Data'!$B$6:$B$1505,$C30,'COOIS Data'!$N$6:$N$1505,2,'COOIS Data'!$K$6:$K$1505,">0")>=$E12,"D",IF(COUNTIFS('COOIS Data'!$B$6:$B$1505,$C30,'COOIS Data'!$N$6:$N$1505,2,'COOIS Data'!$J$6:$J$1505,">0")>=$E12,"I","K"))) -> D | G30: =IF(COUNTIFS('COOIS Data'!$B$6:$B$1505,$C30,'COOIS Data'!$N$6:$N$1505,3,'COOIS Data'!$I$6:$I$1505,">0")<$E12,"–",IF(COUNTIFS('COOIS Data'!$B$6:$B$1505,$C30,'COOIS Data'!$N$6:$N$1505,3,'COOIS Data'!$K$6:$K$1505,">0")>=$E12,"D",IF(COUNTIFS('COOIS Data'!$B$6:$B$1505,$C30,'COOIS Data'!$N$6:$N$1505,3,'COOIS Data'!$J$6:$J$1505,">0")>=$E12,"I","K"))) -> D | H30: =IF(COUNTIFS('COOIS Data'!$B$6:$B$1505,$C30,'COOIS Data'!$N$6:$N$1505,4,'COOIS Data'!$I$6:$I$1505,">0")<$E12,"–",IF(COUNTIFS('COOIS Data'!$B$6:$B$1505,$C30,'COOIS Data'!$N$6:$N$1505,4,'COOIS Data'!$K$6:$K$1505,">0")>=$E12,"D",IF(COUNTIFS('COOIS Data'!$B$6:$B$1505,$C30,'COOIS Data'!$N$6:$N$1505,4,'COOIS Data'!$J$6:$J$1505,">0")>=$E12,"I","K"))) -> D | I30: =IF(COUNTIFS('COOIS Data'!$B$6:$B$1505,$C30,'COOIS Data'!$N$6:$N$1505,5,'COOIS Data'!$I$6:$I$1505,">0")<$E12,"–",IF(COUNTIFS('COOIS Data'!$B$6:$B$1505,$C30,'COOIS Data'!$N$6:$N$1505,5,'COOIS Data'!$K$6:$K$1505,">0")>=$E12,"D",IF(COUNTIFS('COOIS Data'!$B$6:$B$1505,$C30,'COOIS Data'!$N$6:$N$1505,5,'COOIS Data'!$J$6:$J$1505,">0")>=$E12,"I","K"))) -> D | J30: =IF(COUNTIFS('COOIS Data'!$B$6:$B$1505,$C30,'COOIS Data'!$N$6:$N$1505,6,'COOIS Data'!$I$6:$I$1505,">0")<$E12,"–",IF(COUNTIFS('COOIS Data'!$B$6:$B$1505,$C30,'COOIS Data'!$N$6:$N$1505,6,'COOIS Data'!$K$6:$K$1505,">0")>=$E12,"D",IF(COUNTIFS('COOIS Data'!$B$6:$B$1505,$C30,'COOIS Data'!$N$6:$N$1505,6,'COOIS Data'!$J$6:$J$1505,">0")>=$E12,"I","K"))) -> D | K30: =IF(COUNTIFS('COOIS Data'!$B$6:$B$1505,$C30,'COOIS Data'!$N$6:$N$1505,7,'COOIS Data'!$I$6:$I$1505,">0")<$E12,"–",IF(COUNTIFS('COOIS Data'!$B$6:$B$1505,$C30,'COOIS Data'!$N$6:$N$1505,7,'COOIS Data'!$K$6:$K$1505,">0")>=$E12,"D",IF(COUNTIFS('COOIS Data'!$B$6:$B$1505,$C30,'COOIS Data'!$N$6:$N$1505,7,'COOIS Data'!$J$6:$J$1505,">0")>=$E12,"I","K"))) -> D | L30: =IF(COUNTIFS('COOIS Data'!$B$6:$B$1505,$C30,'COOIS Data'!$N$6:$N$1505,8,'COOIS Data'!$I$6:$I$1505,">0")<$E12,"–",IF(COUNTIFS('COOIS Data'!$B$6:$B$1505,$C30,'COOIS Data'!$N$6:$N$1505,8,'COOIS Data'!$K$6:$K$1505,">0")>=$E12,"D",IF(COUNTIFS('COOIS Data'!$B$6:$B$1505,$C30,'COOIS Data'!$N$6:$N$1505,8,'COOIS Data'!$J$6:$J$1505,">0")>=$E12,"I","K"))) -> D | M30: =IF(COUNTIFS('COOIS Data'!$B$6:$B$1505,$C30,'COOIS Data'!$N$6:$N$1505,9,'COOIS Data'!$I$6:$I$1505,">0")<$E12,"–",IF(COUNTIFS('COOIS Data'!$B$6:$B$1505,$C30,'COOIS Data'!$N$6:$N$1505,9,'COOIS Data'!$K$6:$K$1505,">0")>=$E12,"D",IF(COUNTIFS('COOIS Data'!$B$6:$B$1505,$C30,'COOIS Data'!$N$6:$N$1505,9,'COOIS Data'!$J$6:$J$1505,">0")>=$E12,"I","K"))) -> I | N30: =IF(COUNTIFS('COOIS Data'!$B$6:$B$1505,$C30,'COOIS Data'!$N$6:$N$1505,10,'COOIS Data'!$I$6:$I$1505,">0")<$E12,"–",IF(COUNTIFS('COOIS Data'!$B$6:$B$1505,$C30,'COOIS Data'!$N$6:$N$1505,10,'COOIS Data'!$K$6:$K$1505,">0")>=$E12,"D",IF(COUNTIFS('COOIS Data'!$B$6:$B$1505,$C30,'COOIS Data'!$N$6:$N$1505,10,'COOIS Data'!$J$6:$J$1505,">0")>=$E12,"I","K"))) -> K | O30: =IF(COUNTIFS('COOIS Data'!$B$6:$B$1505,$C30,'COOIS Data'!$N$6:$N$1505,11,'COOIS Data'!$I$6:$I$1505,">0")<$E12,"–",IF(COUNTIFS('COOIS Data'!$B$6:$B$1505,$C30,'COOIS Data'!$N$6:$N$1505,11,'COOIS Data'!$K$6:$K$1505,">0")>=$E12,"D",IF(COUNTIFS('COOIS Data'!$B$6:$B$1505,$C30,'COOIS Data'!$N$6:$N$1505,11,'COOIS Data'!$J$6:$J$1505,">0")>=$E12,"I","K"))) -> K | P30: =IF(COUNTIFS('COOIS Data'!$B$6:$B$1505,$C30,'COOIS Data'!$N$6:$N$1505,12,'COOIS Data'!$I$6:$I$1505,">0")<$E12,"–",IF(COUNTIFS('COOIS Data'!$B$6:$B$1505,$C30,'COOIS Data'!$N$6:$N$1505,12,'COOIS Data'!$K$6:$K$1505,">0")>=$E12,"D",IF(COUNTIFS('COOIS Data'!$B$6:$B$1505,$C30,'COOIS Data'!$N$6:$N$1505,12,'COOIS Data'!$J$6:$J$1505,">0")>=$E12,"I","K"))) -> K | Q30: =IF(COUNTIFS('COOIS Data'!$B$6:$B$1505,$C30,'COOIS Data'!$N$6:$N$1505,13,'COOIS Data'!$I$6:$I$1505,">0")<$E12,"–",IF(COUNTIFS('COOIS Data'!$B$6:$B$1505,$C30,'COOIS Data'!$N$6:$N$1505,13,'COOIS Data'!$K$6:$K$1505,">0")>=$E12,"D",IF(COUNTIFS('COOIS Data'!$B$6:$B$1505,$C30,'COOIS Data'!$N$6:$N$1505,13,'COOIS Data'!$J$6:$J$1505,">0")>=$E12,"I","K"))) -> K
B31: =B13 -> PSB ASSY | C31: =C13 -> 91YAF03404AAA | D31: =D13 -> R5B PSB SUB ASSEMBLY 4P-4FP | E31: =IF(COUNTIFS('COOIS Data'!$B$6:$B$1505,$C31,'COOIS Data'!$N$6:$N$1505,1,'COOIS Data'!$I$6:$I$1505,">0")<$E13,"–",IF(COUNTIFS('COOIS Data'!$B$6:$B$1505,$C31,'COOIS Data'!$N$6:$N$1505,1,'COOIS Data'!$K$6:$K$1505,">0")>=$E13,"D",IF(COUNTIFS('COOIS Data'!$B$6:$B$1505,$C31,'COOIS Data'!$N$6:$N$1505,1,'COOIS Data'!$J$6:$J$1505,">0")>=$E13,"I","K"))) -> D | F31: =IF(COUNTIFS('COOIS Data'!$B$6:$B$1505,$C31,'COOIS Data'!$N$6:$N$1505,2,'COOIS Data'!$I$6:$I$1505,">0")<$E13,"–",IF(COUNTIFS('COOIS Data'!$B$6:$B$1505,$C31,'COOIS Data'!$N$6:$N$1505,2,'COOIS Data'!$K$6:$K$1505,">0")>=$E13,"D",IF(COUNTIFS('COOIS Data'!$B$6:$B$1505,$C31,'COOIS Data'!$N$6:$N$1505,2,'COOIS Data'!$J$6:$J$1505,">0")>=$E13,"I","K"))) -> D | G31: =IF(COUNTIFS('COOIS Data'!$B$6:$B$1505,$C31,'COOIS Data'!$N$6:$N$1505,3,'COOIS Data'!$I$6:$I$1505,">0")<$E13,"–",IF(COUNTIFS('COOIS Data'!$B$6:$B$1505,$C31,'COOIS Data'!$N$6:$N$1505,3,'COOIS Data'!$K$6:$K$1505,">0")>=$E13,"D",IF(COUNTIFS('COOIS Data'!$B$6:$B$1505,$C31,'COOIS Data'!$N$6:$N$1505,3,'COOIS Data'!$J$6:$J$1505,">0")>=$E13,"I","K"))) -> D | H31: =IF(COUNTIFS('COOIS Data'!$B$6:$B$1505,$C31,'COOIS Data'!$N$6:$N$1505,4,'COOIS Data'!$I$6:$I$1505,">0")<$E13,"–",IF(COUNTIFS('COOIS Data'!$B$6:$B$1505,$C31,'COOIS Data'!$N$6:$N$1505,4,'COOIS Data'!$K$6:$K$1505,">0")>=$E13,"D",IF(COUNTIFS('COOIS Data'!$B$6:$B$1505,$C31,'COOIS Data'!$N$6:$N$1505,4,'COOIS Data'!$J$6:$J$1505,">0")>=$E13,"I","K"))) -> D | I31: =IF(COUNTIFS('COOIS Data'!$B$6:$B$1505,$C31,'COOIS Data'!$N$6:$N$1505,5,'COOIS Data'!$I$6:$I$1505,">0")<$E13,"–",IF(COUNTIFS('COOIS Data'!$B$6:$B$1505,$C31,'COOIS Data'!$N$6:$N$1505,5,'COOIS Data'!$K$6:$K$1505,">0")>=$E13,"D",IF(COUNTIFS('COOIS Data'!$B$6:$B$1505,$C31,'COOIS Data'!$N$6:$N$1505,5,'COOIS Data'!$J$6:$J$1505,">0")>=$E13,"I","K"))) -> D | J31: =IF(COUNTIFS('COOIS Data'!$B$6:$B$1505,$C31,'COOIS Data'!$N$6:$N$1505,6,'COOIS Data'!$I$6:$I$1505,">0")<$E13,"–",IF(COUNTIFS('COOIS Data'!$B$6:$B$1505,$C31,'COOIS Data'!$N$6:$N$1505,6,'COOIS Data'!$K$6:$K$1505,">0")>=$E13,"D",IF(COUNTIFS('COOIS Data'!$B$6:$B$1505,$C31,'COOIS Data'!$N$6:$N$1505,6,'COOIS Data'!$J$6:$J$1505,">0")>=$E13,"I","K"))) -> D | K31: =IF(COUNTIFS('COOIS Data'!$B$6:$B$1505,$C31,'COOIS Data'!$N$6:$N$1505,7,'COOIS Data'!$I$6:$I$1505,">0")<$E13,"–",IF(COUNTIFS('COOIS Data'!$B$6:$B$1505,$C31,'COOIS Data'!$N$6:$N$1505,7,'COOIS Data'!$K$6:$K$1505,">0")>=$E13,"D",IF(COUNTIFS('COOIS Data'!$B$6:$B$1505,$C31,'COOIS Data'!$N$6:$N$1505,7,'COOIS Data'!$J$6:$J$1505,">0")>=$E13,"I","K"))) -> D | L31: =IF(COUNTIFS('COOIS Data'!$B$6:$B$1505,$C31,'COOIS Data'!$N$6:$N$1505,8,'COOIS Data'!$I$6:$I$1505,">0")<$E13,"–",IF(COUNTIFS('COOIS Data'!$B$6:$B$1505,$C31,'COOIS Data'!$N$6:$N$1505,8,'COOIS Data'!$K$6:$K$1505,">0")>=$E13,"D",IF(COUNTIFS('COOIS Data'!$B$6:$B$1505,$C31,'COOIS Data'!$N$6:$N$1505,8,'COOIS Data'!$J$6:$J$1505,">0")>=$E13,"I","K"))) -> D | M31: =IF(COUNTIFS('COOIS Data'!$B$6:$B$1505,$C31,'COOIS Data'!$N$6:$N$1505,9,'COOIS Data'!$I$6:$I$1505,">0")<$E13,"–",IF(COUNTIFS('COOIS Data'!$B$6:$B$1505,$C31,'COOIS Data'!$N$6:$N$1505,9,'COOIS Data'!$K$6:$K$1505,">0")>=$E13,"D",IF(COUNTIFS('COOIS Data'!$B$6:$B$1505,$C31,'COOIS Data'!$N$6:$N$1505,9,'COOIS Data'!$J$6:$J$1505,">0")>=$E13,"I","K"))) -> D | N31: =IF(COUNTIFS('COOIS Data'!$B$6:$B$1505,$C31,'COOIS Data'!$N$6:$N$1505,10,'COOIS Data'!$I$6:$I$1505,">0")<$E13,"–",IF(COUNTIFS('COOIS Data'!$B$6:$B$1505,$C31,'COOIS Data'!$N$6:$N$1505,10,'COOIS Data'!$K$6:$K$1505,">0")>=$E13,"D",IF(COUNTIFS('COOIS Data'!$B$6:$B$1505,$C31,'COOIS Data'!$N$6:$N$1505,10,'COOIS Data'!$J$6:$J$1505,">0")>=$E13,"I","K"))) -> D | O31: =IF(COUNTIFS('COOIS Data'!$B$6:$B$1505,$C31,'COOIS Data'!$N$6:$N$1505,11,'COOIS Data'!$I$6:$I$1505,">0")<$E13,"–",IF(COUNTIFS('COOIS Data'!$B$6:$B$1505,$C31,'COOIS Data'!$N$6:$N$1505,11,'COOIS Data'!$K$6:$K$1505,">0")>=$E13,"D",IF(COUNTIFS('COOIS Data'!$B$6:$B$1505,$C31,'COOIS Data'!$N$6:$N$1505,11,'COOIS Data'!$J$6:$J$1505,">0")>=$E13,"I","K"))) -> K | P31: =IF(COUNTIFS('COOIS Data'!$B$6:$B$1505,$C31,'COOIS Data'!$N$6:$N$1505,12,'COOIS Data'!$I$6:$I$1505,">0")<$E13,"–",IF(COUNTIFS('COOIS Data'!$B$6:$B$1505,$C31,'COOIS Data'!$N$6:$N$1505,12,'COOIS Data'!$K$6:$K$1505,">0")>=$E13,"D",IF(COUNTIFS('COOIS Data'!$B$6:$B$1505,$C31,'COOIS Data'!$N$6:$N$1505,12,'COOIS Data'!$J$6:$J$1505,">0")>=$E13,"I","K"))) -> K | Q31: =IF(COUNTIFS('COOIS Data'!$B$6:$B$1505,$C31,'COOIS Data'!$N$6:$N$1505,13,'COOIS Data'!$I$6:$I$1505,">0")<$E13,"–",IF(COUNTIFS('COOIS Data'!$B$6:$B$1505,$C31,'COOIS Data'!$N$6:$N$1505,13,'COOIS Data'!$K$6:$K$1505,">0")>=$E13,"D",IF(COUNTIFS('COOIS Data'!$B$6:$B$1505,$C31,'COOIS Data'!$N$6:$N$1505,13,'COOIS Data'!$J$6:$J$1505,">0")>=$E13,"I","K"))) -> D
B32: =B14 -> OPF ASSY | C32: =C14 -> 92YFD04548BAA | D32: =D14 -> R5B OPF ASSEMBLY (4P-4FP) BOAT 1 - E2A | E32: =IF(COUNTIFS('COOIS Data'!$B$6:$B$1505,$C32,'COOIS Data'!$N$6:$N$1505,1,'COOIS Data'!$I$6:$I$1505,">0")<$E14,"–",IF(COUNTIFS('COOIS Data'!$B$6:$B$1505,$C32,'COOIS Data'!$N$6:$N$1505,1,'COOIS Data'!$K$6:$K$1505,">0")>=$E14,"D",IF(COUNTIFS('COOIS Data'!$B$6:$B$1505,$C32,'COOIS Data'!$N$6:$N$1505,1,'COOIS Data'!$J$6:$J$1505,">0")>=$E14,"I","K"))) -> D | F32: =IF(COUNTIFS('COOIS Data'!$B$6:$B$1505,$C32,'COOIS Data'!$N$6:$N$1505,2,'COOIS Data'!$I$6:$I$1505,">0")<$E14,"–",IF(COUNTIFS('COOIS Data'!$B$6:$B$1505,$C32,'COOIS Data'!$N$6:$N$1505,2,'COOIS Data'!$K$6:$K$1505,">0")>=$E14,"D",IF(COUNTIFS('COOIS Data'!$B$6:$B$1505,$C32,'COOIS Data'!$N$6:$N$1505,2,'COOIS Data'!$J$6:$J$1505,">0")>=$E14,"I","K"))) -> D | G32: =IF(COUNTIFS('COOIS Data'!$B$6:$B$1505,$C32,'COOIS Data'!$N$6:$N$1505,3,'COOIS Data'!$I$6:$I$1505,">0")<$E14,"–",IF(COUNTIFS('COOIS Data'!$B$6:$B$1505,$C32,'COOIS Data'!$N$6:$N$1505,3,'COOIS Data'!$K$6:$K$1505,">0")>=$E14,"D",IF(COUNTIFS('COOIS Data'!$B$6:$B$1505,$C32,'COOIS Data'!$N$6:$N$1505,3,'COOIS Data'!$J$6:$J$1505,">0")>=$E14,"I","K"))) -> D | H32: =IF(COUNTIFS('COOIS Data'!$B$6:$B$1505,$C32,'COOIS Data'!$N$6:$N$1505,4,'COOIS Data'!$I$6:$I$1505,">0")<$E14,"–",IF(COUNTIFS('COOIS Data'!$B$6:$B$1505,$C32,'COOIS Data'!$N$6:$N$1505,4,'COOIS Data'!$K$6:$K$1505,">0")>=$E14,"D",IF(COUNTIFS('COOIS Data'!$B$6:$B$1505,$C32,'COOIS Data'!$N$6:$N$1505,4,'COOIS Data'!$J$6:$J$1505,">0")>=$E14,"I","K"))) -> D | I32: =IF(COUNTIFS('COOIS Data'!$B$6:$B$1505,$C32,'COOIS Data'!$N$6:$N$1505,5,'COOIS Data'!$I$6:$I$1505,">0")<$E14,"–",IF(COUNTIFS('COOIS Data'!$B$6:$B$1505,$C32,'COOIS Data'!$N$6:$N$1505,5,'COOIS Data'!$K$6:$K$1505,">0")>=$E14,"D",IF(COUNTIFS('COOIS Data'!$B$6:$B$1505,$C32,'COOIS Data'!$N$6:$N$1505,5,'COOIS Data'!$J$6:$J$1505,">0")>=$E14,"I","K"))) -> D | J32: =IF(COUNTIFS('COOIS Data'!$B$6:$B$1505,$C32,'COOIS Data'!$N$6:$N$1505,6,'COOIS Data'!$I$6:$I$1505,">0")<$E14,"–",IF(COUNTIFS('COOIS Data'!$B$6:$B$1505,$C32,'COOIS Data'!$N$6:$N$1505,6,'COOIS Data'!$K$6:$K$1505,">0")>=$E14,"D",IF(COUNTIFS('COOIS Data'!$B$6:$B$1505,$C32,'COOIS Data'!$N$6:$N$1505,6,'COOIS Data'!$J$6:$J$1505,">0")>=$E14,"I","K"))) -> D | K32: =IF(COUNTIFS('COOIS Data'!$B$6:$B$1505,$C32,'COOIS Data'!$N$6:$N$1505,7,'COOIS Data'!$I$6:$I$1505,">0")<$E14,"–",IF(COUNTIFS('COOIS Data'!$B$6:$B$1505,$C32,'COOIS Data'!$N$6:$N$1505,7,'COOIS Data'!$K$6:$K$1505,">0")>=$E14,"D",IF(COUNTIFS('COOIS Data'!$B$6:$B$1505,$C32,'COOIS Data'!$N$6:$N$1505,7,'COOIS Data'!$J$6:$J$1505,">0")>=$E14,"I","K"))) -> D | L32: =IF(COUNTIFS('COOIS Data'!$B$6:$B$1505,$C32,'COOIS Data'!$N$6:$N$1505,8,'COOIS Data'!$I$6:$I$1505,">0")<$E14,"–",IF(COUNTIFS('COOIS Data'!$B$6:$B$1505,$C32,'COOIS Data'!$N$6:$N$1505,8,'COOIS Data'!$K$6:$K$1505,">0")>=$E14,"D",IF(COUNTIFS('COOIS Data'!$B$6:$B$1505,$C32,'COOIS Data'!$N$6:$N$1505,8,'COOIS Data'!$J$6:$J$1505,">0")>=$E14,"I","K"))) -> D | M32: =IF(COUNTIFS('COOIS Data'!$B$6:$B$1505,$C32,'COOIS Data'!$N$6:$N$1505,9,'COOIS Data'!$I$6:$I$1505,">0")<$E14,"–",IF(COUNTIFS('COOIS Data'!$B$6:$B$1505,$C32,'COOIS Data'!$N$6:$N$1505,9,'COOIS Data'!$K$6:$K$1505,">0")>=$E14,"D",IF(COUNTIFS('COOIS Data'!$B$6:$B$1505,$C32,'COOIS Data'!$N$6:$N$1505,9,'COOIS Data'!$J$6:$J$1505,">0")>=$E14,"I","K"))) -> I | N32: =IF(COUNTIFS('COOIS Data'!$B$6:$B$1505,$C32,'COOIS Data'!$N$6:$N$1505,10,'COOIS Data'!$I$6:$I$1505,">0")<$E14,"–",IF(COUNTIFS('COOIS Data'!$B$6:$B$1505,$C32,'COOIS Data'!$N$6:$N$1505,10,'COOIS Data'!$K$6:$K$1505,">0")>=$E14,"D",IF(COUNTIFS('COOIS Data'!$B$6:$B$1505,$C32,'COOIS Data'!$N$6:$N$1505,10,'COOIS Data'!$J$6:$J$1505,">0")>=$E14,"I","K"))) -> K | O32: =IF(COUNTIFS('COOIS Data'!$B$6:$B$1505,$C32,'COOIS Data'!$N$6:$N$1505,11,'COOIS Data'!$I$6:$I$1505,">0")<$E14,"–",IF(COUNTIFS('COOIS Data'!$B$6:$B$1505,$C32,'COOIS Data'!$N$6:$N$1505,11,'COOIS Data'!$K$6:$K$1505,">0")>=$E14,"D",IF(COUNTIFS('COOIS Data'!$B$6:$B$1505,$C32,'COOIS Data'!$N$6:$N$1505,11,'COOIS Data'!$J$6:$J$1505,">0")>=$E14,"I","K"))) -> K | P32: =IF(COUNTIFS('COOIS Data'!$B$6:$B$1505,$C32,'COOIS Data'!$N$6:$N$1505,12,'COOIS Data'!$I$6:$I$1505,">0")<$E14,"–",IF(COUNTIFS('COOIS Data'!$B$6:$B$1505,$C32,'COOIS Data'!$N$6:$N$1505,12,'COOIS Data'!$K$6:$K$1505,">0")>=$E14,"D",IF(COUNTIFS('COOIS Data'!$B$6:$B$1505,$C32,'COOIS Data'!$N$6:$N$1505,12,'COOIS Data'!$J$6:$J$1505,">0")>=$E14,"I","K"))) -> K | Q32: =IF(COUNTIFS('COOIS Data'!$B$6:$B$1505,$C32,'COOIS Data'!$N$6:$N$1505,13,'COOIS Data'!$I$6:$I$1505,">0")<$E14,"–",IF(COUNTIFS('COOIS Data'!$B$6:$B$1505,$C32,'COOIS Data'!$N$6:$N$1505,13,'COOIS Data'!$K$6:$K$1505,">0")>=$E14,"D",IF(COUNTIFS('COOIS Data'!$B$6:$B$1505,$C32,'COOIS Data'!$N$6:$N$1505,13,'COOIS Data'!$J$6:$J$1505,">0")>=$E14,"I","K"))) -> K
B33: =B15 -> OPF ASSY | C33: =C15 -> 92YFD04548BBA | D33: =D15 -> R5B OPF ASSEMBLY (4P-4FP) BOAT 2/3 - E2A | E33: =IF(COUNTIFS('COOIS Data'!$B$6:$B$1505,$C33,'COOIS Data'!$N$6:$N$1505,1,'COOIS Data'!$I$6:$I$1505,">0")<$E15,"–",IF(COUNTIFS('COOIS Data'!$B$6:$B$1505,$C33,'COOIS Data'!$N$6:$N$1505,1,'COOIS Data'!$K$6:$K$1505,">0")>=$E15,"D",IF(COUNTIFS('COOIS Data'!$B$6:$B$1505,$C33,'COOIS Data'!$N$6:$N$1505,1,'COOIS Data'!$J$6:$J$1505,">0")>=$E15,"I","K"))) -> D | F33: =IF(COUNTIFS('COOIS Data'!$B$6:$B$1505,$C33,'COOIS Data'!$N$6:$N$1505,2,'COOIS Data'!$I$6:$I$1505,">0")<$E15,"–",IF(COUNTIFS('COOIS Data'!$B$6:$B$1505,$C33,'COOIS Data'!$N$6:$N$1505,2,'COOIS Data'!$K$6:$K$1505,">0")>=$E15,"D",IF(COUNTIFS('COOIS Data'!$B$6:$B$1505,$C33,'COOIS Data'!$N$6:$N$1505,2,'COOIS Data'!$J$6:$J$1505,">0")>=$E15,"I","K"))) -> D | G33: =IF(COUNTIFS('COOIS Data'!$B$6:$B$1505,$C33,'COOIS Data'!$N$6:$N$1505,3,'COOIS Data'!$I$6:$I$1505,">0")<$E15,"–",IF(COUNTIFS('COOIS Data'!$B$6:$B$1505,$C33,'COOIS Data'!$N$6:$N$1505,3,'COOIS Data'!$K$6:$K$1505,">0")>=$E15,"D",IF(COUNTIFS('COOIS Data'!$B$6:$B$1505,$C33,'COOIS Data'!$N$6:$N$1505,3,'COOIS Data'!$J$6:$J$1505,">0")>=$E15,"I","K"))) -> D | H33: =IF(COUNTIFS('COOIS Data'!$B$6:$B$1505,$C33,'COOIS Data'!$N$6:$N$1505,4,'COOIS Data'!$I$6:$I$1505,">0")<$E15,"–",IF(COUNTIFS('COOIS Data'!$B$6:$B$1505,$C33,'COOIS Data'!$N$6:$N$1505,4,'COOIS Data'!$K$6:$K$1505,">0")>=$E15,"D",IF(COUNTIFS('COOIS Data'!$B$6:$B$1505,$C33,'COOIS Data'!$N$6:$N$1505,4,'COOIS Data'!$J$6:$J$1505,">0")>=$E15,"I","K"))) -> D | I33: =IF(COUNTIFS('COOIS Data'!$B$6:$B$1505,$C33,'COOIS Data'!$N$6:$N$1505,5,'COOIS Data'!$I$6:$I$1505,">0")<$E15,"–",IF(COUNTIFS('COOIS Data'!$B$6:$B$1505,$C33,'COOIS Data'!$N$6:$N$1505,5,'COOIS Data'!$K$6:$K$1505,">0")>=$E15,"D",IF(COUNTIFS('COOIS Data'!$B$6:$B$1505,$C33,'COOIS Data'!$N$6:$N$1505,5,'COOIS Data'!$J$6:$J$1505,">0")>=$E15,"I","K"))) -> D | J33: =IF(COUNTIFS('COOIS Data'!$B$6:$B$1505,$C33,'COOIS Data'!$N$6:$N$1505,6,'COOIS Data'!$I$6:$I$1505,">0")<$E15,"–",IF(COUNTIFS('COOIS Data'!$B$6:$B$1505,$C33,'COOIS Data'!$N$6:$N$1505,6,'COOIS Data'!$K$6:$K$1505,">0")>=$E15,"D",IF(COUNTIFS('COOIS Data'!$B$6:$B$1505,$C33,'COOIS Data'!$N$6:$N$1505,6,'COOIS Data'!$J$6:$J$1505,">0")>=$E15,"I","K"))) -> D | K33: =IF(COUNTIFS('COOIS Data'!$B$6:$B$1505,$C33,'COOIS Data'!$N$6:$N$1505,7,'COOIS Data'!$I$6:$I$1505,">0")<$E15,"–",IF(COUNTIFS('COOIS Data'!$B$6:$B$1505,$C33,'COOIS Data'!$N$6:$N$1505,7,'COOIS Data'!$K$6:$K$1505,">0")>=$E15,"D",IF(COUNTIFS('COOIS Data'!$B$6:$B$1505,$C33,'COOIS Data'!$N$6:$N$1505,7,'COOIS Data'!$J$6:$J$1505,">0")>=$E15,"I","K"))) -> D | L33: =IF(COUNTIFS('COOIS Data'!$B$6:$B$1505,$C33,'COOIS Data'!$N$6:$N$1505,8,'COOIS Data'!$I$6:$I$1505,">0")<$E15,"–",IF(COUNTIFS('COOIS Data'!$B$6:$B$1505,$C33,'COOIS Data'!$N$6:$N$1505,8,'COOIS Data'!$K$6:$K$1505,">0")>=$E15,"D",IF(COUNTIFS('COOIS Data'!$B$6:$B$1505,$C33,'COOIS Data'!$N$6:$N$1505,8,'COOIS Data'!$J$6:$J$1505,">0")>=$E15,"I","K"))) -> I | M33: =IF(COUNTIFS('COOIS Data'!$B$6:$B$1505,$C33,'COOIS Data'!$N$6:$N$1505,9,'COOIS Data'!$I$6:$I$1505,">0")<$E15,"–",IF(COUNTIFS('COOIS Data'!$B$6:$B$1505,$C33,'COOIS Data'!$N$6:$N$1505,9,'COOIS Data'!$K$6:$K$1505,">0")>=$E15,"D",IF(COUNTIFS('COOIS Data'!$B$6:$B$1505,$C33,'COOIS Data'!$N$6:$N$1505,9,'COOIS Data'!$J$6:$J$1505,">0")>=$E15,"I","K"))) -> K | N33: =IF(COUNTIFS('COOIS Data'!$B$6:$B$1505,$C33,'COOIS Data'!$N$6:$N$1505,10,'COOIS Data'!$I$6:$I$1505,">0")<$E15,"–",IF(COUNTIFS('COOIS Data'!$B$6:$B$1505,$C33,'COOIS Data'!$N$6:$N$1505,10,'COOIS Data'!$K$6:$K$1505,">0")>=$E15,"D",IF(COUNTIFS('COOIS Data'!$B$6:$B$1505,$C33,'COOIS Data'!$N$6:$N$1505,10,'COOIS Data'!$J$6:$J$1505,">0")>=$E15,"I","K"))) -> K | O33: =IF(COUNTIFS('COOIS Data'!$B$6:$B$1505,$C33,'COOIS Data'!$N$6:$N$1505,11,'COOIS Data'!$I$6:$I$1505,">0")<$E15,"–",IF(COUNTIFS('COOIS Data'!$B$6:$B$1505,$C33,'COOIS Data'!$N$6:$N$1505,11,'COOIS Data'!$K$6:$K$1505,">0")>=$E15,"D",IF(COUNTIFS('COOIS Data'!$B$6:$B$1505,$C33,'COOIS Data'!$N$6:$N$1505,11,'COOIS Data'!$J$6:$J$1505,">0")>=$E15,"I","K"))) -> K | P33: =IF(COUNTIFS('COOIS Data'!$B$6:$B$1505,$C33,'COOIS Data'!$N$6:$N$1505,12,'COOIS Data'!$I$6:$I$1505,">0")<$E15,"–",IF(COUNTIFS('COOIS Data'!$B$6:$B$1505,$C33,'COOIS Data'!$N$6:$N$1505,12,'COOIS Data'!$K$6:$K$1505,">0")>=$E15,"D",IF(COUNTIFS('COOIS Data'!$B$6:$B$1505,$C33,'COOIS Data'!$N$6:$N$1505,12,'COOIS Data'!$J$6:$J$1505,">0")>=$E15,"I","K"))) -> K | Q33: =IF(COUNTIFS('COOIS Data'!$B$6:$B$1505,$C33,'COOIS Data'!$N$6:$N$1505,13,'COOIS Data'!$I$6:$I$1505,">0")<$E15,"–",IF(COUNTIFS('COOIS Data'!$B$6:$B$1505,$C33,'COOIS Data'!$N$6:$N$1505,13,'COOIS Data'!$K$6:$K$1505,">0")>=$E15,"D",IF(COUNTIFS('COOIS Data'!$B$6:$B$1505,$C33,'COOIS Data'!$N$6:$N$1505,13,'COOIS Data'!$J$6:$J$1505,">0")>=$E15,"I","K"))) -> K
B34: =B16 -> POB ASSY | C34: =C16 -> 92YWS04548AAA | D34: =D16 -> R5B 4FP POB LUMENTUM SUB ASSEMBLY - E2A | E34: =IF(COUNTIFS('COOIS Data'!$B$6:$B$1505,$C34,'COOIS Data'!$N$6:$N$1505,1,'COOIS Data'!$I$6:$I$1505,">0")<$E16,"–",IF(COUNTIFS('COOIS Data'!$B$6:$B$1505,$C34,'COOIS Data'!$N$6:$N$1505,1,'COOIS Data'!$K$6:$K$1505,">0")>=$E16,"D",IF(COUNTIFS('COOIS Data'!$B$6:$B$1505,$C34,'COOIS Data'!$N$6:$N$1505,1,'COOIS Data'!$J$6:$J$1505,">0")>=$E16,"I","K"))) -> D | F34: =IF(COUNTIFS('COOIS Data'!$B$6:$B$1505,$C34,'COOIS Data'!$N$6:$N$1505,2,'COOIS Data'!$I$6:$I$1505,">0")<$E16,"–",IF(COUNTIFS('COOIS Data'!$B$6:$B$1505,$C34,'COOIS Data'!$N$6:$N$1505,2,'COOIS Data'!$K$6:$K$1505,">0")>=$E16,"D",IF(COUNTIFS('COOIS Data'!$B$6:$B$1505,$C34,'COOIS Data'!$N$6:$N$1505,2,'COOIS Data'!$J$6:$J$1505,">0")>=$E16,"I","K"))) -> D | G34: =IF(COUNTIFS('COOIS Data'!$B$6:$B$1505,$C34,'COOIS Data'!$N$6:$N$1505,3,'COOIS Data'!$I$6:$I$1505,">0")<$E16,"–",IF(COUNTIFS('COOIS Data'!$B$6:$B$1505,$C34,'COOIS Data'!$N$6:$N$1505,3,'COOIS Data'!$K$6:$K$1505,">0")>=$E16,"D",IF(COUNTIFS('COOIS Data'!$B$6:$B$1505,$C34,'COOIS Data'!$N$6:$N$1505,3,'COOIS Data'!$J$6:$J$1505,">0")>=$E16,"I","K"))) -> D | H34: =IF(COUNTIFS('COOIS Data'!$B$6:$B$1505,$C34,'COOIS Data'!$N$6:$N$1505,4,'COOIS Data'!$I$6:$I$1505,">0")<$E16,"–",IF(COUNTIFS('COOIS Data'!$B$6:$B$1505,$C34,'COOIS Data'!$N$6:$N$1505,4,'COOIS Data'!$K$6:$K$1505,">0")>=$E16,"D",IF(COUNTIFS('COOIS Data'!$B$6:$B$1505,$C34,'COOIS Data'!$N$6:$N$1505,4,'COOIS Data'!$J$6:$J$1505,">0")>=$E16,"I","K"))) -> D | I34: =IF(COUNTIFS('COOIS Data'!$B$6:$B$1505,$C34,'COOIS Data'!$N$6:$N$1505,5,'COOIS Data'!$I$6:$I$1505,">0")<$E16,"–",IF(COUNTIFS('COOIS Data'!$B$6:$B$1505,$C34,'COOIS Data'!$N$6:$N$1505,5,'COOIS Data'!$K$6:$K$1505,">0")>=$E16,"D",IF(COUNTIFS('COOIS Data'!$B$6:$B$1505,$C34,'COOIS Data'!$N$6:$N$1505,5,'COOIS Data'!$J$6:$J$1505,">0")>=$E16,"I","K"))) -> D | J34: =IF(COUNTIFS('COOIS Data'!$B$6:$B$1505,$C34,'COOIS Data'!$N$6:$N$1505,6,'COOIS Data'!$I$6:$I$1505,">0")<$E16,"–",IF(COUNTIFS('COOIS Data'!$B$6:$B$1505,$C34,'COOIS Data'!$N$6:$N$1505,6,'COOIS Data'!$K$6:$K$1505,">0")>=$E16,"D",IF(COUNTIFS('COOIS Data'!$B$6:$B$1505,$C34,'COOIS Data'!$N$6:$N$1505,6,'COOIS Data'!$J$6:$J$1505,">0")>=$E16,"I","K"))) -> D | K34: =IF(COUNTIFS('COOIS Data'!$B$6:$B$1505,$C34,'COOIS Data'!$N$6:$N$1505,7,'COOIS Data'!$I$6:$I$1505,">0")<$E16,"–",IF(COUNTIFS('COOIS Data'!$B$6:$B$1505,$C34,'COOIS Data'!$N$6:$N$1505,7,'COOIS Data'!$K$6:$K$1505,">0")>=$E16,"D",IF(COUNTIFS('COOIS Data'!$B$6:$B$1505,$C34,'COOIS Data'!$N$6:$N$1505,7,'COOIS Data'!$J$6:$J$1505,">0")>=$E16,"I","K"))) -> D | L34: =IF(COUNTIFS('COOIS Data'!$B$6:$B$1505,$C34,'COOIS Data'!$N$6:$N$1505,8,'COOIS Data'!$I$6:$I$1505,">0")<$E16,"–",IF(COUNTIFS('COOIS Data'!$B$6:$B$1505,$C34,'COOIS Data'!$N$6:$N$1505,8,'COOIS Data'!$K$6:$K$1505,">0")>=$E16,"D",IF(COUNTIFS('COOIS Data'!$B$6:$B$1505,$C34,'COOIS Data'!$N$6:$N$1505,8,'COOIS Data'!$J$6:$J$1505,">0")>=$E16,"I","K"))) -> D | M34: =IF(COUNTIFS('COOIS Data'!$B$6:$B$1505,$C34,'COOIS Data'!$N$6:$N$1505,9,'COOIS Data'!$I$6:$I$1505,">0")<$E16,"–",IF(COUNTIFS('COOIS Data'!$B$6:$B$1505,$C34,'COOIS Data'!$N$6:$N$1505,9,'COOIS Data'!$K$6:$K$1505,">0")>=$E16,"D",IF(COUNTIFS('COOIS Data'!$B$6:$B$1505,$C34,'COOIS Data'!$N$6:$N$1505,9,'COOIS Data'!$J$6:$J$1505,">0")>=$E16,"I","K"))) -> D | N34: =IF(COUNTIFS('COOIS Data'!$B$6:$B$1505,$C34,'COOIS Data'!$N$6:$N$1505,10,'COOIS Data'!$I$6:$I$1505,">0")<$E16,"–",IF(COUNTIFS('COOIS Data'!$B$6:$B$1505,$C34,'COOIS Data'!$N$6:$N$1505,10,'COOIS Data'!$K$6:$K$1505,">0")>=$E16,"D",IF(COUNTIFS('COOIS Data'!$B$6:$B$1505,$C34,'COOIS Data'!$N$6:$N$1505,10,'COOIS Data'!$J$6:$J$1505,">0")>=$E16,"I","K"))) -> K | O34: =IF(COUNTIFS('COOIS Data'!$B$6:$B$1505,$C34,'COOIS Data'!$N$6:$N$1505,11,'COOIS Data'!$I$6:$I$1505,">0")<$E16,"–",IF(COUNTIFS('COOIS Data'!$B$6:$B$1505,$C34,'COOIS Data'!$N$6:$N$1505,11,'COOIS Data'!$K$6:$K$1505,">0")>=$E16,"D",IF(COUNTIFS('COOIS Data'!$B$6:$B$1505,$C34,'COOIS Data'!$N$6:$N$1505,11,'COOIS Data'!$J$6:$J$1505,">0")>=$E16,"I","K"))) -> K | P34: =IF(COUNTIFS('COOIS Data'!$B$6:$B$1505,$C34,'COOIS Data'!$N$6:$N$1505,12,'COOIS Data'!$I$6:$I$1505,">0")<$E16,"–",IF(COUNTIFS('COOIS Data'!$B$6:$B$1505,$C34,'COOIS Data'!$N$6:$N$1505,12,'COOIS Data'!$K$6:$K$1505,">0")>=$E16,"D",IF(COUNTIFS('COOIS Data'!$B$6:$B$1505,$C34,'COOIS Data'!$N$6:$N$1505,12,'COOIS Data'!$J$6:$J$1505,">0")>=$E16,"I","K"))) -> K | Q34: =IF(COUNTIFS('COOIS Data'!$B$6:$B$1505,$C34,'COOIS Data'!$N$6:$N$1505,13,'COOIS Data'!$I$6:$I$1505,">0")<$E16,"–",IF(COUNTIFS('COOIS Data'!$B$6:$B$1505,$C34,'COOIS Data'!$N$6:$N$1505,13,'COOIS Data'!$K$6:$K$1505,">0")>=$E16,"D",IF(COUNTIFS('COOIS Data'!$B$6:$B$1505,$C34,'COOIS Data'!$N$6:$N$1505,13,'COOIS Data'!$J$6:$J$1505,">0")>=$E16,"I","K"))) -> K
B35: =B17 -> ERBIUM ASSY | C35: =C17 -> 92RRA00548AAA | D35: =D17 -> R5B ERBIUM SPOOL ASSEMBLY - E2A | E35: =IF(COUNTIFS('COOIS Data'!$B$6:$B$1505,$C35,'COOIS Data'!$N$6:$N$1505,1,'COOIS Data'!$I$6:$I$1505,">0")<$E17,"–",IF(COUNTIFS('COOIS Data'!$B$6:$B$1505,$C35,'COOIS Data'!$N$6:$N$1505,1,'COOIS Data'!$K$6:$K$1505,">0")>=$E17,"D",IF(COUNTIFS('COOIS Data'!$B$6:$B$1505,$C35,'COOIS Data'!$N$6:$N$1505,1,'COOIS Data'!$J$6:$J$1505,">0")>=$E17,"I","K"))) -> D | F35: =IF(COUNTIFS('COOIS Data'!$B$6:$B$1505,$C35,'COOIS Data'!$N$6:$N$1505,2,'COOIS Data'!$I$6:$I$1505,">0")<$E17,"–",IF(COUNTIFS('COOIS Data'!$B$6:$B$1505,$C35,'COOIS Data'!$N$6:$N$1505,2,'COOIS Data'!$K$6:$K$1505,">0")>=$E17,"D",IF(COUNTIFS('COOIS Data'!$B$6:$B$1505,$C35,'COOIS Data'!$N$6:$N$1505,2,'COOIS Data'!$J$6:$J$1505,">0")>=$E17,"I","K"))) -> D | G35: =IF(COUNTIFS('COOIS Data'!$B$6:$B$1505,$C35,'COOIS Data'!$N$6:$N$1505,3,'COOIS Data'!$I$6:$I$1505,">0")<$E17,"–",IF(COUNTIFS('COOIS Data'!$B$6:$B$1505,$C35,'COOIS Data'!$N$6:$N$1505,3,'COOIS Data'!$K$6:$K$1505,">0")>=$E17,"D",IF(COUNTIFS('COOIS Data'!$B$6:$B$1505,$C35,'COOIS Data'!$N$6:$N$1505,3,'COOIS Data'!$J$6:$J$1505,">0")>=$E17,"I","K"))) -> D | H35: =IF(COUNTIFS('COOIS Data'!$B$6:$B$1505,$C35,'COOIS Data'!$N$6:$N$1505,4,'COOIS Data'!$I$6:$I$1505,">0")<$E17,"–",IF(COUNTIFS('COOIS Data'!$B$6:$B$1505,$C35,'COOIS Data'!$N$6:$N$1505,4,'COOIS Data'!$K$6:$K$1505,">0")>=$E17,"D",IF(COUNTIFS('COOIS Data'!$B$6:$B$1505,$C35,'COOIS Data'!$N$6:$N$1505,4,'COOIS Data'!$J$6:$J$1505,">0")>=$E17,"I","K"))) -> D | I35: =IF(COUNTIFS('COOIS Data'!$B$6:$B$1505,$C35,'COOIS Data'!$N$6:$N$1505,5,'COOIS Data'!$I$6:$I$1505,">0")<$E17,"–",IF(COUNTIFS('COOIS Data'!$B$6:$B$1505,$C35,'COOIS Data'!$N$6:$N$1505,5,'COOIS Data'!$K$6:$K$1505,">0")>=$E17,"D",IF(COUNTIFS('COOIS Data'!$B$6:$B$1505,$C35,'COOIS Data'!$N$6:$N$1505,5,'COOIS Data'!$J$6:$J$1505,">0")>=$E17,"I","K"))) -> D | J35: =IF(COUNTIFS('COOIS Data'!$B$6:$B$1505,$C35,'COOIS Data'!$N$6:$N$1505,6,'COOIS Data'!$I$6:$I$1505,">0")<$E17,"–",IF(COUNTIFS('COOIS Data'!$B$6:$B$1505,$C35,'COOIS Data'!$N$6:$N$1505,6,'COOIS Data'!$K$6:$K$1505,">0")>=$E17,"D",IF(COUNTIFS('COOIS Data'!$B$6:$B$1505,$C35,'COOIS Data'!$N$6:$N$1505,6,'COOIS Data'!$J$6:$J$1505,">0")>=$E17,"I","K"))) -> D | K35: =IF(COUNTIFS('COOIS Data'!$B$6:$B$1505,$C35,'COOIS Data'!$N$6:$N$1505,7,'COOIS Data'!$I$6:$I$1505,">0")<$E17,"–",IF(COUNTIFS('COOIS Data'!$B$6:$B$1505,$C35,'COOIS Data'!$N$6:$N$1505,7,'COOIS Data'!$K$6:$K$1505,">0")>=$E17,"D",IF(COUNTIFS('COOIS Data'!$B$6:$B$1505,$C35,'COOIS Data'!$N$6:$N$1505,7,'COOIS Data'!$J$6:$J$1505,">0")>=$E17,"I","K"))) -> D | L35: =IF(COUNTIFS('COOIS Data'!$B$6:$B$1505,$C35,'COOIS Data'!$N$6:$N$1505,8,'COOIS Data'!$I$6:$I$1505,">0")<$E17,"–",IF(COUNTIFS('COOIS Data'!$B$6:$B$1505,$C35,'COOIS Data'!$N$6:$N$1505,8,'COOIS Data'!$K$6:$K$1505,">0")>=$E17,"D",IF(COUNTIFS('COOIS Data'!$B$6:$B$1505,$C35,'COOIS Data'!$N$6:$N$1505,8,'COOIS Data'!$J$6:$J$1505,">0")>=$E17,"I","K"))) -> D | M35: =IF(COUNTIFS('COOIS Data'!$B$6:$B$1505,$C35,'COOIS Data'!$N$6:$N$1505,9,'COOIS Data'!$I$6:$I$1505,">0")<$E17,"–",IF(COUNTIFS('COOIS Data'!$B$6:$B$1505,$C35,'COOIS Data'!$N$6:$N$1505,9,'COOIS Data'!$K$6:$K$1505,">0")>=$E17,"D",IF(COUNTIFS('COOIS Data'!$B$6:$B$1505,$C35,'COOIS Data'!$N$6:$N$1505,9,'COOIS Data'!$J$6:$J$1505,">0")>=$E17,"I","K"))) -> K | N35: =IF(COUNTIFS('COOIS Data'!$B$6:$B$1505,$C35,'COOIS Data'!$N$6:$N$1505,10,'COOIS Data'!$I$6:$I$1505,">0")<$E17,"–",IF(COUNTIFS('COOIS Data'!$B$6:$B$1505,$C35,'COOIS Data'!$N$6:$N$1505,10,'COOIS Data'!$K$6:$K$1505,">0")>=$E17,"D",IF(COUNTIFS('COOIS Data'!$B$6:$B$1505,$C35,'COOIS Data'!$N$6:$N$1505,10,'COOIS Data'!$J$6:$J$1505,">0")>=$E17,"I","K"))) -> K | O35: =IF(COUNTIFS('COOIS Data'!$B$6:$B$1505,$C35,'COOIS Data'!$N$6:$N$1505,11,'COOIS Data'!$I$6:$I$1505,">0")<$E17,"–",IF(COUNTIFS('COOIS Data'!$B$6:$B$1505,$C35,'COOIS Data'!$N$6:$N$1505,11,'COOIS Data'!$K$6:$K$1505,">0")>=$E17,"D",IF(COUNTIFS('COOIS Data'!$B$6:$B$1505,$C35,'COOIS Data'!$N$6:$N$1505,11,'COOIS Data'!$J$6:$J$1505,">0")>=$E17,"I","K"))) -> K | P35: =IF(COUNTIFS('COOIS Data'!$B$6:$B$1505,$C35,'COOIS Data'!$N$6:$N$1505,12,'COOIS Data'!$I$6:$I$1505,">0")<$E17,"–",IF(COUNTIFS('COOIS Data'!$B$6:$B$1505,$C35,'COOIS Data'!$N$6:$N$1505,12,'COOIS Data'!$K$6:$K$1505,">0")>=$E17,"D",IF(COUNTIFS('COOIS Data'!$B$6:$B$1505,$C35,'COOIS Data'!$N$6:$N$1505,12,'COOIS Data'!$J$6:$J$1505,">0")>=$E17,"I","K"))) -> K | Q35: =IF(COUNTIFS('COOIS Data'!$B$6:$B$1505,$C35,'COOIS Data'!$N$6:$N$1505,13,'COOIS Data'!$I$6:$I$1505,">0")<$E17,"–",IF(COUNTIFS('COOIS Data'!$B$6:$B$1505,$C35,'COOIS Data'!$N$6:$N$1505,13,'COOIS Data'!$K$6:$K$1505,">0")>=$E17,"D",IF(COUNTIFS('COOIS Data'!$B$6:$B$1505,$C35,'COOIS Data'!$N$6:$N$1505,13,'COOIS Data'!$J$6:$J$1505,">0")>=$E17,"I","K"))) -> K
B36: =B18 -> ERBIUM ASSY | C36: =C18 -> 92YRA01548AAA | D36: =D18 -> R5B ERBIUM ASSEMBLY POSITION 1 | E36: =IF(COUNTIFS('COOIS Data'!$B$6:$B$1505,$C36,'COOIS Data'!$N$6:$N$1505,1,'COOIS Data'!$I$6:$I$1505,">0")<$E18,"–",IF(COUNTIFS('COOIS Data'!$B$6:$B$1505,$C36,'COOIS Data'!$N$6:$N$1505,1,'COOIS Data'!$K$6:$K$1505,">0")>=$E18,"D",IF(COUNTIFS('COOIS Data'!$B$6:$B$1505,$C36,'COOIS Data'!$N$6:$N$1505,1,'COOIS Data'!$J$6:$J$1505,">0")>=$E18,"I","K"))) -> D | F36: =IF(COUNTIFS('COOIS Data'!$B$6:$B$1505,$C36,'COOIS Data'!$N$6:$N$1505,2,'COOIS Data'!$I$6:$I$1505,">0")<$E18,"–",IF(COUNTIFS('COOIS Data'!$B$6:$B$1505,$C36,'COOIS Data'!$N$6:$N$1505,2,'COOIS Data'!$K$6:$K$1505,">0")>=$E18,"D",IF(COUNTIFS('COOIS Data'!$B$6:$B$1505,$C36,'COOIS Data'!$N$6:$N$1505,2,'COOIS Data'!$J$6:$J$1505,">0")>=$E18,"I","K"))) -> D | G36: =IF(COUNTIFS('COOIS Data'!$B$6:$B$1505,$C36,'COOIS Data'!$N$6:$N$1505,3,'COOIS Data'!$I$6:$I$1505,">0")<$E18,"–",IF(COUNTIFS('COOIS Data'!$B$6:$B$1505,$C36,'COOIS Data'!$N$6:$N$1505,3,'COOIS Data'!$K$6:$K$1505,">0")>=$E18,"D",IF(COUNTIFS('COOIS Data'!$B$6:$B$1505,$C36,'COOIS Data'!$N$6:$N$1505,3,'COOIS Data'!$J$6:$J$1505,">0")>=$E18,"I","K"))) -> D | H36: =IF(COUNTIFS('COOIS Data'!$B$6:$B$1505,$C36,'COOIS Data'!$N$6:$N$1505,4,'COOIS Data'!$I$6:$I$1505,">0")<$E18,"–",IF(COUNTIFS('COOIS Data'!$B$6:$B$1505,$C36,'COOIS Data'!$N$6:$N$1505,4,'COOIS Data'!$K$6:$K$1505,">0")>=$E18,"D",IF(COUNTIFS('COOIS Data'!$B$6:$B$1505,$C36,'COOIS Data'!$N$6:$N$1505,4,'COOIS Data'!$J$6:$J$1505,">0")>=$E18,"I","K"))) -> D | I36: =IF(COUNTIFS('COOIS Data'!$B$6:$B$1505,$C36,'COOIS Data'!$N$6:$N$1505,5,'COOIS Data'!$I$6:$I$1505,">0")<$E18,"–",IF(COUNTIFS('COOIS Data'!$B$6:$B$1505,$C36,'COOIS Data'!$N$6:$N$1505,5,'COOIS Data'!$K$6:$K$1505,">0")>=$E18,"D",IF(COUNTIFS('COOIS Data'!$B$6:$B$1505,$C36,'COOIS Data'!$N$6:$N$1505,5,'COOIS Data'!$J$6:$J$1505,">0")>=$E18,"I","K"))) -> D | J36: =IF(COUNTIFS('COOIS Data'!$B$6:$B$1505,$C36,'COOIS Data'!$N$6:$N$1505,6,'COOIS Data'!$I$6:$I$1505,">0")<$E18,"–",IF(COUNTIFS('COOIS Data'!$B$6:$B$1505,$C36,'COOIS Data'!$N$6:$N$1505,6,'COOIS Data'!$K$6:$K$1505,">0")>=$E18,"D",IF(COUNTIFS('COOIS Data'!$B$6:$B$1505,$C36,'COOIS Data'!$N$6:$N$1505,6,'COOIS Data'!$J$6:$J$1505,">0")>=$E18,"I","K"))) -> D | K36: =IF(COUNTIFS('COOIS Data'!$B$6:$B$1505,$C36,'COOIS Data'!$N$6:$N$1505,7,'COOIS Data'!$I$6:$I$1505,">0")<$E18,"–",IF(COUNTIFS('COOIS Data'!$B$6:$B$1505,$C36,'COOIS Data'!$N$6:$N$1505,7,'COOIS Data'!$K$6:$K$1505,">0")>=$E18,"D",IF(COUNTIFS('COOIS Data'!$B$6:$B$1505,$C36,'COOIS Data'!$N$6:$N$1505,7,'COOIS Data'!$J$6:$J$1505,">0")>=$E18,"I","K"))) -> I | L36: =IF(COUNTIFS('COOIS Data'!$B$6:$B$1505,$C36,'COOIS Data'!$N$6:$N$1505,8,'COOIS Data'!$I$6:$I$1505,">0")<$E18,"–",IF(COUNTIFS('COOIS Data'!$B$6:$B$1505,$C36,'COOIS Data'!$N$6:$N$1505,8,'COOIS Data'!$K$6:$K$1505,">0")>=$E18,"D",IF(COUNTIFS('COOIS Data'!$B$6:$B$1505,$C36,'COOIS Data'!$N$6:$N$1505,8,'COOIS Data'!$J$6:$J$1505,">0")>=$E18,"I","K"))) -> I | M36: =IF(COUNTIFS('COOIS Data'!$B$6:$B$1505,$C36,'COOIS Data'!$N$6:$N$1505,9,'COOIS Data'!$I$6:$I$1505,">0")<$E18,"–",IF(COUNTIFS('COOIS Data'!$B$6:$B$1505,$C36,'COOIS Data'!$N$6:$N$1505,9,'COOIS Data'!$K$6:$K$1505,">0")>=$E18,"D",IF(COUNTIFS('COOIS Data'!$B$6:$B$1505,$C36,'COOIS Data'!$N$6:$N$1505,9,'COOIS Data'!$J$6:$J$1505,">0")>=$E18,"I","K"))) -> K | N36: =IF(COUNTIFS('COOIS Data'!$B$6:$B$1505,$C36,'COOIS Data'!$N$6:$N$1505,10,'COOIS Data'!$I$6:$I$1505,">0")<$E18,"–",IF(COUNTIFS('COOIS Data'!$B$6:$B$1505,$C36,'COOIS Data'!$N$6:$N$1505,10,'COOIS Data'!$K$6:$K$1505,">0")>=$E18,"D",IF(COUNTIFS('COOIS Data'!$B$6:$B$1505,$C36,'COOIS Data'!$N$6:$N$1505,10,'COOIS Data'!$J$6:$J$1505,">0")>=$E18,"I","K"))) -> K | O36: =IF(COUNTIFS('COOIS Data'!$B$6:$B$1505,$C36,'COOIS Data'!$N$6:$N$1505,11,'COOIS Data'!$I$6:$I$1505,">0")<$E18,"–",IF(COUNTIFS('COOIS Data'!$B$6:$B$1505,$C36,'COOIS Data'!$N$6:$N$1505,11,'COOIS Data'!$K$6:$K$1505,">0")>=$E18,"D",IF(COUNTIFS('COOIS Data'!$B$6:$B$1505,$C36,'COOIS Data'!$N$6:$N$1505,11,'COOIS Data'!$J$6:$J$1505,">0")>=$E18,"I","K"))) -> K | P36: =IF(COUNTIFS('COOIS Data'!$B$6:$B$1505,$C36,'COOIS Data'!$N$6:$N$1505,12,'COOIS Data'!$I$6:$I$1505,">0")<$E18,"–",IF(COUNTIFS('COOIS Data'!$B$6:$B$1505,$C36,'COOIS Data'!$N$6:$N$1505,12,'COOIS Data'!$K$6:$K$1505,">0")>=$E18,"D",IF(COUNTIFS('COOIS Data'!$B$6:$B$1505,$C36,'COOIS Data'!$N$6:$N$1505,12,'COOIS Data'!$J$6:$J$1505,">0")>=$E18,"I","K"))) -> K | Q36: =IF(COUNTIFS('COOIS Data'!$B$6:$B$1505,$C36,'COOIS Data'!$N$6:$N$1505,13,'COOIS Data'!$I$6:$I$1505,">0")<$E18,"–",IF(COUNTIFS('COOIS Data'!$B$6:$B$1505,$C36,'COOIS Data'!$N$6:$N$1505,13,'COOIS Data'!$K$6:$K$1505,">0")>=$E18,"D",IF(COUNTIFS('COOIS Data'!$B$6:$B$1505,$C36,'COOIS Data'!$N$6:$N$1505,13,'COOIS Data'!$J$6:$J$1505,">0")>=$E18,"I","K"))) -> K
B37: =B19 -> ERBIUM ASSY | C37: =C19 -> 92YRA02548AAA | D37: =D19 -> R5B ERBIUM ASSEMBLY POSITION 2 | E37: =IF(COUNTIFS('COOIS Data'!$B$6:$B$1505,$C37,'COOIS Data'!$N$6:$N$1505,1,'COOIS Data'!$I$6:$I$1505,">0")<$E19,"–",IF(COUNTIFS('COOIS Data'!$B$6:$B$1505,$C37,'COOIS Data'!$N$6:$N$1505,1,'COOIS Data'!$K$6:$K$1505,">0")>=$E19,"D",IF(COUNTIFS('COOIS Data'!$B$6:$B$1505,$C37,'COOIS Data'!$N$6:$N$1505,1,'COOIS Data'!$J$6:$J$1505,">0")>=$E19,"I","K"))) -> D | F37: =IF(COUNTIFS('COOIS Data'!$B$6:$B$1505,$C37,'COOIS Data'!$N$6:$N$1505,2,'COOIS Data'!$I$6:$I$1505,">0")<$E19,"–",IF(COUNTIFS('COOIS Data'!$B$6:$B$1505,$C37,'COOIS Data'!$N$6:$N$1505,2,'COOIS Data'!$K$6:$K$1505,">0")>=$E19,"D",IF(COUNTIFS('COOIS Data'!$B$6:$B$1505,$C37,'COOIS Data'!$N$6:$N$1505,2,'COOIS Data'!$J$6:$J$1505,">0")>=$E19,"I","K"))) -> D | G37: =IF(COUNTIFS('COOIS Data'!$B$6:$B$1505,$C37,'COOIS Data'!$N$6:$N$1505,3,'COOIS Data'!$I$6:$I$1505,">0")<$E19,"–",IF(COUNTIFS('COOIS Data'!$B$6:$B$1505,$C37,'COOIS Data'!$N$6:$N$1505,3,'COOIS Data'!$K$6:$K$1505,">0")>=$E19,"D",IF(COUNTIFS('COOIS Data'!$B$6:$B$1505,$C37,'COOIS Data'!$N$6:$N$1505,3,'COOIS Data'!$J$6:$J$1505,">0")>=$E19,"I","K"))) -> D | H37: =IF(COUNTIFS('COOIS Data'!$B$6:$B$1505,$C37,'COOIS Data'!$N$6:$N$1505,4,'COOIS Data'!$I$6:$I$1505,">0")<$E19,"–",IF(COUNTIFS('COOIS Data'!$B$6:$B$1505,$C37,'COOIS Data'!$N$6:$N$1505,4,'COOIS Data'!$K$6:$K$1505,">0")>=$E19,"D",IF(COUNTIFS('COOIS Data'!$B$6:$B$1505,$C37,'COOIS Data'!$N$6:$N$1505,4,'COOIS Data'!$J$6:$J$1505,">0")>=$E19,"I","K"))) -> D | I37: =IF(COUNTIFS('COOIS Data'!$B$6:$B$1505,$C37,'COOIS Data'!$N$6:$N$1505,5,'COOIS Data'!$I$6:$I$1505,">0")<$E19,"–",IF(COUNTIFS('COOIS Data'!$B$6:$B$1505,$C37,'COOIS Data'!$N$6:$N$1505,5,'COOIS Data'!$K$6:$K$1505,">0")>=$E19,"D",IF(COUNTIFS('COOIS Data'!$B$6:$B$1505,$C37,'COOIS Data'!$N$6:$N$1505,5,'COOIS Data'!$J$6:$J$1505,">0")>=$E19,"I","K"))) -> D | J37: =IF(COUNTIFS('COOIS Data'!$B$6:$B$1505,$C37,'COOIS Data'!$N$6:$N$1505,6,'COOIS Data'!$I$6:$I$1505,">0")<$E19,"–",IF(COUNTIFS('COOIS Data'!$B$6:$B$1505,$C37,'COOIS Data'!$N$6:$N$1505,6,'COOIS Data'!$K$6:$K$1505,">0")>=$E19,"D",IF(COUNTIFS('COOIS Data'!$B$6:$B$1505,$C37,'COOIS Data'!$N$6:$N$1505,6,'COOIS Data'!$J$6:$J$1505,">0")>=$E19,"I","K"))) -> D | K37: =IF(COUNTIFS('COOIS Data'!$B$6:$B$1505,$C37,'COOIS Data'!$N$6:$N$1505,7,'COOIS Data'!$I$6:$I$1505,">0")<$E19,"–",IF(COUNTIFS('COOIS Data'!$B$6:$B$1505,$C37,'COOIS Data'!$N$6:$N$1505,7,'COOIS Data'!$K$6:$K$1505,">0")>=$E19,"D",IF(COUNTIFS('COOIS Data'!$B$6:$B$1505,$C37,'COOIS Data'!$N$6:$N$1505,7,'COOIS Data'!$J$6:$J$1505,">0")>=$E19,"I","K"))) -> I | L37: =IF(COUNTIFS('COOIS Data'!$B$6:$B$1505,$C37,'COOIS Data'!$N$6:$N$1505,8,'COOIS Data'!$I$6:$I$1505,">0")<$E19,"–",IF(COUNTIFS('COOIS Data'!$B$6:$B$1505,$C37,'COOIS Data'!$N$6:$N$1505,8,'COOIS Data'!$K$6:$K$1505,">0")>=$E19,"D",IF(COUNTIFS('COOIS Data'!$B$6:$B$1505,$C37,'COOIS Data'!$N$6:$N$1505,8,'COOIS Data'!$J$6:$J$1505,">0")>=$E19,"I","K"))) -> I | M37: =IF(COUNTIFS('COOIS Data'!$B$6:$B$1505,$C37,'COOIS Data'!$N$6:$N$1505,9,'COOIS Data'!$I$6:$I$1505,">0")<$E19,"–",IF(COUNTIFS('COOIS Data'!$B$6:$B$1505,$C37,'COOIS Data'!$N$6:$N$1505,9,'COOIS Data'!$K$6:$K$1505,">0")>=$E19,"D",IF(COUNTIFS('COOIS Data'!$B$6:$B$1505,$C37,'COOIS Data'!$N$6:$N$1505,9,'COOIS Data'!$J$6:$J$1505,">0")>=$E19,"I","K"))) -> K | N37: =IF(COUNTIFS('COOIS Data'!$B$6:$B$1505,$C37,'COOIS Data'!$N$6:$N$1505,10,'COOIS Data'!$I$6:$I$1505,">0")<$E19,"–",IF(COUNTIFS('COOIS Data'!$B$6:$B$1505,$C37,'COOIS Data'!$N$6:$N$1505,10,'COOIS Data'!$K$6:$K$1505,">0")>=$E19,"D",IF(COUNTIFS('COOIS Data'!$B$6:$B$1505,$C37,'COOIS Data'!$N$6:$N$1505,10,'COOIS Data'!$J$6:$J$1505,">0")>=$E19,"I","K"))) -> K | O37: =IF(COUNTIFS('COOIS Data'!$B$6:$B$1505,$C37,'COOIS Data'!$N$6:$N$1505,11,'COOIS Data'!$I$6:$I$1505,">0")<$E19,"–",IF(COUNTIFS('COOIS Data'!$B$6:$B$1505,$C37,'COOIS Data'!$N$6:$N$1505,11,'COOIS Data'!$K$6:$K$1505,">0")>=$E19,"D",IF(COUNTIFS('COOIS Data'!$B$6:$B$1505,$C37,'COOIS Data'!$N$6:$N$1505,11,'COOIS Data'!$J$6:$J$1505,">0")>=$E19,"I","K"))) -> K | P37: =IF(COUNTIFS('COOIS Data'!$B$6:$B$1505,$C37,'COOIS Data'!$N$6:$N$1505,12,'COOIS Data'!$I$6:$I$1505,">0")<$E19,"–",IF(COUNTIFS('COOIS Data'!$B$6:$B$1505,$C37,'COOIS Data'!$N$6:$N$1505,12,'COOIS Data'!$K$6:$K$1505,">0")>=$E19,"D",IF(COUNTIFS('COOIS Data'!$B$6:$B$1505,$C37,'COOIS Data'!$N$6:$N$1505,12,'COOIS Data'!$J$6:$J$1505,">0")>=$E19,"I","K"))) -> K | Q37: =IF(COUNTIFS('COOIS Data'!$B$6:$B$1505,$C37,'COOIS Data'!$N$6:$N$1505,13,'COOIS Data'!$I$6:$I$1505,">0")<$E19,"–",IF(COUNTIFS('COOIS Data'!$B$6:$B$1505,$C37,'COOIS Data'!$N$6:$N$1505,13,'COOIS Data'!$K$6:$K$1505,">0")>=$E19,"D",IF(COUNTIFS('COOIS Data'!$B$6:$B$1505,$C37,'COOIS Data'!$N$6:$N$1505,13,'COOIS Data'!$J$6:$J$1505,">0")>=$E19,"I","K"))) -> K
B38: =B20 -> ERBIUM ASSY | C38: =C20 -> 92YRA03548AAA | D38: =D20 -> R5B ERBIUM ASSEMBLY POSITION 3 | E38: =IF(COUNTIFS('COOIS Data'!$B$6:$B$1505,$C38,'COOIS Data'!$N$6:$N$1505,1,'COOIS Data'!$I$6:$I$1505,">0")<$E20,"–",IF(COUNTIFS('COOIS Data'!$B$6:$B$1505,$C38,'COOIS Data'!$N$6:$N$1505,1,'COOIS Data'!$K$6:$K$1505,">0")>=$E20,"D",IF(COUNTIFS('COOIS Data'!$B$6:$B$1505,$C38,'COOIS Data'!$N$6:$N$1505,1,'COOIS Data'!$J$6:$J$1505,">0")>=$E20,"I","K"))) -> D | F38: =IF(COUNTIFS('COOIS Data'!$B$6:$B$1505,$C38,'COOIS Data'!$N$6:$N$1505,2,'COOIS Data'!$I$6:$I$1505,">0")<$E20,"–",IF(COUNTIFS('COOIS Data'!$B$6:$B$1505,$C38,'COOIS Data'!$N$6:$N$1505,2,'COOIS Data'!$K$6:$K$1505,">0")>=$E20,"D",IF(COUNTIFS('COOIS Data'!$B$6:$B$1505,$C38,'COOIS Data'!$N$6:$N$1505,2,'COOIS Data'!$J$6:$J$1505,">0")>=$E20,"I","K"))) -> D | G38: =IF(COUNTIFS('COOIS Data'!$B$6:$B$1505,$C38,'COOIS Data'!$N$6:$N$1505,3,'COOIS Data'!$I$6:$I$1505,">0")<$E20,"–",IF(COUNTIFS('COOIS Data'!$B$6:$B$1505,$C38,'COOIS Data'!$N$6:$N$1505,3,'COOIS Data'!$K$6:$K$1505,">0")>=$E20,"D",IF(COUNTIFS('COOIS Data'!$B$6:$B$1505,$C38,'COOIS Data'!$N$6:$N$1505,3,'COOIS Data'!$J$6:$J$1505,">0")>=$E20,"I","K"))) -> K | H38: =IF(COUNTIFS('COOIS Data'!$B$6:$B$1505,$C38,'COOIS Data'!$N$6:$N$1505,4,'COOIS Data'!$I$6:$I$1505,">0")<$E20,"–",IF(COUNTIFS('COOIS Data'!$B$6:$B$1505,$C38,'COOIS Data'!$N$6:$N$1505,4,'COOIS Data'!$K$6:$K$1505,">0")>=$E20,"D",IF(COUNTIFS('COOIS Data'!$B$6:$B$1505,$C38,'COOIS Data'!$N$6:$N$1505,4,'COOIS Data'!$J$6:$J$1505,">0")>=$E20,"I","K"))) -> D | I38: =IF(COUNTIFS('COOIS Data'!$B$6:$B$1505,$C38,'COOIS Data'!$N$6:$N$1505,5,'COOIS Data'!$I$6:$I$1505,">0")<$E20,"–",IF(COUNTIFS('COOIS Data'!$B$6:$B$1505,$C38,'COOIS Data'!$N$6:$N$1505,5,'COOIS Data'!$K$6:$K$1505,">0")>=$E20,"D",IF(COUNTIFS('COOIS Data'!$B$6:$B$1505,$C38,'COOIS Data'!$N$6:$N$1505,5,'COOIS Data'!$J$6:$J$1505,">0")>=$E20,"I","K"))) -> D | J38: =IF(COUNTIFS('COOIS Data'!$B$6:$B$1505,$C38,'COOIS Data'!$N$6:$N$1505,6,'COOIS Data'!$I$6:$I$1505,">0")<$E20,"–",IF(COUNTIFS('COOIS Data'!$B$6:$B$1505,$C38,'COOIS Data'!$N$6:$N$1505,6,'COOIS Data'!$K$6:$K$1505,">0")>=$E20,"D",IF(COUNTIFS('COOIS Data'!$B$6:$B$1505,$C38,'COOIS Data'!$N$6:$N$1505,6,'COOIS Data'!$J$6:$J$1505,">0")>=$E20,"I","K"))) -> D | K38: =IF(COUNTIFS('COOIS Data'!$B$6:$B$1505,$C38,'COOIS Data'!$N$6:$N$1505,7,'COOIS Data'!$I$6:$I$1505,">0")<$E20,"–",IF(COUNTIFS('COOIS Data'!$B$6:$B$1505,$C38,'COOIS Data'!$N$6:$N$1505,7,'COOIS Data'!$K$6:$K$1505,">0")>=$E20,"D",IF(COUNTIFS('COOIS Data'!$B$6:$B$1505,$C38,'COOIS Data'!$N$6:$N$1505,7,'COOIS Data'!$J$6:$J$1505,">0")>=$E20,"I","K"))) -> D | L38: =IF(COUNTIFS('COOIS Data'!$B$6:$B$1505,$C38,'COOIS Data'!$N$6:$N$1505,8,'COOIS Data'!$I$6:$I$1505,">0")<$E20,"–",IF(COUNTIFS('COOIS Data'!$B$6:$B$1505,$C38,'COOIS Data'!$N$6:$N$1505,8,'COOIS Data'!$K$6:$K$1505,">0")>=$E20,"D",IF(COUNTIFS('COOIS Data'!$B$6:$B$1505,$C38,'COOIS Data'!$N$6:$N$1505,8,'COOIS Data'!$J$6:$J$1505,">0")>=$E20,"I","K"))) -> I | M38: =IF(COUNTIFS('COOIS Data'!$B$6:$B$1505,$C38,'COOIS Data'!$N$6:$N$1505,9,'COOIS Data'!$I$6:$I$1505,">0")<$E20,"–",IF(COUNTIFS('COOIS Data'!$B$6:$B$1505,$C38,'COOIS Data'!$N$6:$N$1505,9,'COOIS Data'!$K$6:$K$1505,">0")>=$E20,"D",IF(COUNTIFS('COOIS Data'!$B$6:$B$1505,$C38,'COOIS Data'!$N$6:$N$1505,9,'COOIS Data'!$J$6:$J$1505,">0")>=$E20,"I","K"))) -> I | N38: =IF(COUNTIFS('COOIS Data'!$B$6:$B$1505,$C38,'COOIS Data'!$N$6:$N$1505,10,'COOIS Data'!$I$6:$I$1505,">0")<$E20,"–",IF(COUNTIFS('COOIS Data'!$B$6:$B$1505,$C38,'COOIS Data'!$N$6:$N$1505,10,'COOIS Data'!$K$6:$K$1505,">0")>=$E20,"D",IF(COUNTIFS('COOIS Data'!$B$6:$B$1505,$C38,'COOIS Data'!$N$6:$N$1505,10,'COOIS Data'!$J$6:$J$1505,">0")>=$E20,"I","K"))) -> K | O38: =IF(COUNTIFS('COOIS Data'!$B$6:$B$1505,$C38,'COOIS Data'!$N$6:$N$1505,11,'COOIS Data'!$I$6:$I$1505,">0")<$E20,"–",IF(COUNTIFS('COOIS Data'!$B$6:$B$1505,$C38,'COOIS Data'!$N$6:$N$1505,11,'COOIS Data'!$K$6:$K$1505,">0")>=$E20,"D",IF(COUNTIFS('COOIS Data'!$B$6:$B$1505,$C38,'COOIS Data'!$N$6:$N$1505,11,'COOIS Data'!$J$6:$J$1505,">0")>=$E20,"I","K"))) -> K | P38: =IF(COUNTIFS('COOIS Data'!$B$6:$B$1505,$C38,'COOIS Data'!$N$6:$N$1505,12,'COOIS Data'!$I$6:$I$1505,">0")<$E20,"–",IF(COUNTIFS('COOIS Data'!$B$6:$B$1505,$C38,'COOIS Data'!$N$6:$N$1505,12,'COOIS Data'!$K$6:$K$1505,">0")>=$E20,"D",IF(COUNTIFS('COOIS Data'!$B$6:$B$1505,$C38,'COOIS Data'!$N$6:$N$1505,12,'COOIS Data'!$J$6:$J$1505,">0")>=$E20,"I","K"))) -> K | Q38: =IF(COUNTIFS('COOIS Data'!$B$6:$B$1505,$C38,'COOIS Data'!$N$6:$N$1505,13,'COOIS Data'!$I$6:$I$1505,">0")<$E20,"–",IF(COUNTIFS('COOIS Data'!$B$6:$B$1505,$C38,'COOIS Data'!$N$6:$N$1505,13,'COOIS Data'!$K$6:$K$1505,">0")>=$E20,"D",IF(COUNTIFS('COOIS Data'!$B$6:$B$1505,$C38,'COOIS Data'!$N$6:$N$1505,13,'COOIS Data'!$J$6:$J$1505,">0")>=$E20,"I","K"))) -> K
B39: =B21 -> ERBIUM ASSY | C39: =C21 -> 92YRA04548AAA | D39: =D21 -> R5B ERBIUM ASSEMBLY POSITION 4 | E39: =IF(COUNTIFS('COOIS Data'!$B$6:$B$1505,$C39,'COOIS Data'!$N$6:$N$1505,1,'COOIS Data'!$I$6:$I$1505,">0")<$E21,"–",IF(COUNTIFS('COOIS Data'!$B$6:$B$1505,$C39,'COOIS Data'!$N$6:$N$1505,1,'COOIS Data'!$K$6:$K$1505,">0")>=$E21,"D",IF(COUNTIFS('COOIS Data'!$B$6:$B$1505,$C39,'COOIS Data'!$N$6:$N$1505,1,'COOIS Data'!$J$6:$J$1505,">0")>=$E21,"I","K"))) -> D | F39: =IF(COUNTIFS('COOIS Data'!$B$6:$B$1505,$C39,'COOIS Data'!$N$6:$N$1505,2,'COOIS Data'!$I$6:$I$1505,">0")<$E21,"–",IF(COUNTIFS('COOIS Data'!$B$6:$B$1505,$C39,'COOIS Data'!$N$6:$N$1505,2,'COOIS Data'!$K$6:$K$1505,">0")>=$E21,"D",IF(COUNTIFS('COOIS Data'!$B$6:$B$1505,$C39,'COOIS Data'!$N$6:$N$1505,2,'COOIS Data'!$J$6:$J$1505,">0")>=$E21,"I","K"))) -> D | G39: =IF(COUNTIFS('COOIS Data'!$B$6:$B$1505,$C39,'COOIS Data'!$N$6:$N$1505,3,'COOIS Data'!$I$6:$I$1505,">0")<$E21,"–",IF(COUNTIFS('COOIS Data'!$B$6:$B$1505,$C39,'COOIS Data'!$N$6:$N$1505,3,'COOIS Data'!$K$6:$K$1505,">0")>=$E21,"D",IF(COUNTIFS('COOIS Data'!$B$6:$B$1505,$C39,'COOIS Data'!$N$6:$N$1505,3,'COOIS Data'!$J$6:$J$1505,">0")>=$E21,"I","K"))) -> D | H39: =IF(COUNTIFS('COOIS Data'!$B$6:$B$1505,$C39,'COOIS Data'!$N$6:$N$1505,4,'COOIS Data'!$I$6:$I$1505,">0")<$E21,"–",IF(COUNTIFS('COOIS Data'!$B$6:$B$1505,$C39,'COOIS Data'!$N$6:$N$1505,4,'COOIS Data'!$K$6:$K$1505,">0")>=$E21,"D",IF(COUNTIFS('COOIS Data'!$B$6:$B$1505,$C39,'COOIS Data'!$N$6:$N$1505,4,'COOIS Data'!$J$6:$J$1505,">0")>=$E21,"I","K"))) -> D | I39: =IF(COUNTIFS('COOIS Data'!$B$6:$B$1505,$C39,'COOIS Data'!$N$6:$N$1505,5,'COOIS Data'!$I$6:$I$1505,">0")<$E21,"–",IF(COUNTIFS('COOIS Data'!$B$6:$B$1505,$C39,'COOIS Data'!$N$6:$N$1505,5,'COOIS Data'!$K$6:$K$1505,">0")>=$E21,"D",IF(COUNTIFS('COOIS Data'!$B$6:$B$1505,$C39,'COOIS Data'!$N$6:$N$1505,5,'COOIS Data'!$J$6:$J$1505,">0")>=$E21,"I","K"))) -> D | J39: =IF(COUNTIFS('COOIS Data'!$B$6:$B$1505,$C39,'COOIS Data'!$N$6:$N$1505,6,'COOIS Data'!$I$6:$I$1505,">0")<$E21,"–",IF(COUNTIFS('COOIS Data'!$B$6:$B$1505,$C39,'COOIS Data'!$N$6:$N$1505,6,'COOIS Data'!$K$6:$K$1505,">0")>=$E21,"D",IF(COUNTIFS('COOIS Data'!$B$6:$B$1505,$C39,'COOIS Data'!$N$6:$N$1505,6,'COOIS Data'!$J$6:$J$1505,">0")>=$E21,"I","K"))) -> D | K39: =IF(COUNTIFS('COOIS Data'!$B$6:$B$1505,$C39,'COOIS Data'!$N$6:$N$1505,7,'COOIS Data'!$I$6:$I$1505,">0")<$E21,"–",IF(COUNTIFS('COOIS Data'!$B$6:$B$1505,$C39,'COOIS Data'!$N$6:$N$1505,7,'COOIS Data'!$K$6:$K$1505,">0")>=$E21,"D",IF(COUNTIFS('COOIS Data'!$B$6:$B$1505,$C39,'COOIS Data'!$N$6:$N$1505,7,'COOIS Data'!$J$6:$J$1505,">0")>=$E21,"I","K"))) -> I | L39: =IF(COUNTIFS('COOIS Data'!$B$6:$B$1505,$C39,'COOIS Data'!$N$6:$N$1505,8,'COOIS Data'!$I$6:$I$1505,">0")<$E21,"–",IF(COUNTIFS('COOIS Data'!$B$6:$B$1505,$C39,'COOIS Data'!$N$6:$N$1505,8,'COOIS Data'!$K$6:$K$1505,">0")>=$E21,"D",IF(COUNTIFS('COOIS Data'!$B$6:$B$1505,$C39,'COOIS Data'!$N$6:$N$1505,8,'COOIS Data'!$J$6:$J$1505,">0")>=$E21,"I","K"))) -> I | M39: =IF(COUNTIFS('COOIS Data'!$B$6:$B$1505,$C39,'COOIS Data'!$N$6:$N$1505,9,'COOIS Data'!$I$6:$I$1505,">0")<$E21,"–",IF(COUNTIFS('COOIS Data'!$B$6:$B$1505,$C39,'COOIS Data'!$N$6:$N$1505,9,'COOIS Data'!$K$6:$K$1505,">0")>=$E21,"D",IF(COUNTIFS('COOIS Data'!$B$6:$B$1505,$C39,'COOIS Data'!$N$6:$N$1505,9,'COOIS Data'!$J$6:$J$1505,">0")>=$E21,"I","K"))) -> K | N39: =IF(COUNTIFS('COOIS Data'!$B$6:$B$1505,$C39,'COOIS Data'!$N$6:$N$1505,10,'COOIS Data'!$I$6:$I$1505,">0")<$E21,"–",IF(COUNTIFS('COOIS Data'!$B$6:$B$1505,$C39,'COOIS Data'!$N$6:$N$1505,10,'COOIS Data'!$K$6:$K$1505,">0")>=$E21,"D",IF(COUNTIFS('COOIS Data'!$B$6:$B$1505,$C39,'COOIS Data'!$N$6:$N$1505,10,'COOIS Data'!$J$6:$J$1505,">0")>=$E21,"I","K"))) -> K | O39: =IF(COUNTIFS('COOIS Data'!$B$6:$B$1505,$C39,'COOIS Data'!$N$6:$N$1505,11,'COOIS Data'!$I$6:$I$1505,">0")<$E21,"–",IF(COUNTIFS('COOIS Data'!$B$6:$B$1505,$C39,'COOIS Data'!$N$6:$N$1505,11,'COOIS Data'!$K$6:$K$1505,">0")>=$E21,"D",IF(COUNTIFS('COOIS Data'!$B$6:$B$1505,$C39,'COOIS Data'!$N$6:$N$1505,11,'COOIS Data'!$J$6:$J$1505,">0")>=$E21,"I","K"))) -> K | P39: =IF(COUNTIFS('COOIS Data'!$B$6:$B$1505,$C39,'COOIS Data'!$N$6:$N$1505,12,'COOIS Data'!$I$6:$I$1505,">0")<$E21,"–",IF(COUNTIFS('COOIS Data'!$B$6:$B$1505,$C39,'COOIS Data'!$N$6:$N$1505,12,'COOIS Data'!$K$6:$K$1505,">0")>=$E21,"D",IF(COUNTIFS('COOIS Data'!$B$6:$B$1505,$C39,'COOIS Data'!$N$6:$N$1505,12,'COOIS Data'!$J$6:$J$1505,">0")>=$E21,"I","K"))) -> K | Q39: =IF(COUNTIFS('COOIS Data'!$B$6:$B$1505,$C39,'COOIS Data'!$N$6:$N$1505,13,'COOIS Data'!$I$6:$I$1505,">0")<$E21,"–",IF(COUNTIFS('COOIS Data'!$B$6:$B$1505,$C39,'COOIS Data'!$N$6:$N$1505,13,'COOIS Data'!$K$6:$K$1505,">0")>=$E21,"D",IF(COUNTIFS('COOIS Data'!$B$6:$B$1505,$C39,'COOIS Data'!$N$6:$N$1505,13,'COOIS Data'!$J$6:$J$1505,">0")>=$E21,"I","K"))) -> K
B40: =B22 -> BOAT ASSY | C40: =C22 -> 92UAP04548BAA | D40: =D22 -> R5B BOAT 1 ASSY (4P-4FP) | E40: =IF(COUNTIFS('COOIS Data'!$B$6:$B$1505,$C40,'COOIS Data'!$N$6:$N$1505,1,'COOIS Data'!$I$6:$I$1505,">0")<$E22,"–",IF(COUNTIFS('COOIS Data'!$B$6:$B$1505,$C40,'COOIS Data'!$N$6:$N$1505,1,'COOIS Data'!$K$6:$K$1505,">0")>=$E22,"D",IF(COUNTIFS('COOIS Data'!$B$6:$B$1505,$C40,'COOIS Data'!$N$6:$N$1505,1,'COOIS Data'!$J$6:$J$1505,">0")>=$E22,"I","K"))) -> D | F40: =IF(COUNTIFS('COOIS Data'!$B$6:$B$1505,$C40,'COOIS Data'!$N$6:$N$1505,2,'COOIS Data'!$I$6:$I$1505,">0")<$E22,"–",IF(COUNTIFS('COOIS Data'!$B$6:$B$1505,$C40,'COOIS Data'!$N$6:$N$1505,2,'COOIS Data'!$K$6:$K$1505,">0")>=$E22,"D",IF(COUNTIFS('COOIS Data'!$B$6:$B$1505,$C40,'COOIS Data'!$N$6:$N$1505,2,'COOIS Data'!$J$6:$J$1505,">0")>=$E22,"I","K"))) -> D | G40: =IF(COUNTIFS('COOIS Data'!$B$6:$B$1505,$C40,'COOIS Data'!$N$6:$N$1505,3,'COOIS Data'!$I$6:$I$1505,">0")<$E22,"–",IF(COUNTIFS('COOIS Data'!$B$6:$B$1505,$C40,'COOIS Data'!$N$6:$N$1505,3,'COOIS Data'!$K$6:$K$1505,">0")>=$E22,"D",IF(COUNTIFS('COOIS Data'!$B$6:$B$1505,$C40,'COOIS Data'!$N$6:$N$1505,3,'COOIS Data'!$J$6:$J$1505,">0")>=$E22,"I","K"))) -> D | H40: =IF(COUNTIFS('COOIS Data'!$B$6:$B$1505,$C40,'COOIS Data'!$N$6:$N$1505,4,'COOIS Data'!$I$6:$I$1505,">0")<$E22,"–",IF(COUNTIFS('COOIS Data'!$B$6:$B$1505,$C40,'COOIS Data'!$N$6:$N$1505,4,'COOIS Data'!$K$6:$K$1505,">0")>=$E22,"D",IF(COUNTIFS('COOIS Data'!$B$6:$B$1505,$C40,'COOIS Data'!$N$6:$N$1505,4,'COOIS Data'!$J$6:$J$1505,">0")>=$E22,"I","K"))) -> D | I40: =IF(COUNTIFS('COOIS Data'!$B$6:$B$1505,$C40,'COOIS Data'!$N$6:$N$1505,5,'COOIS Data'!$I$6:$I$1505,">0")<$E22,"–",IF(COUNTIFS('COOIS Data'!$B$6:$B$1505,$C40,'COOIS Data'!$N$6:$N$1505,5,'COOIS Data'!$K$6:$K$1505,">0")>=$E22,"D",IF(COUNTIFS('COOIS Data'!$B$6:$B$1505,$C40,'COOIS Data'!$N$6:$N$1505,5,'COOIS Data'!$J$6:$J$1505,">0")>=$E22,"I","K"))) -> D | J40: =IF(COUNTIFS('COOIS Data'!$B$6:$B$1505,$C40,'COOIS Data'!$N$6:$N$1505,6,'COOIS Data'!$I$6:$I$1505,">0")<$E22,"–",IF(COUNTIFS('COOIS Data'!$B$6:$B$1505,$C40,'COOIS Data'!$N$6:$N$1505,6,'COOIS Data'!$K$6:$K$1505,">0")>=$E22,"D",IF(COUNTIFS('COOIS Data'!$B$6:$B$1505,$C40,'COOIS Data'!$N$6:$N$1505,6,'COOIS Data'!$J$6:$J$1505,">0")>=$E22,"I","K"))) -> I | K40: =IF(COUNTIFS('COOIS Data'!$B$6:$B$1505,$C40,'COOIS Data'!$N$6:$N$1505,7,'COOIS Data'!$I$6:$I$1505,">0")<$E22,"–",IF(COUNTIFS('COOIS Data'!$B$6:$B$1505,$C40,'COOIS Data'!$N$6:$N$1505,7,'COOIS Data'!$K$6:$K$1505,">0")>=$E22,"D",IF(COUNTIFS('COOIS Data'!$B$6:$B$1505,$C40,'COOIS Data'!$N$6:$N$1505,7,'COOIS Data'!$J$6:$J$1505,">0")>=$E22,"I","K"))) -> I | L40: =IF(COUNTIFS('COOIS Data'!$B$6:$B$1505,$C40,'COOIS Data'!$N$6:$N$1505,8,'COOIS Data'!$I$6:$I$1505,">0")<$E22,"–",IF(COUNTIFS('COOIS Data'!$B$6:$B$1505,$C40,'COOIS Data'!$N$6:$N$1505,8,'COOIS Data'!$K$6:$K$1505,">0")>=$E22,"D",IF(COUNTIFS('COOIS Data'!$B$6:$B$1505,$C40,'COOIS Data'!$N$6:$N$1505,8,'COOIS Data'!$J$6:$J$1505,">0")>=$E22,"I","K"))) -> I | M40: =IF(COUNTIFS('COOIS Data'!$B$6:$B$1505,$C40,'COOIS Data'!$N$6:$N$1505,9,'COOIS Data'!$I$6:$I$1505,">0")<$E22,"–",IF(COUNTIFS('COOIS Data'!$B$6:$B$1505,$C40,'COOIS Data'!$N$6:$N$1505,9,'COOIS Data'!$K$6:$K$1505,">0")>=$E22,"D",IF(COUNTIFS('COOIS Data'!$B$6:$B$1505,$C40,'COOIS Data'!$N$6:$N$1505,9,'COOIS Data'!$J$6:$J$1505,">0")>=$E22,"I","K"))) -> K | N40: =IF(COUNTIFS('COOIS Data'!$B$6:$B$1505,$C40,'COOIS Data'!$N$6:$N$1505,10,'COOIS Data'!$I$6:$I$1505,">0")<$E22,"–",IF(COUNTIFS('COOIS Data'!$B$6:$B$1505,$C40,'COOIS Data'!$N$6:$N$1505,10,'COOIS Data'!$K$6:$K$1505,">0")>=$E22,"D",IF(COUNTIFS('COOIS Data'!$B$6:$B$1505,$C40,'COOIS Data'!$N$6:$N$1505,10,'COOIS Data'!$J$6:$J$1505,">0")>=$E22,"I","K"))) -> K | O40: =IF(COUNTIFS('COOIS Data'!$B$6:$B$1505,$C40,'COOIS Data'!$N$6:$N$1505,11,'COOIS Data'!$I$6:$I$1505,">0")<$E22,"–",IF(COUNTIFS('COOIS Data'!$B$6:$B$1505,$C40,'COOIS Data'!$N$6:$N$1505,11,'COOIS Data'!$K$6:$K$1505,">0")>=$E22,"D",IF(COUNTIFS('COOIS Data'!$B$6:$B$1505,$C40,'COOIS Data'!$N$6:$N$1505,11,'COOIS Data'!$J$6:$J$1505,">0")>=$E22,"I","K"))) -> K | P40: =IF(COUNTIFS('COOIS Data'!$B$6:$B$1505,$C40,'COOIS Data'!$N$6:$N$1505,12,'COOIS Data'!$I$6:$I$1505,">0")<$E22,"–",IF(COUNTIFS('COOIS Data'!$B$6:$B$1505,$C40,'COOIS Data'!$N$6:$N$1505,12,'COOIS Data'!$K$6:$K$1505,">0")>=$E22,"D",IF(COUNTIFS('COOIS Data'!$B$6:$B$1505,$C40,'COOIS Data'!$N$6:$N$1505,12,'COOIS Data'!$J$6:$J$1505,">0")>=$E22,"I","K"))) -> K | Q40: =IF(COUNTIFS('COOIS Data'!$B$6:$B$1505,$C40,'COOIS Data'!$N$6:$N$1505,13,'COOIS Data'!$I$6:$I$1505,">0")<$E22,"–",IF(COUNTIFS('COOIS Data'!$B$6:$B$1505,$C40,'COOIS Data'!$N$6:$N$1505,13,'COOIS Data'!$K$6:$K$1505,">0")>=$E22,"D",IF(COUNTIFS('COOIS Data'!$B$6:$B$1505,$C40,'COOIS Data'!$N$6:$N$1505,13,'COOIS Data'!$J$6:$J$1505,">0")>=$E22,"I","K"))) -> K
... B42: =B24 -> BOAT ASSY | C42: =C24 -> 92UAP04548BCA | D42: =D24 -> R5B BOAT 3 ASSY (4P-4FP) | E42: =IF(COUNTIFS('COOIS Data'!$B$6:$B$1505,$C42,'COOIS Data'!$N$6:$N$1505,1,'COOIS Data'!$I$6:$I$1505,">0")<$E24,"–",IF(COUNTIFS('COOIS Data'!$B$6:$B$1505,$C42,'COOIS Data'!$N$6:$N$1505,1,'COOIS Data'!$K$6:$K$1505,">0")>=$E24,"D",IF(COUNTIFS('COOIS Data'!$B$6:$B$1505,$C42,'COOIS Data'!$N$6:$N$1505,1,'COOIS Data'!$J$6:$J$1505,">0")>=$E24,"I","K"))) -> D | F42: =IF(COUNTIFS('COOIS Data'!$B$6:$B$1505,$C42,'COOIS Data'!$N$6:$N$1505,2,'COOIS Data'!$I$6:$I$1505,">0")<$E24,"–",IF(COUNTIFS('COOIS Data'!$B$6:$B$1505,$C42,'COOIS Data'!$N$6:$N$1505,2,'COOIS Data'!$K$6:$K$1505,">0")>=$E24,"D",IF(COUNTIFS('COOIS Data'!$B$6:$B$1505,$C42,'COOIS Data'!$N$6:$N$1505,2,'COOIS Data'!$J$6:$J$1505,">0")>=$E24,"I","K"))) -> D | G42: =IF(COUNTIFS('COOIS Data'!$B$6:$B$1505,$C42,'COOIS Data'!$N$6:$N$1505,3,'COOIS Data'!$I$6:$I$1505,">0")<$E24,"–",IF(COUNTIFS('COOIS Data'!$B$6:$B$1505,$C42,'COOIS Data'!$N$6:$N$1505,3,'COOIS Data'!$K$6:$K$1505,">0")>=$E24,"D",IF(COUNTIFS('COOIS Data'!$B$6:$B$1505,$C42,'COOIS Data'!$N$6:$N$1505,3,'COOIS Data'!$J$6:$J$1505,">0")>=$E24,"I","K"))) -> D | H42: =IF(COUNTIFS('COOIS Data'!$B$6:$B$1505,$C42,'COOIS Data'!$N$6:$N$1505,4,'COOIS Data'!$I$6:$I$1505,">0")<$E24,"–",IF(COUNTIFS('COOIS Data'!$B$6:$B$1505,$C42,'COOIS Data'!$N$6:$N$1505,4,'COOIS Data'!$K$6:$K$1505,">0")>=$E24,"D",IF(COUNTIFS('COOIS Data'!$B$6:$B$1505,$C42,'COOIS Data'!$N$6:$N$1505,4,'COOIS Data'!$J$6:$J$1505,">0")>=$E24,"I","K"))) -> D | I42: =IF(COUNTIFS('COOIS Data'!$B$6:$B$1505,$C42,'COOIS Data'!$N$6:$N$1505,5,'COOIS Data'!$I$6:$I$1505,">0")<$E24,"–",IF(COUNTIFS('COOIS Data'!$B$6:$B$1505,$C42,'COOIS Data'!$N$6:$N$1505,5,'COOIS Data'!$K$6:$K$1505,">0")>=$E24,"D",IF(COUNTIFS('COOIS Data'!$B$6:$B$1505,$C42,'COOIS Data'!$N$6:$N$1505,5,'COOIS Data'!$J$6:$J$1505,">0")>=$E24,"I","K"))) -> D | J42: =IF(COUNTIFS('COOIS Data'!$B$6:$B$1505,$C42,'COOIS Data'!$N$6:$N$1505,6,'COOIS Data'!$I$6:$I$1505,">0")<$E24,"–",IF(COUNTIFS('COOIS Data'!$B$6:$B$1505,$C42,'COOIS Data'!$N$6:$N$1505,6,'COOIS Data'!$K$6:$K$1505,">0")>=$E24,"D",IF(COUNTIFS('COOIS Data'!$B$6:$B$1505,$C42,'COOIS Data'!$N$6:$N$1505,6,'COOIS Data'!$J$6:$J$1505,">0")>=$E24,"I","K"))) -> D | K42: =IF(COUNTIFS('COOIS Data'!$B$6:$B$1505,$C42,'COOIS Data'!$N$6:$N$1505,7,'COOIS Data'!$I$6:$I$1505,">0")<$E24,"–",IF(COUNTIFS('COOIS Data'!$B$6:$B$1505,$C42,'COOIS Data'!$N$6:$N$1505,7,'COOIS Data'!$K$6:$K$1505,">0")>=$E24,"D",IF(COUNTIFS('COOIS Data'!$B$6:$B$1505,$C42,'COOIS Data'!$N$6:$N$1505,7,'COOIS Data'!$J$6:$J$1505,">0")>=$E24,"I","K"))) -> I | L42: =IF(COUNTIFS('COOIS Data'!$B$6:$B$1505,$C42,'COOIS Data'!$N$6:$N$1505,8,'COOIS Data'!$I$6:$I$1505,">0")<$E24,"–",IF(COUNTIFS('COOIS Data'!$B$6:$B$1505,$C42,'COOIS Data'!$N$6:$N$1505,8,'COOIS Data'!$K$6:$K$1505,">0")>=$E24,"D",IF(COUNTIFS('COOIS Data'!$B$6:$B$1505,$C42,'COOIS Data'!$N$6:$N$1505,8,'COOIS Data'!$J$6:$J$1505,">0")>=$E24,"I","K"))) -> K | M42: =IF(COUNTIFS('COOIS Data'!$B$6:$B$1505,$C42,'COOIS Data'!$N$6:$N$1505,9,'COOIS Data'!$I$6:$I$1505,">0")<$E24,"–",IF(COUNTIFS('COOIS Data'!$B$6:$B$1505,$C42,'COOIS Data'!$N$6:$N$1505,9,'COOIS Data'!$K$6:$K$1505,">0")>=$E24,"D",IF(COUNTIFS('COOIS Data'!$B$6:$B$1505,$C42,'COOIS Data'!$N$6:$N$1505,9,'COOIS Data'!$J$6:$J$1505,">0")>=$E24,"I","K"))) -> K | N42: =IF(COUNTIFS('COOIS Data'!$B$6:$B$1505,$C42,'COOIS Data'!$N$6:$N$1505,10,'COOIS Data'!$I$6:$I$1505,">0")<$E24,"–",IF(COUNTIFS('COOIS Data'!$B$6:$B$1505,$C42,'COOIS Data'!$N$6:$N$1505,10,'COOIS Data'!$K$6:$K$1505,">0")>=$E24,"D",IF(COUNTIFS('COOIS Data'!$B$6:$B$1505,$C42,'COOIS Data'!$N$6:$N$1505,10,'COOIS Data'!$J$6:$J$1505,">0")>=$E24,"I","K"))) -> K | O42: =IF(COUNTIFS('COOIS Data'!$B$6:$B$1505,$C42,'COOIS Data'!$N$6:$N$1505,11,'COOIS Data'!$I$6:$I$1505,">0")<$E24,"–",IF(COUNTIFS('COOIS Data'!$B$6:$B$1505,$C42,'COOIS Data'!$N$6:$N$1505,11,'COOIS Data'!$K$6:$K$1505,">0")>=$E24,"D",IF(COUNTIFS('COOIS Data'!$B$6:$B$1505,$C42,'COOIS Data'!$N$6:$N$1505,11,'COOIS Data'!$J$6:$J$1505,">0")>=$E24,"I","K"))) -> K | P42: =IF(COUNTIFS('COOIS Data'!$B$6:$B$1505,$C42,'COOIS Data'!$N$6:$N$1505,12,'COOIS Data'!$I$6:$I$1505,">0")<$E24,"–",IF(COUNTIFS('COOIS Data'!$B$6:$B$1505,$C42,'COOIS Data'!$N$6:$N$1505,12,'COOIS Data'!$K$6:$K$1505,">0")>=$E24,"D",IF(COUNTIFS('COOIS Data'!$B$6:$B$1505,$C42,'COOIS Data'!$N$6:$N$1505,12,'COOIS Data'!$J$6:$J$1505,">0")>=$E24,"I","K"))) -> K | Q42: =IF(COUNTIFS('COOIS Data'!$B$6:$B$1505,$C42,'COOIS Data'!$N$6:$N$1505,13,'COOIS Data'!$I$6:$I$1505,">0")<$E24,"–",IF(COUNTIFS('COOIS Data'!$B$6:$B$1505,$C42,'COOIS Data'!$N$6:$N$1505,13,'COOIS Data'!$K$6:$K$1505,">0")>=$E24,"D",IF(COUNTIFS('COOIS Data'!$B$6:$B$1505,$C42,'COOIS Data'!$N$6:$N$1505,13,'COOIS Data'!$J$6:$J$1505,">0")>=$E24,"I","K"))) -> K
C43: REPEATER STATUS | D43: Kitted = all codes kitted · Delivered = all codes delivered | E43: =IF(COUNTIF(E29:E42,"–")>0,"OPEN",IF(COUNTIF(E29:E42,"D")=14,"DLV",IF(COUNTIF(E29:E42,"K")=0,"ISSUED","KITTED"))) -> DLV | F43: =IF(COUNTIF(F29:F42,"–")>0,"OPEN",IF(COUNTIF(F29:F42,"D")=14,"DLV",IF(COUNTIF(F29:F42,"K")=0,"ISSUED","KITTED"))) -> DLV | G43: =IF(COUNTIF(G29:G42,"–")>0,"OPEN",IF(COUNTIF(G29:G42,"D")=14,"DLV",IF(COUNTIF(G29:G42,"K")=0,"ISSUED","KITTED"))) -> KITTED | H43: =IF(COUNTIF(H29:H42,"–")>0,"OPEN",IF(COUNTIF(H29:H42,"D")=14,"DLV",IF(COUNTIF(H29:H42,"K")=0,"ISSUED","KITTED"))) -> DLV | I43: =IF(COUNTIF(I29:I42,"–")>0,"OPEN",IF(COUNTIF(I29:I42,"D")=14,"DLV",IF(COUNTIF(I29:I42,"K")=0,"ISSUED","KITTED"))) -> DLV | J43: =IF(COUNTIF(J29:J42,"–")>0,"OPEN",IF(COUNTIF(J29:J42,"D")=14,"DLV",IF(COUNTIF(J29:J42,"K")=0,"ISSUED","KITTED"))) -> ISSUED | K43: =IF(COUNTIF(K29:K42,"–")>0,"OPEN",IF(COUNTIF(K29:K42,"D")=14,"DLV",IF(COUNTIF(K29:K42,"K")=0,"ISSUED","KITTED"))) -> ISSUED | L43: =IF(COUNTIF(L29:L42,"–")>0,"OPEN",IF(COUNTIF(L29:L42,"D")=14,"DLV",IF(COUNTIF(L29:L42,"K")=0,"ISSUED","KITTED"))) -> KITTED | ... Q43: =IF(COUNTIF(Q29:Q42,"–")>0,"OPEN",IF(COUNTIF(Q29:Q42,"D")=14,"DLV",IF(COUNTIF(Q29:Q42,"K")=0,"ISSUED","KITTED"))) -> KITTED
C44: Surplus WOs (beyond rep 13) | D44: =COUNTIF('COOIS Data'!$O$6:$O$1505,"Surplus")&" WOs — filter Contract = Surplus on COOIS Data to see which" -> 28 WOs — filter Contract = Surplus on COOIS Data to see which
C45: Not in plan | D45: =COUNTIF('COOIS Data'!$G$6:$G$1505,"Not in plan")&" WOs in COOIS for codes not on the kitting plan" -> 0 WOs in COOIS for codes not on the kitting plan

Sheet Kitting Plan
A1: KITTING PLAN — QTY TO BUILD ONE REPEATER
A2: Source: kitting plan supplied by the user. Blue cells are inputs.
A3: Contract repeaters | C3: 13
A5: Sequence | B5: Assy Code | C5: Assy Description | D5: Qty per Repeater | E5: Contract Qty
A6: LASER ASSY | B6: 92YLS00548BAA | C6: R5B LASER ASSEMBLY 4P BOAT 1 - E2A | D6: 1 | E6: =D6*$C$3 -> 13
A7: LASER ASSY | B7: 92YLS00548BBA | C7: R5B LASER ASSEMBLY 4P BOAT 2/3 - E2A | D7: 2 | E7: =D7*$C$3 -> 26
A8: PSB ASSY | B8: 91YAF03404AAA | C8: R5B PSB SUB ASSEMBLY 4P-4FP | D8: 3 | E8: =D8*$C$3 -> 39
A9: OPF ASSY | B9: 92YFD04548BAA | C9: R5B OPF ASSEMBLY (4P-4FP) BOAT 1 - E2A | D9: 1 | E9: =D9*$C$3 -> 13
A10: OPF ASSY | B10: 92YFD04548BBA | C10: R5B OPF ASSEMBLY (4P-4FP) BOAT 2/3 - E2A | D10: 2 | E10: =D10*$C$3 -> 26
A11: POB ASSY | B11: 92YWS04548AAA | C11: R5B 4FP POB LUMENTUM SUB ASSEMBLY - E2A | D11: 3 | E11: =D11*$C$3 -> 39
A12: ERBIUM ASSY | B12: 92RRA00548AAA | C12: R5B ERBIUM SPOOL ASSEMBLY - E2A | D12: 24 | E12: =D12*$C$3 -> 312
A13: ERBIUM ASSY | B13: 92YRA01548AAA | C13: R5B ERBIUM ASSEMBLY POSITION 1 | D13: 3 | E13: =D13*$C$3 -> 39
A14: ERBIUM ASSY | B14: 92YRA02548AAA | C14: R5B ERBIUM ASSEMBLY POSITION 2 | D14: 3 | E14: =D14*$C$3 -> 39
A15: ERBIUM ASSY | B15: 92YRA03548AAA | C15: R5B ERBIUM ASSEMBLY POSITION 3 | D15: 3 | E15: =D15*$C$3 -> 39
A16: ERBIUM ASSY | B16: 92YRA04548AAA | C16: R5B ERBIUM ASSEMBLY POSITION 4 | D16: 3 | E16: =D16*$C$3 -> 39
A17: BOAT ASSY | B17: 92UAP04548BAA | C17: R5B BOAT 1 ASSY (4P-4FP) | D17: 1 | E17: =D17*$C$3 -> 13
... A19: BOAT ASSY | B19: 92UAP04548BCA | C19: R5B BOAT 3 ASSY (4P-4FP) | D19: 1 | E19: =D19*$C$3 -> 13

Sheet COOIS Data
A1: COOIS DATA — READ AUTOMATICALLY FROM 'COOIS Raw'
A2: Do not type here. Paste the COOIS export into 'COOIS Raw' (cell A1, with headers). Everything below recalculates.
A3: Column found in COOIS Raw:
A4: =IFERROR(MATCH("Order",'COOIS Raw'!$1:$1,0),0) -> 1 | B4: =IFERROR(MATCH("Material Number",'COOIS Raw'!$1:$1,0),0) -> 3 | C4: =IFERROR(MATCH("Material desc*",'COOIS Raw'!$1:$1,0),0) -> 4 | D4: =IFERROR(MATCH("Order quantity*",'COOIS Raw'!$1:$1,0),0) -> 7 | E4: =IFERROR(MATCH("System Status",'COOIS Raw'!$1:$1,0),0) -> 15 | F4: =IFERROR(MATCH("Release date*",'COOIS Raw'!$1:$1,0),0) -> 9
A5: WO (Order) | B5: Assy Code | C5: Description | D5: Qty | E5: SAP System Status | F5: Release Date | G5: In Plan | H5: Qty / Rep | I5: Kitted (PRT) | J5: Issued (GMPS) | K5: Delivered (DLV) | L5: Stage | M5: Seq # in Code | N5: Repeater # | O5: Contract
A6: =IF(OR($A$4=0,INDEX('COOIS Raw'!$A:$GZ,ROW()-4,$A$4)=""),"",IFERROR(--INDEX('COOIS Raw'!$A:$GZ,ROW()-4,$A$4),INDEX('COOIS Raw'!$A:$GZ,ROW()-4,$A$4))) -> 100880307 | B6: =IF(A6="","",TRIM(INDEX('COOIS Raw'!$A:$GZ,ROW()-4,$B$4))) -> 92YRA01548AAA | C6: =IF(OR(A6="",$C$4=0),"",INDEX('COOIS Raw'!$A:$GZ,ROW()-4,$C$4)) -> R5B ERBIUM ASSEMBLY 1 | D6: =IF(A6="","",IF($D$4=0,1,IFERROR(--INDEX('COOIS Raw'!$A:$GZ,ROW()-4,$D$4),1))) -> 1 | E6: =IF(A6="","",INDEX('COOIS Raw'!$A:$GZ,ROW()-4,$E$4)&"") -> REL PRT PCNF PRC GMPS MANC SETC | F6: =IF(A6="","",IFERROR(DATEVALUE(INDEX('COOIS Raw'!$A:$GZ,ROW()-4,$F$4)),INDEX('COOIS Raw'!$A:$GZ,ROW()-4,$F$4))) -> 46298 | G6: =IF(A6="","",IF(ISNA(MATCH(B6,'Kitting Plan'!$B$6:$B$19,0)),"Not in plan","Yes")) -> Yes | H6: =IF(G6="Yes",INDEX('Kitting Plan'!$D$6:$D$19,MATCH(B6,'Kitting Plan'!$B$6:$B$19,0)),"") -> 3 | I6: =IF(A6="","",IF(ISNUMBER(SEARCH("PRT",E6)),D6,0)) -> 1 | J6: =IF(A6="","",IF(ISNUMBER(SEARCH("GMPS",E6)),D6,0)) -> 1 | K6: =IF(A6="","",IF(ISNUMBER(SEARCH("DLV",E6)),D6,0)) -> 0 | L6: =IF(A6="","",IF(K6>0,"Delivered",IF(ISNUMBER(SEARCH("CNF",E6)),"In production",IF(J6>0,"Issued",IF(I6>0,"Kitted","Released"))))) -> In production | M6: =IF(G6<>"Yes","",COUNTIFS($B$6:$B$1505,B6,$F$6:$F$1505,"<"&F6)+COUNTIFS($B$6:$B$1505,B6,$F$6:$F$1505,F6,$A$6:$A$1505,"<="&A6)) -> 40 | N6: =IF(M6="","",ROUNDUP(M6/H6,0)) -> 14 | O6: =IF(N6="","",IF(N6<='Kitting Plan'!$C$3,"Rep "&N6,"Surplus")) -> Surplus
A7: =IF(OR($A$4=0,INDEX('COOIS Raw'!$A:$GZ,ROW()-4,$A$4)=""),"",IFERROR(--INDEX('COOIS Raw'!$A:$GZ,ROW()-4,$A$4),INDEX('COOIS Raw'!$A:$GZ,ROW()-4,$A$4))) -> 100880184 | B7: =IF(A7="","",TRIM(INDEX('COOIS Raw'!$A:$GZ,ROW()-4,$B$4))) -> 92YLS00548BAA | C7: =IF(OR(A7="",$C$4=0),"",INDEX('COOIS Raw'!$A:$GZ,ROW()-4,$C$4)) -> R5B LASER ASSEMBLY 4P BOAT 1 - E2A | D7: =IF(A7="","",IF($D$4=0,1,IFERROR(--INDEX('COOIS Raw'!$A:$GZ,ROW()-4,$D$4),1))) -> 1 | E7: =IF(A7="","",INDEX('COOIS Raw'!$A:$GZ,ROW()-4,$E$4)&"") -> REL PRT PRC MANC SETC | F7: =IF(A7="","",IFERROR(DATEVALUE(INDEX('COOIS Raw'!$A:$GZ,ROW()-4,$F$4)),INDEX('COOIS Raw'!$A:$GZ,ROW()-4,$F$4))) -> 46297 | G7: =IF(A7="","",IF(ISNA(MATCH(B7,'Kitting Plan'!$B$6:$B$19,0)),"Not in plan","Yes")) -> Yes | H7: =IF(G7="Yes",INDEX('Kitting Plan'!$D$6:$D$19,MATCH(B7,'Kitting Plan'!$B$6:$B$19,0)),"") -> 1 | I7: =IF(A7="","",IF(ISNUMBER(SEARCH("PRT",E7)),D7,0)) -> 1 | J7: =IF(A7="","",IF(ISNUMBER(SEARCH("GMPS",E7)),D7,0)) -> 0 | K7: =IF(A7="","",IF(ISNUMBER(SEARCH("DLV",E7)),D7,0)) -> 0 | L7: =IF(A7="","",IF(K7>0,"Delivered",IF(ISNUMBER(SEARCH("CNF",E7)),"In production",IF(J7>0,"Issued",IF(I7>0,"Kitted","Released"))))) -> Kitted | M7: =IF(G7<>"Yes","",COUNTIFS($B$6:$B$1505,B7,$F$6:$F$1505,"<"&F7)+COUNTIFS($B$6:$B$1505,B7,$F$6:$F$1505,F7,$A$6:$A$1505,"<="&A7)) -> 13 | N7: =IF(M7="","",ROUNDUP(M7/H7,0)) -> 13 | O7: =IF(N7="","",IF(N7<='Kitting Plan'!$C$3,"Rep "&N7,"Surplus")) -> Rep 13
A8: =IF(OR($A$4=0,INDEX('COOIS Raw'!$A:$GZ,ROW()-4,$A$4)=""),"",IFERROR(--INDEX('COOIS Raw'!$A:$GZ,ROW()-4,$A$4),INDEX('COOIS Raw'!$A:$GZ,ROW()-4,$A$4))) -> 100880185 | B8: =IF(A8="","",TRIM(INDEX('COOIS Raw'!$A:$GZ,ROW()-4,$B$4))) -> 92YLS00548BBA | C8: =IF(OR(A8="",$C$4=0),"",INDEX('COOIS Raw'!$A:$GZ,ROW()-4,$C$4)) -> R5B LASER ASSEMBLY 4P BOAT 2/3 - E2A | D8: =IF(A8="","",IF($D$4=0,1,IFERROR(--INDEX('COOIS Raw'!$A:$GZ,ROW()-4,$D$4),1))) -> 1 | E8: =IF(A8="","",INDEX('COOIS Raw'!$A:$GZ,ROW()-4,$E$4)&"") -> REL PRT PRC MANC SETC | F8: =IF(A8="","",IFERROR(DATEVALUE(INDEX('COOIS Raw'!$A:$GZ,ROW()-4,$F$4)),INDEX('COOIS Raw'!$A:$GZ,ROW()-4,$F$4))) -> 46297 | G8: =IF(A8="","",IF(ISNA(MATCH(B8,'Kitting Plan'!$B$6:$B$19,0)),"Not in plan","Yes")) -> Yes | H8: =IF(G8="Yes",INDEX('Kitting Plan'!$D$6:$D$19,MATCH(B8,'Kitting Plan'!$B$6:$B$19,0)),"") -> 2 | I8: =IF(A8="","",IF(ISNUMBER(SEARCH("PRT",E8)),D8,0)) -> 1 | J8: =IF(A8="","",IF(ISNUMBER(SEARCH("GMPS",E8)),D8,0)) -> 0 | K8: =IF(A8="","",IF(ISNUMBER(SEARCH("DLV",E8)),D8,0)) -> 0 | L8: =IF(A8="","",IF(K8>0,"Delivered",IF(ISNUMBER(SEARCH("CNF",E8)),"In production",IF(J8>0,"Issued",IF(I8>0,"Kitted","Released"))))) -> Kitted | M8: =IF(G8<>"Yes","",COUNTIFS($B$6:$B$1505,B8,$F$6:$F$1505,"<"&F8)+COUNTIFS($B$6:$B$1505,B8,$F$6:$F$1505,F8,$A$6:$A$1505,"<="&A8)) -> 23 | N8: =IF(M8="","",ROUNDUP(M8/H8,0)) -> 12 | O8: =IF(N8="","",IF(N8<='Kitting Plan'!$C$3,"Rep "&N8,"Surplus")) -> Rep 12
A9: =IF(OR($A$4=0,INDEX('COOIS Raw'!$A:$GZ,ROW()-4,$A$4)=""),"",IFERROR(--INDEX('COOIS Raw'!$A:$GZ,ROW()-4,$A$4),INDEX('COOIS Raw'!$A:$GZ,ROW()-4,$A$4))) -> 100880186 | B9: =IF(A9="","",TRIM(INDEX('COOIS Raw'!$A:$GZ,ROW()-4,$B$4))) -> 92YLS00548BBA | C9: =IF(OR(A9="",$C$4=0),"",INDEX('COOIS Raw'!$A:$GZ,ROW()-4,$C$4)) -> R5B LASER ASSEMBLY 4P BOAT 2/3 - E2A | D9: =IF(A9="","",IF($D$4=0,1,IFERROR(--INDEX('COOIS Raw'!$A:$GZ,ROW()-4,$D$4),1))) -> 1 | E9: =IF(A9="","",INDEX('COOIS Raw'!$A:$GZ,ROW()-4,$E$4)&"") -> REL PRT PRC MANC SETC | F9: =IF(A9="","",IFERROR(DATEVALUE(INDEX('COOIS Raw'!$A:$GZ,ROW()-4,$F$4)),INDEX('COOIS Raw'!$A:$GZ,ROW()-4,$F$4))) -> 46297 | G9: =IF(A9="","",IF(ISNA(MATCH(B9,'Kitting Plan'!$B$6:$B$19,0)),"Not in plan","Yes")) -> Yes | H9: =IF(G9="Yes",INDEX('Kitting Plan'!$D$6:$D$19,MATCH(B9,'Kitting Plan'!$B$6:$B$19,0)),"") -> 2 | I9: =IF(A9="","",IF(ISNUMBER(SEARCH("PRT",E9)),D9,0)) -> 1 | J9: =IF(A9="","",IF(ISNUMBER(SEARCH("GMPS",E9)),D9,0)) -> 0 | K9: =IF(A9="","",IF(ISNUMBER(SEARCH("DLV",E9)),D9,0)) -> 0 | L9: =IF(A9="","",IF(K9>0,"Delivered",IF(ISNUMBER(SEARCH("CNF",E9)),"In production",IF(J9>0,"Issued",IF(I9>0,"Kitted","Released"))))) -> Kitted | M9: =IF(G9<>"Yes","",COUNTIFS($B$6:$B$1505,B9,$F$6:$F$1505,"<"&F9)+COUNTIFS($B$6:$B$1505,B9,$F$6:$F$1505,F9,$A$6:$A$1505,"<="&A9)) -> 24 | N9: =IF(M9="","",ROUNDUP(M9/H9,0)) -> 12 | O9: =IF(N9="","",IF(N9<='Kitting Plan'!$C$3,"Rep "&N9,"Surplus")) -> Rep 12
A10: =IF(OR($A$4=0,INDEX('COOIS Raw'!$A:$GZ,ROW()-4,$A$4)=""),"",IFERROR(--INDEX('COOIS Raw'!$A:$GZ,ROW()-4,$A$4),INDEX('COOIS Raw'!$A:$GZ,ROW()-4,$A$4))) -> 100880187 | B10: =IF(A10="","",TRIM(INDEX('COOIS Raw'!$A:$GZ,ROW()-4,$B$4))) -> 91YAF03404AAA | C10: =IF(OR(A10="",$C$4=0),"",INDEX('COOIS Raw'!$A:$GZ,ROW()-4,$C$4)) -> R5B PSB SUB ASSEMBLY 4P-4FP | D10: =IF(A10="","",IF($D$4=0,1,IFERROR(--INDEX('COOIS Raw'!$A:$GZ,ROW()-4,$D$4),1))) -> 1 | E10: =IF(A10="","",INDEX('COOIS Raw'!$A:$GZ,ROW()-4,$E$4)&"") -> REL PRT PRC MANC SETC | F10: =IF(A10="","",IFERROR(DATEVALUE(INDEX('COOIS Raw'!$A:$GZ,ROW()-4,$F$4)),INDEX('COOIS Raw'!$A:$GZ,ROW()-4,$F$4))) -> 46297 | G10: =IF(A10="","",IF(ISNA(MATCH(B10,'Kitting Plan'!$B$6:$B$19,0)),"Not in plan","Yes")) -> Yes | H10: =IF(G10="Yes",INDEX('Kitting Plan'!$D$6:$D$19,MATCH(B10,'Kitting Plan'!$B$6:$B$19,0)),"") -> 3 | I10: =IF(A10="","",IF(ISNUMBER(SEARCH("PRT",E10)),D10,0)) -> 1 | J10: =IF(A10="","",IF(ISNUMBER(SEARCH("GMPS",E10)),D10,0)) -> 0 | K10: =IF(A10="","",IF(ISNUMBER(SEARCH("DLV",E10)),D10,0)) -> 0 | L10: =IF(A10="","",IF(K10>0,"Delivered",IF(ISNUMBER(SEARCH("CNF",E10)),"In production",IF(J10>0,"Issued",IF(I10>0,"Kitted","Released"))))) -> Kitted | M10: =IF(G10<>"Yes","",COUNTIFS($B$6:$B$1505,B10,$F$6:$F$1505,"<"&F10)+COUNTIFS($B$6:$B$1505,B10,$F$6:$F$1505,F10,$A$6:$A$1505,"<="&A10)) -> 46 | N10: =IF(M10="","",ROUNDUP(M10/H10,0)) -> 16 | O10: =IF(N10="","",IF(N10<='Kitting Plan'!$C$3,"Rep "&N10,"Surplus")) -> Surplus
A11: =IF(OR($A$4=0,INDEX('COOIS Raw'!$A:$GZ,ROW()-4,$A$4)=""),"",IFERROR(--INDEX('COOIS Raw'!$A:$GZ,ROW()-4,$A$4),INDEX('COOIS Raw'!$A:$GZ,ROW()-4,$A$4))) -> 100880188 | B11: =IF(A11="","",TRIM(INDEX('COOIS Raw'!$A:$GZ,ROW()-4,$B$4))) -> 91YAF03404AAA | C11: =IF(OR(A11="",$C$4=0),"",INDEX('COOIS Raw'!$A:$GZ,ROW()-4,$C$4)) -> R5B PSB SUB ASSEMBLY 4P-4FP | D11: =IF(A11="","",IF($D$4=0,1,IFERROR(--INDEX('COOIS Raw'!$A:$GZ,ROW()-4,$D$4),1))) -> 1 | E11: =IF(A11="","",INDEX('COOIS Raw'!$A:$GZ,ROW()-4,$E$4)&"") -> REL PRT PRC MANC SETC | F11: =IF(A11="","",IFERROR(DATEVALUE(INDEX('COOIS Raw'!$A:$GZ,ROW()-4,$F$4)),INDEX('COOIS Raw'!$A:$GZ,ROW()-4,$F$4))) -> 46297 | G11: =IF(A11="","",IF(ISNA(MATCH(B11,'Kitting Plan'!$B$6:$B$19,0)),"Not in plan","Yes")) -> Yes | H11: =IF(G11="Yes",INDEX('Kitting Plan'!$D$6:$D$19,MATCH(B11,'Kitting Plan'!$B$6:$B$19,0)),"") -> 3 | I11: =IF(A11="","",IF(ISNUMBER(SEARCH("PRT",E11)),D11,0)) -> 1 | J11: =IF(A11="","",IF(ISNUMBER(SEARCH("GMPS",E11)),D11,0)) -> 0 | K11: =IF(A11="","",IF(ISNUMBER(SEARCH("DLV",E11)),D11,0)) -> 0 | L11: =IF(A11="","",IF(K11>0,"Delivered",IF(ISNUMBER(SEARCH("CNF",E11)),"In production",IF(J11>0,"Issued",IF(I11>0,"Kitted","Released"))))) -> Kitted | M11: =IF(G11<>"Yes","",COUNTIFS($B$6:$B$1505,B11,$F$6:$F$1505,"<"&F11)+COUNTIFS($B$6:$B$1505,B11,$F$6:$F$1505,F11,$A$6:$A$1505,"<="&A11)) -> 47 | N11: =IF(M11="","",ROUNDUP(M11/H11,0)) -> 16 | O11: =IF(N11="","",IF(N11<='Kitting Plan'!$C$3,"Rep "&N11,"Surplus")) -> Surplus
A12: =IF(OR($A$4=0,INDEX('COOIS Raw'!$A:$GZ,ROW()-4,$A$4)=""),"",IFERROR(--INDEX('COOIS Raw'!$A:$GZ,ROW()-4,$A$4),INDEX('COOIS Raw'!$A:$GZ,ROW()-4,$A$4))) -> 100880189 | B12: =IF(A12="","",TRIM(INDEX('COOIS Raw'!$A:$GZ,ROW()-4,$B$4))) -> 91YAF03404AAA | C12: =IF(OR(A12="",$C$4=0),"",INDEX('COOIS Raw'!$A:$GZ,ROW()-4,$C$4)) -> R5B PSB SUB ASSEMBLY 4P-4FP | D12: =IF(A12="","",IF($D$4=0,1,IFERROR(--INDEX('COOIS Raw'!$A:$GZ,ROW()-4,$D$4),1))) -> 1 | E12: =IF(A12="","",INDEX('COOIS Raw'!$A:$GZ,ROW()-4,$E$4)&"") -> REL PRT PRC MANC SETC | F12: =IF(A12="","",IFERROR(DATEVALUE(INDEX('COOIS Raw'!$A:$GZ,ROW()-4,$F$4)),INDEX('COOIS Raw'!$A:$GZ,ROW()-4,$F$4))) -> 46297 | G12: =IF(A12="","",IF(ISNA(MATCH(B12,'Kitting Plan'!$B$6:$B$19,0)),"Not in plan","Yes")) -> Yes | H12: =IF(G12="Yes",INDEX('Kitting Plan'!$D$6:$D$19,MATCH(B12,'Kitting Plan'!$B$6:$B$19,0)),"") -> 3 | I12: =IF(A12="","",IF(ISNUMBER(SEARCH("PRT",E12)),D12,0)) -> 1 | J12: =IF(A12="","",IF(ISNUMBER(SEARCH("GMPS",E12)),D12,0)) -> 0 | K12: =IF(A12="","",IF(ISNUMBER(SEARCH("DLV",E12)),D12,0)) -> 0 | L12: =IF(A12="","",IF(K12>0,"Delivered",IF(ISNUMBER(SEARCH("CNF",E12)),"In production",IF(J12>0,"Issued",IF(I12>0,"Kitted","Released"))))) -> Kitted | M12: =IF(G12<>"Yes","",COUNTIFS($B$6:$B$1505,B12,$F$6:$F$1505,"<"&F12)+COUNTIFS($B$6:$B$1505,B12,$F$6:$F$1505,F12,$A$6:$A$1505,"<="&A12)) -> 48 | N12: =IF(M12="","",ROUNDUP(M12/H12,0)) -> 16 | O12: =IF(N12="","",IF(N12<='Kitting Plan'!$C$3,"Rep "&N12,"Surplus")) -> Surplus
A13: =IF(OR($A$4=0,INDEX('COOIS Raw'!$A:$GZ,ROW()-4,$A$4)=""),"",IFERROR(--INDEX('COOIS Raw'!$A:$GZ,ROW()-4,$A$4),INDEX('COOIS Raw'!$A:$GZ,ROW()-4,$A$4))) -> 100880190 | B13: =IF(A13="","",TRIM(INDEX('COOIS Raw'!$A:$GZ,ROW()-4,$B$4))) -> 92YFD04548BAA | C13: =IF(OR(A13="",$C$4=0),"",INDEX('COOIS Raw'!$A:$GZ,ROW()-4,$C$4)) -> R5B OPF ASSEMBLY (4P-4FP) BOAT 1 - E2A | D13: =IF(A13="","",IF($D$4=0,1,IFERROR(--INDEX('COOIS Raw'!$A:$GZ,ROW()-4,$D$4),1))) -> 1 | E13: =IF(A13="","",INDEX('COOIS Raw'!$A:$GZ,ROW()-4,$E$4)&"") -> REL PRT PRC MANC SETC | F13: =IF(A13="","",IFERROR(DATEVALUE(INDEX('COOIS Raw'!$A:$GZ,ROW()-4,$F$4)),INDEX('COOIS Raw'!$A:$GZ,ROW()-4,$F$4))) -> 46297 | G13: =IF(A13="","",IF(ISNA(MATCH(B13,'Kitting Plan'!$B$6:$B$19,0)),"Not in plan","Yes")) -> Yes | H13: =IF(G13="Yes",INDEX('Kitting Plan'!$D$6:$D$19,MATCH(B13,'Kitting Plan'!$B$6:$B$19,0)),"") -> 1 | I13: =IF(A13="","",IF(ISNUMBER(SEARCH("PRT",E13)),D13,0)) -> 1 | J13: =IF(A13="","",IF(ISNUMBER(SEARCH("GMPS",E13)),D13,0)) -> 0 | K13: =IF(A13="","",IF(ISNUMBER(SEARCH("DLV",E13)),D13,0)) -> 0 | L13: =IF(A13="","",IF(K13>0,"Delivered",IF(ISNUMBER(SEARCH("CNF",E13)),"In production",IF(J13>0,"Issued",IF(I13>0,"Kitted","Released"))))) -> Kitted | M13: =IF(G13<>"Yes","",COUNTIFS($B$6:$B$1505,B13,$F$6:$F$1505,"<"&F13)+COUNTIFS($B$6:$B$1505,B13,$F$6:$F$1505,F13,$A$6:$A$1505,"<="&A13)) -> 13 | N13: =IF(M13="","",ROUNDUP(M13/H13,0)) -> 13 | O13: =IF(N13="","",IF(N13<='Kitting Plan'!$C$3,"Rep "&N13,"Surplus")) -> Rep 13
A14: =IF(OR($A$4=0,INDEX('COOIS Raw'!$A:$GZ,ROW()-4,$A$4)=""),"",IFERROR(--INDEX('COOIS Raw'!$A:$GZ,ROW()-4,$A$4),INDEX('COOIS Raw'!$A:$GZ,ROW()-4,$A$4))) -> 100880191 | B14: =IF(A14="","",TRIM(INDEX('COOIS Raw'!$A:$GZ,ROW()-4,$B$4))) -> 92YFD04548BBA | C14: =IF(OR(A14="",$C$4=0),"",INDEX('COOIS Raw'!$A:$GZ,ROW()-4,$C$4)) -> R5B OPF ASSEMBLY (4P-4FP) BOAT 2/3 - E2A | D14: =IF(A14="","",IF($D$4=0,1,IFERROR(--INDEX('COOIS Raw'!$A:$GZ,ROW()-4,$D$4),1))) -> 1 | E14: =IF(A14="","",INDEX('COOIS Raw'!$A:$GZ,ROW()-4,$E$4)&"") -> REL PRT PRC MANC SETC | F14: =IF(A14="","",IFERROR(DATEVALUE(INDEX('COOIS Raw'!$A:$GZ,ROW()-4,$F$4)),INDEX('COOIS Raw'!$A:$GZ,ROW()-4,$F$4))) -> 46297 | G14: =IF(A14="","",IF(ISNA(MATCH(B14,'Kitting Plan'!$B$6:$B$19,0)),"Not in plan","Yes")) -> Yes | H14: =IF(G14="Yes",INDEX('Kitting Plan'!$D$6:$D$19,MATCH(B14,'Kitting Plan'!$B$6:$B$19,0)),"") -> 2 | I14: =IF(A14="","",IF(ISNUMBER(SEARCH("PRT",E14)),D14,0)) -> 1 | J14: =IF(A14="","",IF(ISNUMBER(SEARCH("GMPS",E14)),D14,0)) -> 0 | K14: =IF(A14="","",IF(ISNUMBER(SEARCH("DLV",E14)),D14,0)) -> 0 | L14: =IF(A14="","",IF(K14>0,"Delivered",IF(ISNUMBER(SEARCH("CNF",E14)),"In production",IF(J14>0,"Issued",IF(I14>0,"Kitted","Released"))))) -> Kitted | M14: =IF(G14<>"Yes","",COUNTIFS($B$6:$B$1505,B14,$F$6:$F$1505,"<"&F14)+COUNTIFS($B$6:$B$1505,B14,$F$6:$F$1505,F14,$A$6:$A$1505,"<="&A14)) -> 23 | N14: =IF(M14="","",ROUNDUP(M14/H14,0)) -> 12 | O14: =IF(N14="","",IF(N14<='Kitting Plan'!$C$3,"Rep "&N14,"Surplus")) -> Rep 12
A15: =IF(OR($A$4=0,INDEX('COOIS Raw'!$A:$GZ,ROW()-4,$A$4)=""),"",IFERROR(--INDEX('COOIS Raw'!$A:$GZ,ROW()-4,$A$4),INDEX('COOIS Raw'!$A:$GZ,ROW()-4,$A$4))) -> 100880192 | B15: =IF(A15="","",TRIM(INDEX('COOIS Raw'!$A:$GZ,ROW()-4,$B$4))) -> 92YFD04548BBA | C15: =IF(OR(A15="",$C$4=0),"",INDEX('COOIS Raw'!$A:$GZ,ROW()-4,$C$4)) -> R5B OPF ASSEMBLY (4P-4FP) BOAT 2/3 - E2A | D15: =IF(A15="","",IF($D$4=0,1,IFERROR(--INDEX('COOIS Raw'!$A:$GZ,ROW()-4,$D$4),1))) -> 1 | E15: =IF(A15="","",INDEX('COOIS Raw'!$A:$GZ,ROW()-4,$E$4)&"") -> REL PRT PRC MANC SETC | F15: =IF(A15="","",IFERROR(DATEVALUE(INDEX('COOIS Raw'!$A:$GZ,ROW()-4,$F$4)),INDEX('COOIS Raw'!$A:$GZ,ROW()-4,$F$4))) -> 46297 | G15: =IF(A15="","",IF(ISNA(MATCH(B15,'Kitting Plan'!$B$6:$B$19,0)),"Not in plan","Yes")) -> Yes | H15: =IF(G15="Yes",INDEX('Kitting Plan'!$D$6:$D$19,MATCH(B15,'Kitting Plan'!$B$6:$B$19,0)),"") -> 2 | I15: =IF(A15="","",IF(ISNUMBER(SEARCH("PRT",E15)),D15,0)) -> 1 | J15: =IF(A15="","",IF(ISNUMBER(SEARCH("GMPS",E15)),D15,0)) -> 0 | K15: =IF(A15="","",IF(ISNUMBER(SEARCH("DLV",E15)),D15,0)) -> 0 | L15: =IF(A15="","",IF(K15>0,"Delivered",IF(ISNUMBER(SEARCH("CNF",E15)),"In production",IF(J15>0,"Issued",IF(I15>0,"Kitted","Released"))))) -> Kitted | M15: =IF(G15<>"Yes","",COUNTIFS($B$6:$B$1505,B15,$F$6:$F$1505,"<"&F15)+COUNTIFS($B$6:$B$1505,B15,$F$6:$F$1505,F15,$A$6:$A$1505,"<="&A15)) -> 24 | N15: =IF(M15="","",ROUNDUP(M15/H15,0)) -> 12 | O15: =IF(N15="","",IF(N15<='Kitting Plan'!$C$3,"Rep "&N15,"Surplus")) -> Rep 12
A16: =IF(OR($A$4=0,INDEX('COOIS Raw'!$A:$GZ,ROW()-4,$A$4)=""),"",IFERROR(--INDEX('COOIS Raw'!$A:$GZ,ROW()-4,$A$4),INDEX('COOIS Raw'!$A:$GZ,ROW()-4,$A$4))) -> 100880193 | B16: =IF(A16="","",TRIM(INDEX('COOIS Raw'!$A:$GZ,ROW()-4,$B$4))) -> 92YWS04548AAA | C16: =IF(OR(A16="",$C$4=0),"",INDEX('COOIS Raw'!$A:$GZ,ROW()-4,$C$4)) -> R5B 4FP POB LUMENTUM SUB ASSEMBLY - E2A | D16: =IF(A16="","",IF($D$4=0,1,IFERROR(--INDEX('COOIS Raw'!$A:$GZ,ROW()-4,$D$4),1))) -> 1 | E16: =IF(A16="","",INDEX('COOIS Raw'!$A:$GZ,ROW()-4,$E$4)&"") -> REL PRT PRC MANC SETC | F16: =IF(A16="","",IFERROR(DATEVALUE(INDEX('COOIS Raw'!$A:$GZ,ROW()-4,$F$4)),INDEX('COOIS Raw'!$A:$GZ,ROW()-4,$F$4))) -> 46297 | G16: =IF(A16="","",IF(ISNA(MATCH(B16,'Kitting Plan'!$B$6:$B$19,0)),"Not in plan","Yes")) -> Yes | H16: =IF(G16="Yes",INDEX('Kitting Plan'!$D$6:$D$19,MATCH(B16,'Kitting Plan'!$B$6:$B$19,0)),"") -> 3 | I16: =IF(A16="","",IF(ISNUMBER(SEARCH("PRT",E16)),D16,0)) -> 1 | J16: =IF(A16="","",IF(ISNUMBER(SEARCH("GMPS",E16)),D16,0)) -> 0 | K16: =IF(A16="","",IF(ISNUMBER(SEARCH("DLV",E16)),D16,0)) -> 0 | L16: =IF(A16="","",IF(K16>0,"Delivered",IF(ISNUMBER(SEARCH("CNF",E16)),"In production",IF(J16>0,"Issued",IF(I16>0,"Kitted","Released"))))) -> Kitted | M16: =IF(G16<>"Yes","",COUNTIFS($B$6:$B$1505,B16,$F$6:$F$1505,"<"&F16)+COUNTIFS($B$6:$B$1505,B16,$F$6:$F$1505,F16,$A$6:$A$1505,"<="&A16)) -> 34 | N16: =IF(M16="","",ROUNDUP(M16/H16,0)) -> 12 | O16: =IF(N16="","",IF(N16<='Kitting Plan'!$C$3,"Rep "&N16,"Surplus")) -> Rep 12
A17: =IF(OR($A$4=0,INDEX('COOIS Raw'!$A:$GZ,ROW()-4,$A$4)=""),"",IFERROR(--INDEX('COOIS Raw'!$A:$GZ,ROW()-4,$A$4),INDEX('COOIS Raw'!$A:$GZ,ROW()-4,$A$4))) -> 100880194 | B17: =IF(A17="","",TRIM(INDEX('COOIS Raw'!$A:$GZ,ROW()-4,$B$4))) -> 92YWS04548AAA | C17: =IF(OR(A17="",$C$4=0),"",INDEX('COOIS Raw'!$A:$GZ,ROW()-4,$C$4)) -> R5B 4FP POB LUMENTUM SUB ASSEMBLY - E2A | D17: =IF(A17="","",IF($D$4=0,1,IFERROR(--INDEX('COOIS Raw'!$A:$GZ,ROW()-4,$D$4),1))) -> 1 | E17: =IF(A17="","",INDEX('COOIS Raw'!$A:$GZ,ROW()-4,$E$4)&"") -> REL PRT PRC MANC SETC | F17: =IF(A17="","",IFERROR(DATEVALUE(INDEX('COOIS Raw'!$A:$GZ,ROW()-4,$F$4)),INDEX('COOIS Raw'!$A:$GZ,ROW()-4,$F$4))) -> 46297 | G17: =IF(A17="","",IF(ISNA(MATCH(B17,'Kitting Plan'!$B$6:$B$19,0)),"Not in plan","Yes")) -> Yes | H17: =IF(G17="Yes",INDEX('Kitting Plan'!$D$6:$D$19,MATCH(B17,'Kitting Plan'!$B$6:$B$19,0)),"") -> 3 | I17: =IF(A17="","",IF(ISNUMBER(SEARCH("PRT",E17)),D17,0)) -> 1 | J17: =IF(A17="","",IF(ISNUMBER(SEARCH("GMPS",E17)),D17,0)) -> 0 | K17: =IF(A17="","",IF(ISNUMBER(SEARCH("DLV",E17)),D17,0)) -> 0 | L17: =IF(A17="","",IF(K17>0,"Delivered",IF(ISNUMBER(SEARCH("CNF",E17)),"In production",IF(J17>0,"Issued",IF(I17>0,"Kitted","Released"))))) -> Kitted | M17: =IF(G17<>"Yes","",COUNTIFS($B$6:$B$1505,B17,$F$6:$F$1505,"<"&F17)+COUNTIFS($B$6:$B$1505,B17,$F$6:$F$1505,F17,$A$6:$A$1505,"<="&A17)) -> 35 | N17: =IF(M17="","",ROUNDUP(M17/H17,0)) -> 12 | O17: =IF(N17="","",IF(N17<='Kitting Plan'!$C$3,"Rep "&N17,"Surplus")) -> Rep 12
... A1505: =IF(OR($A$4=0,INDEX('COOIS Raw'!$A:$GZ,ROW()-4,$A$4)=""),"",IFERROR(--INDEX('COOIS Raw'!$A:$GZ,ROW()-4,$A$4),INDEX('COOIS Raw'!$A:$GZ,ROW()-4,$A$4))) | B1505: =IF(A1505="","",TRIM(INDEX('COOIS Raw'!$A:$GZ,ROW()-4,$B$4))) | C1505: =IF(OR(A1505="",$C$4=0),"",INDEX('COOIS Raw'!$A:$GZ,ROW()-4,$C$4)) | D1505: =IF(A1505="","",IF($D$4=0,1,IFERROR(--INDEX('COOIS Raw'!$A:$GZ,ROW()-4,$D$4),1))) | E1505: =IF(A1505="","",INDEX('COOIS Raw'!$A:$GZ,ROW()-4,$E$4)&"") | F1505: =IF(A1505="","",IFERROR(DATEVALUE(INDEX('COOIS Raw'!$A:$GZ,ROW()-4,$F$4)),INDEX('COOIS Raw'!$A:$GZ,ROW()-4,$F$4))) | G1505: =IF(A1505="","",IF(ISNA(MATCH(B1505,'Kitting Plan'!$B$6:$B$19,0)),"Not in plan","Yes")) | H1505: =IF(G1505="Yes",INDEX('Kitting Plan'!$D$6:$D$19,MATCH(B1505,'Kitting Plan'!$B$6:$B$19,0)),"") | I1505: =IF(A1505="","",IF(ISNUMBER(SEARCH("PRT",E1505)),D1505,0)) | J1505: =IF(A1505="","",IF(ISNUMBER(SEARCH("GMPS",E1505)),D1505,0)) | K1505: =IF(A1505="","",IF(ISNUMBER(SEARCH("DLV",E1505)),D1505,0)) | L1505: =IF(A1505="","",IF(K1505>0,"Delivered",IF(ISNUMBER(SEARCH("CNF",E1505)),"In production",IF(J1505>0,"Issued",IF(I1505>0,"Kitted","Released"))))) | M1505: =IF(G1505<>"Yes","",COUNTIFS($B$6:$B$1505,B1505,$F$6:$F$1505,"<"&F1505)+COUNTIFS($B$6:$B$1505,B1505,$F$6:$F$1505,F1505,$A$6:$A$1505,"<="&A1505)) | N1505: =IF(M1505="","",ROUNDUP(M1505/H1505,0)) | O1505: =IF(N1505="","",IF(N1505<='Kitting Plan'!$C$3,"Rep "&N1505,"Surplus"))

Sheet How To Use
B2: HOW THE KITTING COUNT WORKS
B5: Refresh (weekly)
B6: 1. Run COOIS | C6: Material = the 14 assy codes (multiple selection). Exclude TECO as usual. Layout must include: Order, Material Number, Material description, Order quantity, System Status, Release date (actual).
B7: 2. Paste | C7: Export to spreadsheet, select all, copy, and paste into 'COOIS Raw' cell A1 (headers in row 1). Clear old data first. Column order does not matter — headers are matched by name.
B8: 3. Read | C8: The Dashboard recalculates. Nothing else to type.
B10: Definitions
B11: Kitted | C11: A WO is kitted when COOIS shows it released and printed: status contains PRT (or PPRT). Printing the order papers / pick list is the production controller's kitting step.
B12: Issued (GMPS) | C12: Goods movement posted: components issued to the WO in SAP.
B13: Delivered (DLV) | C13: Finished assembly goods-receipted.
B14: Repeater kits | C14: Kitted WOs ÷ qty per repeater (from 'Kitting Plan'), rounded down. REPEATERS KITTED = the lowest value across all 14 codes, because a repeater needs every code.
B15: Repeater # | C15: Each WO is given a repeater number by release order within its code (oldest first): seq ÷ qty per repeater, rounded up. E.g. spool orders 1–24 = Rep 1, 25–48 = Rep 2.
B16: Surplus | C16: WOs numbered beyond the contract repeaters (13). They are extra releases — usually rework / replacement orders whose original was not TECO'd. Review and TECO as needed.
B17: How to check '13' | C17: Filter 'COOIS Data' on Assy Code: the count of WOs ÷ qty per repeater gives the repeaters kitted for that code. The Dashboard shows the lowest — that is the answer for the contract.

Sheet COOIS Raw
A1: Order | B1: Order Type | C1: Material Number | D1: Material description | E1: Plant | F1: Batch | G1: Order quantity (GMEIN) | H1: Unit of measure (=GMEIN) | I1: Release date (actual) | J1: Delivered quantity (GMEIN) | K1: Created on | L1: Entered by | M1: Change date | N1: Last changed by | O1: System Status | P1: Planned opening date | Q1: Basic start date | R1: Basic finish date | S1: Firming indicator | T1: Results Analysis Key | U1: Processing group | V1: Requesting co. code | W1: Address Number | X1: Change Number | Y1: Changed at | Z1: Request. cost center | AA1: Priority | AB1: User Status | AC1: Request ID | AD1: Reservation/Purc.req | AE1: Expl. date rtg/BOM | AF1: Order category | AG1: Variance Key | AH1: Accounting Indicator | AI1: Exact break times | AJ1: Av.chk: committ.diff. | AK1: Av.chk: committ.fact. (PROZENT) | AL1: Company Code | AM1: Cost collector key | AN1: CO processing | AO1: Identical object | AP1: Update costs | AQ1: Apportionment Struct | AR1: Sequence number | AS1: MRP controller | AT1: Time created | AU1: Equity type | AV1: Production scheduler | AW1: SchedMargin key | AX1: Release period | AY1: Release date plan. | AZ1: Release date (scheduled) | BA1: Prog. release | BB1: Functional Area | BC1: Total scrap (GMEIN) | BD1: Confirmed finish date | BE1: Actual finish | BF1: Expected variance (GMEIN) | BG1: Forecast finish date | BH1: Prog.finish sched. | BI1: Actual finish date | BJ1: Scheduled finish date | BK1: Basic finish time | BL1: Scheduled fin. time | BM1: Business Area | BN1: Committed date | BO1: Forecast start date | BP1: Prog.start date | BQ1: Actual start time | BR1: Start date (sched) | BS1: ActualStartTime | BT1: Basic start time | BU1: Scheduled start time | BV1: Confirmed scrap (GMEIN) | BW1: Message Type | BX1: Confirmed quantity (GMEIN) | BY1: Investment profile | BZ1: Investment reason | CA1: JIB/JIBE Class | CB1: JIB/JIBE Subclass A | CC1: Costing Sheet | CD1: Version | CE1: Sales Order | CF1: Sales Order Item | CG1: Cstg variant actual | CH1: Cstg variant planned | CI1: Controlling Area | CJ1: Responsible CCtr | CK1: Settlement cost elem | CL1: Cost collector | CM1: Description | CN1: Type avail.chck | CO1: Proj. summ. MastData | CP1: Leading order | CQ1: Deletion flag | CR1: Long txt exists | CS1: Superior order | CT1: Production line | CU1: Planning ID 2 | CV1: ExpectYieldVariance (GMEIN) | CW1: Av.chk.messages | CX1: No planned costs | CY1: Change indicator | CZ1: Joint Venture Object Type | DA1: Routing change number | DB1: Routing valid from | DC1: Cost collector.1 | DD1: Explosion date | DE1: Planner group | DF1: Routing group cnt. | DG1: Routing appl. | DH1: Routing material | DI1: Task list unit (=PLNME) | DJ1: Routing group | DK1: Task List Type | DL1: Routing lot size to (PLNME) | DM1: Routing lot size frm (PLNME) | DN1: Planning plant | DO1: Outline finish date | DP1: Finish | DQ1: Outline start date | DR1: Start | DS1: Item (SD) | DT1: Item (SD).1 | DU1: Profit Center | DV1: Max. problem class | DW1: Production Process No | DX1: Collective order | DY1: WBS Element | DZ1: Process category | EA1: Percent (=PROZENT) | EB1: Inspection Lot | EC1: Identification | ED1: Recovery Indicator | EE1: Reduction indicator | EF1: Reference order | EG1: Av.chk.result | EH1: Revision Level | EI1: Sales Document | EJ1: Rework qty (GMEIN) | EK1: Reservation | EL1: Refurbishment order | EM1: Confirmation number | EN1: BOM change number | EO1: Run schedule header | EP1: Base Unit of Measure (=SBMEH) | EQ1: BOM base quantity (SBMEH) | ER1: Controlling area | ES1: BOM valid from | ET1: Prod.Sched.Profile | EU1: Float after prod. | EV1: SchedFloatAfterProd. | EW1: Scale | EX1: BOM lot size to (SBMEH) | EY1: BOM lot size from (SBMEH) | EZ1: Special Stock | FA1: Location plant | FB1: Split status | FC1: Status Profile | FD1: BOM alternative | FE1: BOM usage | FF1: BOM material | FG1: BOM number | FH1: BOM status | FI1: BOM category | FJ1: Object ID | FK1: Scheduling note | FL1: Scheduling type | FM1: Scheduled on | FN1: Long Text Language | FO1: Envir. investment | FP1: Estimated costs (WAERS) | FQ1: Production Version | FR1: Committed qty (GMEIN) | FS1: Joint Venture | FT1: Float before prod. | FU1: SchedFloatBeforeProd. | FV1: Version.1 | FW1: Currency | FX1: Overhead key
A2: 100880307 | B2: REP | C2: 92YRA01548AAA | D2: R5B ERBIUM ASSEMBLY 1 | E2: 8000.0 | G2: 1 | H2: EA | I2: 46298 | J2: 0 | K2: 2026-10-03 | L2: NBAKARE | M2: 46298 | N2: NBAKARE | O2: REL PRT PCNF PRC GMPS MANC SETC | Q2: 46298 | R2: 46305 | T2: ZSUBME | U2: 0.0 | Y2: 10:35:35 | AD2: 3.0 | AE2: 46297 | AF2: 10.0 | AG2: PP1 | AK2: 0.0 | AL2: 8000.0 | AO2: 0.0 | AR2: 0.0 | AS2: 10.0 | AT2: 10:35:32 | AV2: 7.0 | AW2: 1.0 | AX2: 5.0 | AZ2: 46296 | BC2: 0.0 | BE2: 0:00:00 | BF2: 0.0 | BJ2: 46303 | BK2: 0:00:00 | BL2: 24:00:00 | BM2: 1.0 | BQ2: 2026-10-03 | BR2: 46303 | BS2: 09:36:37 | BT2: 0:00:00 | BU2: 24:00:00 | BV2: 0.0 | BX2: 0 | CC2: PP-PC1 | CD2: 0.0 | CF2: 0.0 | CG2: PPP2 | CH2: PPP1 | CI2: 3000.0 | CM2: R5B ERBIUM ASSEMBLY 1 | CV2: 0.0 | DB2: 2013-01-01 | DD2: 46297 | DF2: 1.0 | DG2: P | DH2: 92YRA01548AAA | DI2: EA | DJ2: 50002992.0 | DK2: S | DL2: 99999999.0 | DM2: 0.0 | DN2: 8000.0 | DP2: 24:00:00 | DR2: 0:00:00 | DS2: 0.0 | DT2: 0.0 | DW2: 0.0 | EA2: % | EB2: 0.0 | EH2: 2.0 | EJ2: 0.0 | EK2: 153475351.0 | EM2: 0.0 | EN2: S9I00022646 | EP2: EA | EQ2: 1 | ER2: Production | ES2: 2026-03-01 | ET2: 1.0 | EU2: 1.0 | EV2: 1.0 | EX2: 0.0 | EY2: 0.0 | FC2: Z0000001 | FD2: 1.0 | FE2: 1.0 | FF2: 92YRA01548AAA | FG2: 107317.0 | FH2: 1.0 | FI2: M | FJ2: 0.0 | FL2: 2.0 | FM2: 2026-10-03 | FP2: 0.0 | FR2: 0.0 | FT2: 2.0 | FU2: 2.0 | FW2: GBP
A3: 100880184 | B3: REP | C3: 92YLS00548BAA | D3: R5B LASER ASSEMBLY 4P BOAT 1 - E2A | E3: 8000.0 | G3: 1 | H3: EA | I3: 46297 | J3: 0 | K3: 2026-10-02 | L3: TWRIGHT | M3: 46297 | N3: TWRIGHT | O3: REL PRT PRC MANC SETC | Q3: 46297 | R3: 46304 | T3: ZSUBME | U3: 0.0 | Y3: 14:06:23 | AD3: 3.0 | AE3: 46279 | AF3: 10.0 | AG3: PP1 | AK3: 0.0 | AL3: 8000.0 | AO3: 0.0 | AR3: 0.0 | AS3: 10.0 | AT3: 14:06:20 | AV3: 7.0 | AW3: 1.0 | AX3: 5.0 | AZ3: 46289 | BC3: 0.0 | BE3: 0:00:00 | BF3: 0.0 | BJ3: 46302 | BK3: 0:00:00 | BL3: 24:00:00 | BM3: 1.0 | BR3: 46296 | BS3: 0:00:00 | BT3: 0:00:00 | BU3: 0:00:00 | BV3: 0.0 | BX3: 0 | CC3: PP-PC1 | CD3: 0.0 | CF3: 0.0 | CG3: PPP2 | CH3: PPP1 | CI3: 3000.0 | CM3: R5B LASER ASSEMBLY 4P BOAT 1 - E2A | CV3: 0.0 | DB3: 2013-01-01 | DD3: 46279 | DF3: 1.0 | DG3: P | DH3: 92YLS00548BAA | DI3: EA | DJ3: 50003000.0 | DK3: S | DL3: 99999999.0 | DM3: 0.0 | DN3: 8000.0 | DP3: 0:00:00 | DR3: 0:00:00 | DS3: 0.0 | DT3: 0.0 | DW3: 0.0 | EA3: % | EB3: 0.0 | EH3: 1.0 | EJ3: 0.0 | EK3: 153458217.0 | EM3: 0.0 | EN3: S9I00022630 | EP3: EA | EQ3: 1 | ER3: Production | ES3: 2026-02-01 | ET3: 1.0 | EU3: 1.0 | EV3: 1.0 | EX3: 0.0 | EY3: 0.0 | FC3: Z0000001 | FD3: 1.0 | FE3: 1.0 | FF3: 92YLS00548BAA | FG3: 107280.0 | FH3: 1.0 | FI3: M | FJ3: 0.0 | FL3: 2.0 | FM3: 2026-10-02 | FP3: 0.0 | FR3: 0.0 | FT3: 2.0 | FU3: 2.0 | FW3: GBP
A4: 100880185 | B4: REP | C4: 92YLS00548BBA | D4: R5B LASER ASSEMBLY 4P BOAT 2/3 - E2A | E4: 8000.0 | G4: 1 | H4: EA | I4: 46297 | J4: 0 | K4: 2026-10-02 | L4: TWRIGHT | M4: 46297 | N4: TWRIGHT | O4: REL PRT PRC MANC SETC | Q4: 46297 | R4: 46304 | T4: ZSUBME | U4: 0.0 | Y4: 14:07:34 | AD4: 3.0 | AE4: 46279 | AF4: 10.0 | AG4: PP1 | AK4: 0.0 | AL4: 8000.0 | AO4: 0.0 | AR4: 0.0 | AS4: 10.0 | AT4: 14:07:31 | AV4: 7.0 | AW4: 1.0 | AX4: 5.0 | AZ4: 46289 | BC4: 0.0 | BE4: 0:00:00 | BF4: 0.0 | BJ4: 46302 | BK4: 0:00:00 | BL4: 24:00:00 | BM4: 1.0 | BR4: 46296 | BS4: 0:00:00 | BT4: 0:00:00 | BU4: 0:00:00 | BV4: 0.0 | BX4: 0 | CC4: PP-PC1 | CD4: 0.0 | CF4: 0.0 | CG4: PPP2 | CH4: PPP1 | CI4: 3000.0 | CM4: R5B LASER ASSEMBLY 4P BOAT 2/3 - E2A | CV4: 0.0 | DB4: 2013-01-01 | DD4: 46279 | DF4: 1.0 | DG4: P | DH4: 92YLS00548BBA | DI4: EA | DJ4: 50003001.0 | DK4: S | DL4: 99999999.0 | DM4: 0.0 | DN4: 8000.0 | DP4: 0:00:00 | DR4: 0:00:00 | DS4: 0.0 | DT4: 0.0 | DW4: 0.0 | EA4: % | EB4: 0.0 | EH4: 1.0 | EJ4: 0.0 | EK4: 153458240.0 | EM4: 0.0 | EN4: S9I00022633 | EP4: EA | EQ4: 1 | ER4: Production | ES4: 2026-02-01 | ET4: 1.0 | EU4: 1.0 | EV4: 1.0 | EX4: 0.0 | EY4: 0.0 | FC4: Z0000001 | FD4: 1.0 | FE4: 1.0 | FF4: 92YLS00548BBA | FG4: 107294.0 | FH4: 1.0 | FI4: M | FJ4: 0.0 | FL4: 2.0 | FM4: 2026-10-02 | FP4: 0.0 | FR4: 0.0 | FT4: 2.0 | FU4: 2.0 | FW4: GBP
A5: 100880186 | B5: REP | C5: 92YLS00548BBA | D5: R5B LASER ASSEMBLY 4P BOAT 2/3 - E2A | E5: 8000.0 | G5: 1 | H5: EA | I5: 46297 | J5: 0 | K5: 2026-10-02 | L5: TWRIGHT | O5: REL PRT PRC MANC SETC | Q5: 46297 | R5: 46303 | T5: ZSUBME | U5: 0.0 | Y5: 0:00:00 | AD5: 3.0 | AE5: 46279 | AF5: 10.0 | AG5: PP1 | AK5: 0.0 | AL5: 8000.0 | AO5: 0.0 | AR5: 0.0 | AS5: 10.0 | AT5: 14:07:38 | AV5: 7.0 | AW5: 1.0 | AX5: 5.0 | AZ5: 46289 | BC5: 0.0 | BE5: 0:00:00 | BF5: 0.0 | BJ5: 46302 | BK5: 24:00:00 | BL5: 24:00:00 | BM5: 1.0 | BR5: 46296 | BS5: 0:00:00 | BT5: 0:00:00 | BU5: 0:00:00 | BV5: 0.0 | BX5: 0 | CC5: PP-PC1 | CD5: 0.0 | CF5: 0.0 | CG5: PPP2 | CH5: PPP1 | CI5: 3000.0 | CM5: R5B LASER ASSEMBLY 4P BOAT 2/3 - E2A | CV5: 0.0 | DB5: 2013-01-01 | DD5: 46279 | DF5: 1.0 | DG5: P | DH5: 92YLS00548BBA | DI5: EA | DJ5: 50003001.0 | DK5: S | DL5: 99999999.0 | DM5: 0.0 | DN5: 8000.0 | DP5: 0:00:00 | DR5: 0:00:00 | DS5: 0.0 | DT5: 0.0 | DW5: 0.0 | EA5: % | EB5: 0.0 | EF5: 100880185.0 | EH5: 1.0 | EJ5: 0.0 | EK5: 153469271.0 | EM5: 0.0 | EN5: S9I00022633 | EP5: EA | EQ5: 1 | ER5: Production | ES5: 2026-02-01 | ET5: 1.0 | EU5: 1.0 | EV5: 1.0 | EX5: 0.0 | EY5: 0.0 | FC5: Z0000001 | FD5: 1.0 | FE5: 1.0 | FF5: 92YLS00548BBA | FG5: 107294.0 | FH5: 1.0 | FI5: M | FJ5: 0.0 | FL5: 2.0 | FM5: 2026-10-02 | FP5: 0.0 | FR5: 0.0 | FT5: 2.0 | FU5: 2.0 | FW5: GBP
A6: 100880187 | B6: REP | C6: 91YAF03404AAA | D6: R5B PSB SUB ASSEMBLY 4P-4FP | E6: 8000.0 | G6: 1 | H6: EA | I6: 46297 | J6: 0 | K6: 2026-10-02 | L6: TWRIGHT | M6: 46297 | N6: TWRIGHT | O6: REL PRT PRC MANC SETC | Q6: 46297 | R6: 46304 | T6: ZSUBME | U6: 0.0 | Y6: 14:09:35 | AD6: 3.0 | AE6: 46272 | AF6: 10.0 | AG6: PP1 | AK6: 0.0 | AL6: 8000.0 | AO6: 0.0 | AR6: 0.0 | AS6: 10.0 | AT6: 14:09:32 | AV6: 7.0 | AW6: 1.0 | AX6: 5.0 | AZ6: 46289 | BC6: 0.0 | BE6: 0:00:00 | BF6: 0.0 | BJ6: 46302 | BK6: 0:00:00 | BL6: 24:00:00 | BM6: 1.0 | BR6: 46296 | BS6: 0:00:00 | BT6: 0:00:00 | BU6: 0:00:00 | BV6: 0.0 | BX6: 0 | CC6: PP-PC1 | CD6: 0.0 | CF6: 0.0 | CG6: PPP2 | CH6: PPP1 | CI6: 3000.0 | CM6: R5B PSB SUB ASSEMBLY 4P-4FP | CV6: 0.0 | DB6: 2013-01-01 | DD6: 46272 | DF6: 1.0 | DG6: P | DH6: 91YAF03404AAA | DI6: EA | DJ6: 50002999.0 | DK6: S | DL6: 99999999.0 | DM6: 0.0 | DN6: 8000.0 | DP6: 0:00:00 | DR6: 0:00:00 | DS6: 0.0 | DT6: 0.0 | DW6: 0.0 | EA6: % | EB6: 0.0 | EH6: 1.0 | EJ6: 0.0 | EK6: 153459989.0 | EM6: 0.0 | EN6: S9I00020481 | EP6: EA | EQ6: 1 | ER6: Production | ES6: 2025-06-23 | ET6: 1.0 | EU6: 1.0 | EV6: 1.0 | EX6: 0.0 | EY6: 0.0 | FC6: Z0000001 | FD6: 1.0 | FE6: 1.0 | FF6: 91YAF03404AAA | FG6: 104710.0 | FH6: 1.0 | FI6: M | FJ6: 0.0 | FL6: 2.0 | FM6: 2026-10-02 | FP6: 0.0 | FR6: 0.0 | FT6: 2.0 | FU6: 2.0 | FW6: GBP
A7: 100880188 | B7: REP | C7: 91YAF03404AAA | D7: R5B PSB SUB ASSEMBLY 4P-4FP | E7: 8000.0 | G7: 1 | H7: EA | I7: 46297 | J7: 0 | K7: 2026-10-02 | L7: TWRIGHT | O7: REL PRT PRC MANC SETC | Q7: 46297 | R7: 46303 | T7: ZSUBME | U7: 0.0 | Y7: 0:00:00 | AD7: 3.0 | AE7: 46272 | AF7: 10.0 | AG7: PP1 | AK7: 0.0 | AL7: 8000.0 | AO7: 0.0 | AR7: 0.0 | AS7: 10.0 | AT7: 14:09:38 | AV7: 7.0 | AW7: 1.0 | AX7: 5.0 | AZ7: 46289 | BC7: 0.0 | BE7: 0:00:00 | BF7: 0.0 | BJ7: 46302 | BK7: 24:00:00 | BL7: 24:00:00 | BM7: 1.0 | BR7: 46296 | BS7: 0:00:00 | BT7: 0:00:00 | BU7: 0:00:00 | BV7: 0.0 | BX7: 0 | CC7: PP-PC1 | CD7: 0.0 | CF7: 0.0 | CG7: PPP2 | CH7: PPP1 | CI7: 3000.0 | CM7: R5B PSB SUB ASSEMBLY 4P-4FP | CV7: 0.0 | DB7: 2013-01-01 | DD7: 46272 | DF7: 1.0 | DG7: P | DH7: 91YAF03404AAA | DI7: EA | DJ7: 50002999.0 | DK7: S | DL7: 99999999.0 | DM7: 0.0 | DN7: 8000.0 | DP7: 0:00:00 | DR7: 0:00:00 | DS7: 0.0 | DT7: 0.0 | DW7: 0.0 | EA7: % | EB7: 0.0 | EF7: 100880187.0 | EH7: 1.0 | EJ7: 0.0 | EK7: 153469273.0 | EM7: 0.0 | EN7: S9I00020481 | EP7: EA | EQ7: 1 | ER7: Production | ES7: 2025-06-23 | ET7: 1.0 | EU7: 1.0 | EV7: 1.0 | EX7: 0.0 | EY7: 0.0 | FC7: Z0000001 | FD7: 1.0 | FE7: 1.0 | FF7: 91YAF03404AAA | FG7: 104710.0 | FH7: 1.0 | FI7: M | FJ7: 0.0 | FL7: 2.0 | FM7: 2026-10-02 | FP7: 0.0 | FR7: 0.0 | FT7: 2.0 | FU7: 2.0 | FW7: GBP
A8: 100880189 | B8: REP | C8: 91YAF03404AAA | D8: R5B PSB SUB ASSEMBLY 4P-4FP | E8: 8000.0 | G8: 1 | H8: EA | I8: 46297 | J8: 0 | K8: 2026-10-02 | L8: TWRIGHT | O8: REL PRT PRC MANC SETC | Q8: 46297 | R8: 46303 | T8: ZSUBME | U8: 0.0 | Y8: 0:00:00 | AD8: 3.0 | AE8: 46272 | AF8: 10.0 | AG8: PP1 | AK8: 0.0 | AL8: 8000.0 | AO8: 0.0 | AR8: 0.0 | AS8: 10.0 | AT8: 14:09:41 | AV8: 7.0 | AW8: 1.0 | AX8: 5.0 | AZ8: 46289 | BC8: 0.0 | BE8: 0:00:00 | BF8: 0.0 | BJ8: 46302 | BK8: 24:00:00 | BL8: 24:00:00 | BM8: 1.0 | BR8: 46296 | BS8: 0:00:00 | BT8: 0:00:00 | BU8: 0:00:00 | BV8: 0.0 | BX8: 0 | CC8: PP-PC1 | CD8: 0.0 | CF8: 0.0 | CG8: PPP2 | CH8: PPP1 | CI8: 3000.0 | CM8: R5B PSB SUB ASSEMBLY 4P-4FP | CV8: 0.0 | DB8: 2013-01-01 | DD8: 46272 | DF8: 1.0 | DG8: P | DH8: 91YAF03404AAA | DI8: EA | DJ8: 50002999.0 | DK8: S | DL8: 99999999.0 | DM8: 0.0 | DN8: 8000.0 | DP8: 0:00:00 | DR8: 0:00:00 | DS8: 0.0 | DT8: 0.0 | DW8: 0.0 | EA8: % | EB8: 0.0 | EF8: 100880187.0 | EH8: 1.0 | EJ8: 0.0 | EK8: 153469274.0 | EM8: 0.0 | EN8: S9I00020481 | EP8: EA | EQ8: 1 | ER8: Production | ES8: 2025-06-23 | ET8: 1.0 | EU8: 1.0 | EV8: 1.0 | EX8: 0.0 | EY8: 0.0 | FC8: Z0000001 | FD8: 1.0 | FE8: 1.0 | FF8: 91YAF03404AAA | FG8: 104710.0 | FH8: 1.0 | FI8: M | FJ8: 0.0 | FL8: 2.0 | FM8: 2026-10-02 | FP8: 0.0 | FR8: 0.0 | FT8: 2.0 | FU8: 2.0 | FW8: GBP
A9: 100880190 | B9: REP | C9: 92YFD04548BAA | D9: R5B OPF ASSEMBLY (4P-4FP) BOAT 1 - E2A | E9: 8000.0 | G9: 1 | H9: EA | I9: 46297 | J9: 0 | K9: 2026-10-02 | L9: TWRIGHT | M9: 46297 | N9: TWRIGHT | O9: REL PRT PRC MANC SETC | Q9: 46297 | R9: 46304 | T9: ZSUBME | U9: 0.0 | Y9: 14:12:03 | AD9: 3.0 | AE9: 46282 | AF9: 10.0 | AG9: PP1 | AK9: 0.0 | AL9: 8000.0 | AO9: 0.0 | AR9: 0.0 | AS9: 10.0 | AT9: 14:12:00 | AV9: 7.0 | AW9: 1.0 | AX9: 5.0 | AZ9: 46289 | BC9: 0.0 | BE9: 0:00:00 | BF9: 0.0 | BJ9: 46302 | BK9: 0:00:00 | BL9: 24:00:00 | BM9: 1.0 | BR9: 46296 | BS9: 0:00:00 | BT9: 0:00:00 | BU9: 0:00:00 | BV9: 0.0 | BX9: 0 | CC9: PP-PC1 | CD9: 0.0 | CF9: 0.0 | CG9: PPP2 | CH9: PPP1 | CI9: 3000.0 | CM9: R5B OPF ASSEMBLY (4P-4FP) BOAT 1 - E2A | CV9: 0.0 | DB9: 2013-01-01 | DD9: 46282 | DF9: 1.0 | DG9: P | DH9: 92YFD04548BAA | DI9: EA | DJ9: 50003002.0 | DK9: S | DL9: 99999999.0 | DM9: 0.0 | DN9: 8000.0 | DP9: 0:00:00 | DR9: 0:00:00 | DS9: 0.0 | DT9: 0.0 | DW9: 0.0 | EA9: % | EB9: 0.0 | EH9: 1.0 | EJ9: 0.0 | EK9: 153455392.0 | EM9: 0.0 | EN9: S9I00022650 | EP9: EA | EQ9: 1 | ER9: Production | ES9: 2026-02-01 | ET9: 1.0 | EU9: 1.0 | EV9: 1.0 | EX9: 0.0 | EY9: 0.0 | FC9: Z0000001 | FD9: 1.0 | FE9: 1.0 | FF9: 92YFD04548BAA | FG9: 107321.0 | FH9: 1.0 | FI9: M | FJ9: 0.0 | FL9: 2.0 | FM9: 2026-10-02 | FP9: 0.0 | FR9: 0.0 | FT9: 2.0 | FU9: 2.0 | FW9: GBP
A10: 100880191 | B10: REP | C10: 92YFD04548BBA | D10: R5B OPF ASSEMBLY (4P-4FP) BOAT 2/3 - E2A | E10: 8000.0 | G10: 1 | H10: EA | I10: 46297 | J10: 0 | K10: 2026-10-02 | L10: TWRIGHT | M10: 46297 | N10: TWRIGHT | O10: REL PRT PRC MANC SETC | Q10: 46297 | R10: 46304 | T10: ZSUBME | U10: 0.0 | Y10: 14:15:21 | AD10: 3.0 | AE10: 46275 | AF10: 10.0 | AG10: PP1 | AK10: 0.0 | AL10: 8000.0 | AO10: 0.0 | AR10: 0.0 | AS10: 10.0 | AT10: 14:15:19 | AV10: 7.0 | AW10: 1.0 | AX10: 5.0 | AZ10: 46289 | BC10: 0.0 | BE10: 0:00:00 | BF10: 0.0 | BJ10: 46302 | BK10: 0:00:00 | BL10: 24:00:00 | BM10: 1.0 | BR10: 46296 | BS10: 0:00:00 | BT10: 0:00:00 | BU10: 0:00:00 | BV10: 0.0 | BX10: 0 | CC10: PP-PC1 | CD10: 0.0 | CF10: 0.0 | CG10: PPP2 | CH10: PPP1 | CI10: 3000.0 | CM10: R5B OPF ASSEMBLY (4P-4FP) BOAT 2/3 - E2A | CV10: 0.0 | DB10: 2013-01-01 | DD10: 46275 | DF10: 1.0 | DG10: P | DH10: 92YFD04548BBA | DI10: EA | DJ10: 50003002.0 | DK10: S | DL10: 99999999.0 | DM10: 0.0 | DN10: 8000.0 | DP10: 0:00:00 | DR10: 0:00:00 | DS10: 0.0 | DT10: 0.0 | DW10: 0.0 | EA10: % | EB10: 0.0 | EH10: 1.0 | EJ10: 0.0 | EK10: 153455416.0 | EM10: 0.0 | EN10: S9I00022651 | EP10: EA | EQ10: 1 | ER10: Production | ES10: 2026-02-01 | ET10: 1.0 | EU10: 1.0 | EV10: 1.0 | EX10: 0.0 | EY10: 0.0 | FC10: Z0000001 | FD10: 1.0 | FE10: 1.0 | FF10: 92YFD04548BBA | FG10: 107322.0 | FH10: 1.0 | FI10: M | FJ10: 0.0 | FL10: 2.0 | FM10: 2026-10-02 | FP10: 0.0 | FR10: 0.0 | FT10: 2.0 | FU10: 2.0 | FW10: GBP
A11: 100880192 | B11: REP | C11: 92YFD04548BBA | D11: R5B OPF ASSEMBLY (4P-4FP) BOAT 2/3 - E2A | E11: 8000.0 | G11: 1 | H11: EA | I11: 46297 | J11: 0 | K11: 2026-10-02 | L11: TWRIGHT | M11: 46297 | N11: TWRIGHT | O11: REL PRT PRC MANC SETC | Q11: 46297 | R11: 46304 | T11: ZSUBME | U11: 0.0 | Y11: 14:17:10 | AD11: 3.0 | AE11: 46282 | AF11: 10.0 | AG11: PP1 | AK11: 0.0 | AL11: 8000.0 | AO11: 0.0 | AR11: 0.0 | AS11: 10.0 | AT11: 14:17:08 | AV11: 7.0 | AW11: 1.0 | AX11: 5.0 | AZ11: 46289 | BC11: 0.0 | BE11: 0:00:00 | BF11: 0.0 | BJ11: 46302 | BK11: 0:00:00 | BL11: 24:00:00 | BM11: 1.0 | BR11: 46296 | BS11: 0:00:00 | BT11: 0:00:00 | BU11: 0:00:00 | BV11: 0.0 | BX11: 0 | CC11: PP-PC1 | CD11: 0.0 | CF11: 0.0 | CG11: PPP2 | CH11: PPP1 | CI11: 3000.0 | CM11: R5B OPF ASSEMBLY (4P-4FP) BOAT 2/3 - E2A | CV11: 0.0 | DB11: 2013-01-01 | DD11: 46282 | DF11: 1.0 | DG11: P | DH11: 92YFD04548BBA | DI11: EA | DJ11: 50003002.0 | DK11: S | DL11: 99999999.0 | DM11: 0.0 | DN11: 8000.0 | DP11: 0:00:00 | DR11: 0:00:00 | DS11: 0.0 | DT11: 0.0 | DW11: 0.0 | EA11: % | EB11: 0.0 | EH11: 1.0 | EJ11: 0.0 | EK11: 153455417.0 | EM11: 0.0 | EN11: S9I00022651 | EP11: EA | EQ11: 1 | ER11: Production | ES11: 2026-02-01 | ET11: 1.0 | EU11: 1.0 | EV11: 1.0 | EX11: 0.0 | EY11: 0.0 | FC11: Z0000001 | FD11: 1.0 | FE11: 1.0 | FF11: 92YFD04548BBA | FG11: 107322.0 | FH11: 1.0 | FI11: M | FJ11: 0.0 | FL11: 2.0 | FM11: 2026-10-02 | FP11: 0.0 | FR11: 0.0 | FT11: 2.0 | FU11: 2.0 | FW11: GBP
A12: 100880193 | B12: REP | C12: 92YWS04548AAA | D12: R5B 4FP POB LUMENTUM SUB ASSEMBLY - E2A | E12: 8000.0 | G12: 1 | H12: EA | I12: 46297 | J12: 0 | K12: 2026-10-02 | L12: TWRIGHT | M12: 46297 | N12: TWRIGHT | O12: REL PRT PRC MANC SETC | Q12: 46297 | R12: 46304 | T12: ZSUBME | U12: 0.0 | Y12: 14:19:04 | AD12: 3.0 | AE12: 46275 | AF12: 10.0 | AG12: PP1 | AK12: 0.0 | AL12: 8000.0 | AO12: 0.0 | AR12: 0.0 | AS12: 10.0 | AT12: 14:19:01 | AV12: 7.0 | AW12: 1.0 | AX12: 5.0 | AZ12: 46295 | BC12: 0.0 | BE12: 0:00:00 | BF12: 0.0 | BJ12: 46302 | BK12: 0:00:00 | BL12: 24:00:00 | BM12: 1.0 | BR12: 46302 | BS12: 0:00:00 | BT12: 0:00:00 | BU12: 24:00:00 | BV12: 0.0 | BX12: 0 | CC12: PP-PC1 | CD12: 0.0 | CF12: 0.0 | CG12: PPP2 | CH12: PPP1 | CI12: 3000.0 | CM12: R5B 4FP POB LUMENTUM SUB ASSEMBLY - E2A | CV12: 0.0 | DB12: 2013-01-01 | DD12: 46275 | DF12: 1.0 | DG12: P | DH12: 92YWS04548AAA | DI12: EA | DJ12: 50002991.0 | DK12: S | DL12: 99999999.0 | DM12: 0.0 | DN12: 8000.0 | DP12: 0:00:00 | DR12: 0:00:00 | DS12: 0.0 | DT12: 0.0 | DW12: 0.0 | EA12: % | EB12: 0.0 | EH12: 1.0 | EJ12: 0.0 | EK12: 153455694.0 | EM12: 0.0 | EN12: S9I00022614 | EP12: EA | EQ12: 1 | ER12: Production | ES12: 2026-02-13 | ET12: 1.0 | EU12: 1.0 | EV12: 1.0 | EX12: 0.0 | EY12: 0.0 | FC12: Z0000001 | FD12: 1.0 | FE12: 1.0 | FF12: 92YWS04548AAA | FG12: 107275.0 | FH12: 1.0 | FI12: M | FJ12: 0.0 | FL12: 2.0 | FM12: 2026-10-02 | FP12: 0.0 | FR12: 0.0 | FT12: 2.0 | FU12: 2.0 | FW12: GBP
A13: 100880194 | B13: REP | C13: 92YWS04548AAA | D13: R5B 4FP POB LUMENTUM SUB ASSEMBLY - E2A | E13: 8000.0 | G13: 1 | H13: EA | I13: 46297 | J13: 0 | K13: 2026-10-02 | L13: TWRIGHT | M13: 46297 | N13: TWRIGHT | O13: REL PRT PRC MANC SETC | Q13: 46297 | R13: 46304 | T13: ZSUBME | U13: 0.0 | Y13: 14:20:10 | AD13: 3.0 | AE13: 46282 | AF13: 10.0 | AG13: PP1 | AK13: 0.0 | AL13: 8000.0 | AO13: 0.0 | AR13: 0.0 | AS13: 10.0 | AT13: 14:20:07 | AV13: 7.0 | AW13: 1.0 | AX13: 5.0 | AZ13: 46295 | BC13: 0.0 | BE13: 0:00:00 | BF13: 0.0 | BJ13: 46302 | BK13: 0:00:00 | BL13: 24:00:00 | BM13: 1.0 | BR13: 46302 | BS13: 0:00:00 | BT13: 0:00:00 | BU13: 24:00:00 | BV13: 0.0 | BX13: 0 | CC13: PP-PC1 | CD13: 0.0 | CF13: 0.0 | CG13: PPP2 | CH13: PPP1 | CI13: 3000.0 | CM13: R5B 4FP POB LUMENTUM SUB ASSEMBLY - E2A | CV13: 0.0 | DB13: 2013-01-01 | DD13: 46282 | DF13: 1.0 | DG13: P | DH13: 92YWS04548AAA | DI13: EA | DJ13: 50002991.0 | DK13: S | DL13: 99999999.0 | DM13: 0.0 | DN13: 8000.0 | DP13: 0:00:00 | DR13: 0:00:00 | DS13: 0.0 | DT13: 0.0 | DW13: 0.0 | EA13: % | EB13: 0.0 | EH13: 1.0 | EJ13: 0.0 | EK13: 153455695.0 | EM13: 0.0 | EN13: S9I00022614 | EP13: EA | EQ13: 1 | ER13: Production | ES13: 2026-02-13 | ET13: 1.0 | EU13: 1.0 | EV13: 1.0 | EX13: 0.0 | EY13: 0.0 | FC13: Z0000001 | FD13: 1.0 | FE13: 1.0 | FF13: 92YWS04548AAA | FG13: 107275.0 | FH13: 1.0 | FI13: M | FJ13: 0.0 | FL13: 2.0 | FM13: 2026-10-02 | FP13: 0.0 | FR13: 0.0 | FT13: 2.0 | FU13: 2.0 | FW13: GBP
A14: 100880195 | B14: REP | C14: 92YWS04548AAA | D14: R5B 4FP POB LUMENTUM SUB ASSEMBLY - E2A | E14: 8000.0 | G14: 1 | H14: EA | I14: 46297 | J14: 0 | K14: 2026-10-02 | L14: TWRIGHT | O14: REL PRT PRC MANC SETC | Q14: 46297 | R14: 46303 | T14: ZSUBME | U14: 0.0 | Y14: 0:00:00 | AD14: 3.0 | AE14: 46282 | AF14: 10.0 | AG14: PP1 | AK14: 0.0 | AL14: 8000.0 | AO14: 0.0 | AR14: 0.0 | AS14: 10.0 | AT14: 14:20:14 | AV14: 7.0 | AW14: 1.0 | AX14: 5.0 | AZ14: 46295 | BC14: 0.0 | BE14: 0:00:00 | BF14: 0.0 | BJ14: 46302 | BK14: 24:00:00 | BL14: 24:00:00 | BM14: 1.0 | BR14: 46302 | BS14: 0:00:00 | BT14: 0:00:00 | BU14: 24:00:00 | BV14: 0.0 | BX14: 0 | CC14: PP-PC1 | CD14: 0.0 | CF14: 0.0 | CG14: PPP2 | CH14: PPP1 | CI14: 3000.0 | CM14: R5B 4FP POB LUMENTUM SUB ASSEMBLY - E2A | CV14: 0.0 | DB14: 2013-01-01 | DD14: 46282 | DF14: 1.0 | DG14: P | DH14: 92YWS04548AAA | DI14: EA | DJ14: 50002991.0 | DK14: S | DL14: 99999999.0 | DM14: 0.0 | DN14: 8000.0 | DP14: 0:00:00 | DR14: 0:00:00 | DS14: 0.0 | DT14: 0.0 | DW14: 0.0 | EA14: % | EB14: 0.0 | EF14: 100880194.0 | EH14: 1.0 | EJ14: 0.0 | EK14: 153469690.0 | EM14: 0.0 | EN14: S9I00022614 | EP14: EA | EQ14: 1 | ER14: Production | ES14: 2026-02-13 | ET14: 1.0 | EU14: 1.0 | EV14: 1.0 | EX14: 0.0 | EY14: 0.0 | FC14: Z0000001 | FD14: 1.0 | FE14: 1.0 | FF14: 92YWS04548AAA | FG14: 107275.0 | FH14: 1.0 | FI14: M | FJ14: 0.0 | FL14: 2.0 | FM14: 2026-10-02 | FP14: 0.0 | FR14: 0.0 | FT14: 2.0 | FU14: 2.0 | FW14: GBP
A15: 100880196 | B15: REP | C15: 92RRA00548AAA | D15: R5B ERBIUM SPOOL ASSEMBLY - E2A | E15: 8000.0 | G15: 1 | H15: EA | I15: 46297 | J15: 0 | K15: 2026-10-02 | L15: TWRIGHT | M15: 46297 | N15: TWRIGHT | O15: REL PRT PRC MANC SETC | Q15: 46297 | R15: 46304 | T15: ZSUBME | U15: 0.0 | Y15: 14:21:44 | AD15: 3.0 | AE15: 46286 | AF15: 10.0 | AG15: PP1 | AK15: 0.0 | AL15: 8000.0 | AO15: 0.0 | AR15: 0.0 | AS15: 10.0 | AT15: 14:21:41 | AV15: 7.0 | AW15: 1.0 | AX15: 5.0 | AZ15: 46295 | BC15: 0.0 | BE15: 0:00:00 | BF15: 0.0 | BJ15: 46302 | BK15: 0:00:00 | BL15: 24:00:00 | BM15: 1.0 | BR15: 46302 | BS15: 0:00:00 | BT15: 0:00:00 | BU15: 24:00:00 | BV15: 0.0 | BX15: 0 | CC15: PP-PC1 | CD15: 0.0 | CF15: 0.0 | CG15: PPP2 | CH15: PPP1 | CI15: 3000.0 | CM15: R5B ERBIUM SPOOL ASSEMBLY - E2A | CV15: 0.0 | DB15: 2013-01-01 | DD15: 46286 | DF15: 1.0 | DG15: P | DH15: 92RRA00548AAA | DI15: EA | DJ15: 50002963.0 | DK15: S | DL15: 99999999.0 | DM15: 0.0 | DN15: 8000.0 | DP15: 0:00:00 | DR15: 0:00:00 | DS15: 0.0 | DT15: 0.0 | DW15: 0.0 | EA15: % | EB15: 0.0 | EH15: 1.0 | EJ15: 0.0 | EK15: 153458136.0 | EM15: 0.0 | EN15: S9I00022645 | EP15: EA | EQ15: 1 | ER15: Production | ES15: 2026-03-01 | ET15: 1.0 | EU15: 1.0 | EV15: 1.0 | EX15: 0.0 | EY15: 0.0 | FC15: Z0000001 | FD15: 1.0 | FE15: 1.0 | FF15: 92RRA00548AAA | FG15: 107316.0 | FH15: 1.0 | FI15: M | FJ15: 0.0 | FL15: 2.0 | FM15: 2026-10-02 | FP15: 0.0 | FR15: 0.0 | FT15: 2.0 | FU15: 2.0 | FW15: GBP
A16: 100880197 | B16: REP | C16: 92RRA00548AAA | D16: R5B ERBIUM SPOOL ASSEMBLY - E2A | E16: 8000.0 | G16: 1 | H16: EA | I16: 46297 | J16: 0 | K16: 2026-10-02 | L16: TWRIGHT | O16: REL PRT PRC MANC SETC | Q16: 46297 | R16: 46303 | T16: ZSUBME | U16: 0.0 | Y16: 0:00:00 | AD16: 3.0 | AE16: 46286 | AF16: 10.0 | AG16: PP1 | AK16: 0.0 | AL16: 8000.0 | AO16: 0.0 | AR16: 0.0 | AS16: 10.0 | AT16: 14:21:47 | AV16: 7.0 | AW16: 1.0 | AX16: 5.0 | AZ16: 46295 | BC16: 0.0 | BE16: 0:00:00 | BF16: 0.0 | BJ16: 46302 | BK16: 24:00:00 | BL16: 24:00:00 | BM16: 1.0 | BR16: 46302 | BS16: 0:00:00 | BT16: 0:00:00 | BU16: 24:00:00 | BV16: 0.0 | BX16: 0 | CC16: PP-PC1 | CD16: 0.0 | CF16: 0.0 | CG16: PPP2 | CH16: PPP1 | CI16: 3000.0 | CM16: R5B ERBIUM SPOOL ASSEMBLY - E2A | CV16: 0.0 | DB16: 2013-01-01 | DD16: 46286 | DF16: 1.0 | DG16: P | DH16: 92RRA00548AAA | DI16: EA | DJ16: 50002963.0 | DK16: S | DL16: 99999999.0 | DM16: 0.0 | DN16: 8000.0 | DP16: 0:00:00 | DR16: 0:00:00 | DS16: 0.0 | DT16: 0.0 | DW16: 0.0 | EA16: % | EB16: 0.0 | EF16: 100880196.0 | EH16: 1.0 | EJ16: 0.0 | EK16: 153469743.0 | EM16: 0.0 | EN16: S9I00022645 | EP16: EA | EQ16: 1 | ER16: Production | ES16: 2026-03-01 | ET16: 1.0 | EU16: 1.0 | EV16: 1.0 | EX16: 0.0 | EY16: 0.0 | FC16: Z0000001 | FD16: 1.0 | FE16: 1.0 | FF16: 92RRA00548AAA | FG16: 107316.0 | FH16: 1.0 | FI16: M | FJ16: 0.0 | FL16: 2.0 | FM16: 2026-10-02 | FP16: 0.0 | FR16: 0.0 | FT16: 2.0 | FU16: 2.0 | FW16: GBP
A17: 100880198 | B17: REP | C17: 92RRA00548AAA | D17: R5B ERBIUM SPOOL ASSEMBLY - E2A | E17: 8000.0 | G17: 1 | H17: EA | I17: 46297 | J17: 0 | K17: 2026-10-02 | L17: TWRIGHT | O17: REL PRT PRC MANC SETC | Q17: 46297 | R17: 46303 | T17: ZSUBME | U17: 0.0 | Y17: 0:00:00 | AD17: 3.0 | AE17: 46286 | AF17: 10.0 | AG17: PP1 | AK17: 0.0 | AL17: 8000.0 | AO17: 0.0 | AR17: 0.0 | AS17: 10.0 | AT17: 14:21:50 | AV17: 7.0 | AW17: 1.0 | AX17: 5.0 | AZ17: 46295 | BC17: 0.0 | BE17: 0:00:00 | BF17: 0.0 | BJ17: 46302 | BK17: 24:00:00 | BL17: 24:00:00 | BM17: 1.0 | BR17: 46302 | BS17: 0:00:00 | BT17: 0:00:00 | BU17: 24:00:00 | BV17: 0.0 | BX17: 0 | CC17: PP-PC1 | CD17: 0.0 | CF17: 0.0 | CG17: PPP2 | CH17: PPP1 | CI17: 3000.0 | CM17: R5B ERBIUM SPOOL ASSEMBLY - E2A | CV17: 0.0 | DB17: 2013-01-01 | DD17: 46286 | DF17: 1.0 | DG17: P | DH17: 92RRA00548AAA | DI17: EA | DJ17: 50002963.0 | DK17: S | DL17: 99999999.0 | DM17: 0.0 | DN17: 8000.0 | DP17: 0:00:00 | DR17: 0:00:00 | DS17: 0.0 | DT17: 0.0 | DW17: 0.0 | EA17: % | EB17: 0.0 | EF17: 100880196.0 | EH17: 1.0 | EJ17: 0.0 | EK17: 153469744.0 | EM17: 0.0 | EN17: S9I00022645 | EP17: EA | EQ17: 1 | ER17: Production | ES17: 2026-03-01 | ET17: 1.0 | EU17: 1.0 | EV17: 1.0 | EX17: 0.0 | EY17: 0.0 | FC17: Z0000001 | FD17: 1.0 | FE17: 1.0 | FF17: 92RRA00548AAA | FG17: 107316.0 | FH17: 1.0 | FI17: M | FJ17: 0.0 | FL17: 2.0 | FM17: 2026-10-02 | FP17: 0.0 | FR17: 0.0 | FT17: 2.0 | FU17: 2.0 | FW17: GBP
A18: 100880199 | B18: REP | C18: 92RRA00548AAA | D18: R5B ERBIUM SPOOL ASSEMBLY - E2A | E18: 8000.0 | G18: 1 | H18: EA | I18: 46297 | J18: 0 | K18: 2026-10-02 | L18: TWRIGHT | O18: REL PRT PRC MANC SETC | Q18: 46297 | R18: 46303 | T18: ZSUBME | U18: 0.0 | Y18: 0:00:00 | AD18: 3.0 | AE18: 46286 | AF18: 10.0 | AG18: PP1 | AK18: 0.0 | AL18: 8000.0 | AO18: 0.0 | AR18: 0.0 | AS18: 10.0 | AT18: 14:21:53 | AV18: 7.0 | AW18: 1.0 | AX18: 5.0 | AZ18: 46295 | BC18: 0.0 | BE18: 0:00:00 | BF18: 0.0 | BJ18: 46302 | BK18: 24:00:00 | BL18: 24:00:00 | BM18: 1.0 | BR18: 46302 | BS18: 0:00:00 | BT18: 0:00:00 | BU18: 24:00:00 | BV18: 0.0 | BX18: 0 | CC18: PP-PC1 | CD18: 0.0 | CF18: 0.0 | CG18: PPP2 | CH18: PPP1 | CI18: 3000.0 | CM18: R5B ERBIUM SPOOL ASSEMBLY - E2A | CV18: 0.0 | DB18: 2013-01-01 | DD18: 46286 | DF18: 1.0 | DG18: P | DH18: 92RRA00548AAA | DI18: EA | DJ18: 50002963.0 | DK18: S | DL18: 99999999.0 | DM18: 0.0 | DN18: 8000.0 | DP18: 0:00:00 | DR18: 0:00:00 | DS18: 0.0 | DT18: 0.0 | DW18: 0.0 | EA18: % | EB18: 0.0 | EF18: 100880196.0 | EH18: 1.0 | EJ18: 0.0 | EK18: 153469745.0 | EM18: 0.0 | EN18: S9I00022645 | EP18: EA | EQ18: 1 | ER18: Production | ES18: 2026-03-01 | ET18: 1.0 | EU18: 1.0 | EV18: 1.0 | EX18: 0.0 | EY18: 0.0 | FC18: Z0000001 | FD18: 1.0 | FE18: 1.0 | FF18: 92RRA00548AAA | FG18: 107316.0 | FH18: 1.0 | FI18: M | FJ18: 0.0 | FL18: 2.0 | FM18: 2026-10-02 | FP18: 0.0 | FR18: 0.0 | FT18: 2.0 | FU18: 2.0 | FW18: GBP
A19: 100880200 | B19: REP | C19: 92RRA00548AAA | D19: R5B ERBIUM SPOOL ASSEMBLY - E2A | E19: 8000.0 | G19: 1 | H19: EA | I19: 46297 | J19: 0 | K19: 2026-10-02 | L19: TWRIGHT | O19: REL PRT PRC MANC SETC | Q19: 46297 | R19: 46303 | T19: ZSUBME | U19: 0.0 | Y19: 0:00:00 | AD19: 3.0 | AE19: 46286 | AF19: 10.0 | AG19: PP1 | AK19: 0.0 | AL19: 8000.0 | AO19: 0.0 | AR19: 0.0 | AS19: 10.0 | AT19: 14:21:57 | AV19: 7.0 | AW19: 1.0 | AX19: 5.0 | AZ19: 46295 | BC19: 0.0 | BE19: 0:00:00 | BF19: 0.0 | BJ19: 46302 | BK19: 24:00:00 | BL19: 24:00:00 | BM19: 1.0 | BR19: 46302 | BS19: 0:00:00 | BT19: 0:00:00 | BU19: 24:00:00 | BV19: 0.0 | BX19: 0 | CC19: PP-PC1 | CD19: 0.0 | CF19: 0.0 | CG19: PPP2 | CH19: PPP1 | CI19: 3000.0 | CM19: R5B ERBIUM SPOOL ASSEMBLY - E2A | CV19: 0.0 | DB19: 2013-01-01 | DD19: 46286 | DF19: 1.0 | DG19: P | DH19: 92RRA00548AAA | DI19: EA | DJ19: 50002963.0 | DK19: S | DL19: 99999999.0 | DM19: 0.0 | DN19: 8000.0 | DP19: 0:00:00 | DR19: 0:00:00 | DS19: 0.0 | DT19: 0.0 | DW19: 0.0 | EA19: % | EB19: 0.0 | EF19: 100880196.0 | EH19: 1.0 | EJ19: 0.0 | EK19: 153469746.0 | EM19: 0.0 | EN19: S9I00022645 | EP19: EA | EQ19: 1 | ER19: Production | ES19: 2026-03-01 | ET19: 1.0 | EU19: 1.0 | EV19: 1.0 | EX19: 0.0 | EY19: 0.0 | FC19: Z0000001 | FD19: 1.0 | FE19: 1.0 | FF19: 92RRA00548AAA | FG19: 107316.0 | FH19: 1.0 | FI19: M | FJ19: 0.0 | FL19: 2.0 | FM19: 2026-10-02 | FP19: 0.0 | FR19: 0.0 | FT19: 2.0 | FU19: 2.0 | FW19: GBP
A20: 100880201 | B20: REP | C20: 92RRA00548AAA | D20: R5B ERBIUM SPOOL ASSEMBLY - E2A | E20: 8000.0 | G20: 1 | H20: EA | I20: 46297 | J20: 0 | K20: 2026-10-02 | L20: TWRIGHT | O20: REL PRT PRC MANC SETC | Q20: 46297 | R20: 46303 | T20: ZSUBME | U20: 0.0 | Y20: 0:00:00 | AD20: 3.0 | AE20: 46286 | AF20: 10.0 | AG20: PP1 | AK20: 0.0 | AL20: 8000.0 | AO20: 0.0 | AR20: 0.0 | AS20: 10.0 | AT20: 14:22:00 | AV20: 7.0 | AW20: 1.0 | AX20: 5.0 | AZ20: 46295 | BC20: 0.0 | BE20: 0:00:00 | BF20: 0.0 | BJ20: 46302 | BK20: 24:00:00 | BL20: 24:00:00 | BM20: 1.0 | BR20: 46302 | BS20: 0:00:00 | BT20: 0:00:00 | BU20: 24:00:00 | BV20: 0.0 | BX20: 0 | CC20: PP-PC1 | CD20: 0.0 | CF20: 0.0 | CG20: PPP2 | CH20: PPP1 | CI20: 3000.0 | CM20: R5B ERBIUM SPOOL ASSEMBLY - E2A | CV20: 0.0 | DB20: 2013-01-01 | DD20: 46286 | DF20: 1.0 | DG20: P | DH20: 92RRA00548AAA | DI20: EA | DJ20: 50002963.0 | DK20: S | DL20: 99999999.0 | DM20: 0.0 | DN20: 8000.0 | DP20: 0:00:00 | DR20: 0:00:00 | DS20: 0.0 | DT20: 0.0 | DW20: 0.0 | EA20: % | EB20: 0.0 | EF20: 100880196.0 | EH20: 1.0 | EJ20: 0.0 | EK20: 153469747.0 | EM20: 0.0 | EN20: S9I00022645 | EP20: EA | EQ20: 1 | ER20: Production | ES20: 2026-03-01 | ET20: 1.0 | EU20: 1.0 | EV20: 1.0 | EX20: 0.0 | EY20: 0.0 | FC20: Z0000001 | FD20: 1.0 | FE20: 1.0 | FF20: 92RRA00548AAA | FG20: 107316.0 | FH20: 1.0 | FI20: M | FJ20: 0.0 | FL20: 2.0 | FM20: 2026-10-02 | FP20: 0.0 | FR20: 0.0 | FT20: 2.0 | FU20: 2.0 | FW20: GBP
A21: 100880202 | B21: REP | C21: 92RRA00548AAA | D21: R5B ERBIUM SPOOL ASSEMBLY - E2A | E21: 8000.0 | G21: 1 | H21: EA | I21: 46297 | J21: 0 | K21: 2026-10-02 | L21: TWRIGHT | O21: REL PRT PRC MANC SETC | Q21: 46297 | R21: 46303 | T21: ZSUBME | U21: 0.0 | Y21: 0:00:00 | AD21: 3.0 | AE21: 46286 | AF21: 10.0 | AG21: PP1 | AK21: 0.0 | AL21: 8000.0 | AO21: 0.0 | AR21: 0.0 | AS21: 10.0 | AT21: 14:22:03 | AV21: 7.0 | AW21: 1.0 | AX21: 5.0 | AZ21: 46295 | BC21: 0.0 | BE21: 0:00:00 | BF21: 0.0 | BJ21: 46302 | BK21: 24:00:00 | BL21: 24:00:00 | BM21: 1.0 | BR21: 46302 | BS21: 0:00:00 | BT21: 0:00:00 | BU21: 24:00:00 | BV21: 0.0 | BX21: 0 | CC21: PP-PC1 | CD21: 0.0 | CF21: 0.0 | CG21: PPP2 | CH21: PPP1 | CI21: 3000.0 | CM21: R5B ERBIUM SPOOL ASSEMBLY - E2A | CV21: 0.0 | DB21: 2013-01-01 | DD21: 46286 | DF21: 1.0 | DG21: P | DH21: 92RRA00548AAA | DI21: EA | DJ21: 50002963.0 | DK21: S | DL21: 99999999.0 | DM21: 0.0 | DN21: 8000.0 | DP21: 0:00:00 | DR21: 0:00:00 | DS21: 0.0 | DT21: 0.0 | DW21: 0.0 | EA21: % | EB21: 0.0 | EF21: 100880196.0 | EH21: 1.0 | EJ21: 0.0 | EK21: 153469748.0 | EM21: 0.0 | EN21: S9I00022645 | EP21: EA | EQ21: 1 | ER21: Production | ES21: 2026-03-01 | ET21: 1.0 | EU21: 1.0 | EV21: 1.0 | EX21: 0.0 | EY21: 0.0 | FC21: Z0000001 | FD21: 1.0 | FE21: 1.0 | FF21: 92RRA00548AAA | FG21: 107316.0 | FH21: 1.0 | FI21: M | FJ21: 0.0 | FL21: 2.0 | FM21: 2026-10-02 | FP21: 0.0 | FR21: 0.0 | FT21: 2.0 | FU21: 2.0 | FW21: GBP
A22: 100880203 | B22: REP | C22: 92RRA00548AAA | D22: R5B ERBIUM SPOOL ASSEMBLY - E2A | E22: 8000.0 | G22: 1 | H22: EA | I22: 46297 | J22: 0 | K22: 2026-10-02 | L22: TWRIGHT | O22: REL PRT PRC MANC SETC | Q22: 46297 | R22: 46303 | T22: ZSUBME | U22: 0.0 | Y22: 0:00:00 | AD22: 3.0 | AE22: 46286 | AF22: 10.0 | AG22: PP1 | AK22: 0.0 | AL22: 8000.0 | AO22: 0.0 | AR22: 0.0 | AS22: 10.0 | AT22: 14:22:06 | AV22: 7.0 | AW22: 1.0 | AX22: 5.0 | AZ22: 46295 | BC22: 0.0 | BE22: 0:00:00 | BF22: 0.0 | BJ22: 46302 | BK22: 24:00:00 | BL22: 24:00:00 | BM22: 1.0 | BR22: 46302 | BS22: 0:00:00 | BT22: 0:00:00 | BU22: 24:00:00 | BV22: 0.0 | BX22: 0 | CC22: PP-PC1 | CD22: 0.0 | CF22: 0.0 | CG22: PPP2 | CH22: PPP1 | CI22: 3000.0 | CM22: R5B ERBIUM SPOOL ASSEMBLY - E2A | CV22: 0.0 | DB22: 2013-01-01 | DD22: 46286 | DF22: 1.0 | DG22: P | DH22: 92RRA00548AAA | DI22: EA | DJ22: 50002963.0 | DK22: S | DL22: 99999999.0 | DM22: 0.0 | DN22: 8000.0 | DP22: 0:00:00 | DR22: 0:00:00 | DS22: 0.0 | DT22: 0.0 | DW22: 0.0 | EA22: % | EB22: 0.0 | EF22: 100880196.0 | EH22: 1.0 | EJ22: 0.0 | EK22: 153469749.0 | EM22: 0.0 | EN22: S9I00022645 | EP22: EA | EQ22: 1 | ER22: Production | ES22: 2026-03-01 | ET22: 1.0 | EU22: 1.0 | EV22: 1.0 | EX22: 0.0 | EY22: 0.0 | FC22: Z0000001 | FD22: 1.0 | FE22: 1.0 | FF22: 92RRA00548AAA | FG22: 107316.0 | FH22: 1.0 | FI22: M | FJ22: 0.0 | FL22: 2.0 | FM22: 2026-10-02 | FP22: 0.0 | FR22: 0.0 | FT22: 2.0 | FU22: 2.0 | FW22: GBP
A23: 100880204 | B23: REP | C23: 92RRA00548AAA | D23: R5B ERBIUM SPOOL ASSEMBLY - E2A | E23: 8000.0 | G23: 1 | H23: EA | I23: 46297 | J23: 0 | K23: 2026-10-02 | L23: TWRIGHT | O23: REL PRT PRC MANC SETC | Q23: 46297 | R23: 46303 | T23: ZSUBME | U23: 0.0 | Y23: 0:00:00 | AD23: 3.0 | AE23: 46286 | AF23: 10.0 | AG23: PP1 | AK23: 0.0 | AL23: 8000.0 | AO23: 0.0 | AR23: 0.0 | AS23: 10.0 | AT23: 14:22:09 | AV23: 7.0 | AW23: 1.0 | AX23: 5.0 | AZ23: 46295 | BC23: 0.0 | BE23: 0:00:00 | BF23: 0.0 | BJ23: 46302 | BK23: 24:00:00 | BL23: 24:00:00 | BM23: 1.0 | BR23: 46302 | BS23: 0:00:00 | BT23: 0:00:00 | BU23: 24:00:00 | BV23: 0.0 | BX23: 0 | CC23: PP-PC1 | CD23: 0.0 | CF23: 0.0 | CG23: PPP2 | CH23: PPP1 | CI23: 3000.0 | CM23: R5B ERBIUM SPOOL ASSEMBLY - E2A | CV23: 0.0 | DB23: 2013-01-01 | DD23: 46286 | DF23: 1.0 | DG23: P | DH23: 92RRA00548AAA | DI23: EA | DJ23: 50002963.0 | DK23: S | DL23: 99999999.0 | DM23: 0.0 | DN23: 8000.0 | DP23: 0:00:00 | DR23: 0:00:00 | DS23: 0.0 | DT23: 0.0 | DW23: 0.0 | EA23: % | EB23: 0.0 | EF23: 100880196.0 | EH23: 1.0 | EJ23: 0.0 | EK23: 153469750.0 | EM23: 0.0 | EN23: S9I00022645 | EP23: EA | EQ23: 1 | ER23: Production | ES23: 2026-03-01 | ET23: 1.0 | EU23: 1.0 | EV23: 1.0 | EX23: 0.0 | EY23: 0.0 | FC23: Z0000001 | FD23: 1.0 | FE23: 1.0 | FF23: 92RRA00548AAA | FG23: 107316.0 | FH23: 1.0 | FI23: M | FJ23: 0.0 | FL23: 2.0 | FM23: 2026-10-02 | FP23: 0.0 | FR23: 0.0 | FT23: 2.0 | FU23: 2.0 | FW23: GBP
A24: 100880205 | B24: REP | C24: 92RRA00548AAA | D24: R5B ERBIUM SPOOL ASSEMBLY - E2A | E24: 8000.0 | G24: 1 | H24: EA | I24: 46297 | J24: 0 | K24: 2026-10-02 | L24: TWRIGHT | O24: REL PRT PRC MANC SETC | Q24: 46297 | R24: 46303 | T24: ZSUBME | U24: 0.0 | Y24: 0:00:00 | AD24: 3.0 | AE24: 46286 | AF24: 10.0 | AG24: PP1 | AK24: 0.0 | AL24: 8000.0 | AO24: 0.0 | AR24: 0.0 | AS24: 10.0 | AT24: 14:22:12 | AV24: 7.0 | AW24: 1.0 | AX24: 5.0 | AZ24: 46295 | BC24: 0.0 | BE24: 0:00:00 | BF24: 0.0 | BJ24: 46302 | BK24: 24:00:00 | BL24: 24:00:00 | BM24: 1.0 | BR24: 46302 | BS24: 0:00:00 | BT24: 0:00:00 | BU24: 24:00:00 | BV24: 0.0 | BX24: 0 | CC24: PP-PC1 | CD24: 0.0 | CF24: 0.0 | CG24: PPP2 | CH24: PPP1 | CI24: 3000.0 | CM24: R5B ERBIUM SPOOL ASSEMBLY - E2A | CV24: 0.0 | DB24: 2013-01-01 | DD24: 46286 | DF24: 1.0 | DG24: P | DH24: 92RRA00548AAA | DI24: EA | DJ24: 50002963.0 | DK24: S | DL24: 99999999.0 | DM24: 0.0 | DN24: 8000.0 | DP24: 0:00:00 | DR24: 0:00:00 | DS24: 0.0 | DT24: 0.0 | DW24: 0.0 | EA24: % | EB24: 0.0 | EF24: 100880196.0 | EH24: 1.0 | EJ24: 0.0 | EK24: 153469751.0 | EM24: 0.0 | EN24: S9I00022645 | EP24: EA | EQ24: 1 | ER24: Production | ES24: 2026-03-01 | ET24: 1.0 | EU24: 1.0 | EV24: 1.0 | EX24: 0.0 | EY24: 0.0 | FC24: Z0000001 | FD24: 1.0 | FE24: 1.0 | FF24: 92RRA00548AAA | FG24: 107316.0 | FH24: 1.0 | FI24: M | FJ24: 0.0 | FL24: 2.0 | FM24: 2026-10-02 | FP24: 0.0 | FR24: 0.0 | FT24: 2.0 | FU24: 2.0 | FW24: GBP
A25: 100880206 | B25: REP | C25: 92RRA00548AAA | D25: R5B ERBIUM SPOOL ASSEMBLY - E2A | E25: 8000.0 | G25: 1 | H25: EA | I25: 46297 | J25: 0 | K25: 2026-10-02 | L25: TWRIGHT | O25: REL PRT PRC MANC SETC | Q25: 46297 | R25: 46303 | T25: ZSUBME | U25: 0.0 | Y25: 0:00:00 | AD25: 3.0 | AE25: 46286 | AF25: 10.0 | AG25: PP1 | AK25: 0.0 | AL25: 8000.0 | AO25: 0.0 | AR25: 0.0 | AS25: 10.0 | AT25: 14:22:15 | AV25: 7.0 | AW25: 1.0 | AX25: 5.0 | AZ25: 46295 | BC25: 0.0 | BE25: 0:00:00 | BF25: 0.0 | BJ25: 46302 | BK25: 24:00:00 | BL25: 24:00:00 | BM25: 1.0 | BR25: 46302 | BS25: 0:00:00 | BT25: 0:00:00 | BU25: 24:00:00 | BV25: 0.0 | BX25: 0 | CC25: PP-PC1 | CD25: 0.0 | CF25: 0.0 | CG25: PPP2 | CH25: PPP1 | CI25: 3000.0 | CM25: R5B ERBIUM SPOOL ASSEMBLY - E2A | CV25: 0.0 | DB25: 2013-01-01 | DD25: 46286 | DF25: 1.0 | DG25: P | DH25: 92RRA00548AAA | DI25: EA | DJ25: 50002963.0 | DK25: S | DL25: 99999999.0 | DM25: 0.0 | DN25: 8000.0 | DP25: 0:00:00 | DR25: 0:00:00 | DS25: 0.0 | DT25: 0.0 | DW25: 0.0 | EA25: % | EB25: 0.0 | EF25: 100880196.0 | EH25: 1.0 | EJ25: 0.0 | EK25: 153469752.0 | EM25: 0.0 | EN25: S9I00022645 | EP25: EA | EQ25: 1 | ER25: Production | ES25: 2026-03-01 | ET25: 1.0 | EU25: 1.0 | EV25: 1.0 | EX25: 0.0 | EY25: 0.0 | FC25: Z0000001 | FD25: 1.0 | FE25: 1.0 | FF25: 92RRA00548AAA | FG25: 107316.0 | FH25: 1.0 | FI25: M | FJ25: 0.0 | FL25: 2.0 | FM25: 2026-10-02 | FP25: 0.0 | FR25: 0.0 | FT25: 2.0 | FU25: 2.0 | FW25: GBP
A26: 100880207 | B26: REP | C26: 92RRA00548AAA | D26: R5B ERBIUM SPOOL ASSEMBLY - E2A | E26: 8000.0 | G26: 1 | H26: EA | I26: 46297 | J26: 0 | K26: 2026-10-02 | L26: TWRIGHT | O26: REL PRT PRC MANC SETC | Q26: 46297 | R26: 46303 | T26: ZSUBME | U26: 0.0 | Y26: 0:00:00 | AD26: 3.0 | AE26: 46286 | AF26: 10.0 | AG26: PP1 | AK26: 0.0 | AL26: 8000.0 | AO26: 0.0 | AR26: 0.0 | AS26: 10.0 | AT26: 14:22:18 | AV26: 7.0 | AW26: 1.0 | AX26: 5.0 | AZ26: 46295 | BC26: 0.0 | BE26: 0:00:00 | BF26: 0.0 | BJ26: 46302 | BK26: 24:00:00 | BL26: 24:00:00 | BM26: 1.0 | BR26: 46302 | BS26: 0:00:00 | BT26: 0:00:00 | BU26: 24:00:00 | BV26: 0.0 | BX26: 0 | CC26: PP-PC1 | CD26: 0.0 | CF26: 0.0 | CG26: PPP2 | CH26: PPP1 | CI26: 3000.0 | CM26: R5B ERBIUM SPOOL ASSEMBLY - E2A | CV26: 0.0 | DB26: 2013-01-01 | DD26: 46286 | DF26: 1.0 | DG26: P | DH26: 92RRA00548AAA | DI26: EA | DJ26: 50002963.0 | DK26: S | DL26: 99999999.0 | DM26: 0.0 | DN26: 8000.0 | DP26: 0:00:00 | DR26: 0:00:00 | DS26: 0.0 | DT26: 0.0 | DW26: 0.0 | EA26: % | EB26: 0.0 | EF26: 100880196.0 | EH26: 1.0 | EJ26: 0.0 | EK26: 153469753.0 | EM26: 0.0 | EN26: S9I00022645 | EP26: EA | EQ26: 1 | ER26: Production | ES26: 2026-03-01 | ET26: 1.0 | EU26: 1.0 | EV26: 1.0 | EX26: 0.0 | EY26: 0.0 | FC26: Z0000001 | FD26: 1.0 | FE26: 1.0 | FF26: 92RRA00548AAA | FG26: 107316.0 | FH26: 1.0 | FI26: M | FJ26: 0.0 | FL26: 2.0 | FM26: 2026-10-02 | FP26: 0.0 | FR26: 0.0 | FT26: 2.0 | FU26: 2.0 | FW26: GBP
A27: 100880208 | B27: REP | C27: 92RRA00548AAA | D27: R5B ERBIUM SPOOL ASSEMBLY - E2A | E27: 8000.0 | G27: 1 | H27: EA | I27: 46297 | J27: 0 | K27: 2026-10-02 | L27: TWRIGHT | O27: REL PRT PRC MANC SETC | Q27: 46297 | R27: 46303 | T27: ZSUBME | U27: 0.0 | Y27: 0:00:00 | AD27: 3.0 | AE27: 46286 | AF27: 10.0 | AG27: PP1 | AK27: 0.0 | AL27: 8000.0 | AO27: 0.0 | AR27: 0.0 | AS27: 10.0 | AT27: 14:22:21 | AV27: 7.0 | AW27: 1.0 | AX27: 5.0 | AZ27: 46295 | BC27: 0.0 | BE27: 0:00:00 | BF27: 0.0 | BJ27: 46302 | BK27: 24:00:00 | BL27: 24:00:00 | BM27: 1.0 | BR27: 46302 | BS27: 0:00:00 | BT27: 0:00:00 | BU27: 24:00:00 | BV27: 0.0 | BX27: 0 | CC27: PP-PC1 | CD27: 0.0 | CF27: 0.0 | CG27: PPP2 | CH27: PPP1 | CI27: 3000.0 | CM27: R5B ERBIUM SPOOL ASSEMBLY - E2A | CV27: 0.0 | DB27: 2013-01-01 | DD27: 46286 | DF27: 1.0 | DG27: P | DH27: 92RRA00548AAA | DI27: EA | DJ27: 50002963.0 | DK27: S | DL27: 99999999.0 | DM27: 0.0 | DN27: 8000.0 | DP27: 0:00:00 | DR27: 0:00:00 | DS27: 0.0 | DT27: 0.0 | DW27: 0.0 | EA27: % | EB27: 0.0 | EF27: 100880196.0 | EH27: 1.0 | EJ27: 0.0 | EK27: 153469754.0 | EM27: 0.0 | EN27: S9I00022645 | EP27: EA | EQ27: 1 | ER27: Production | ES27: 2026-03-01 | ET27: 1.0 | EU27: 1.0 | EV27: 1.0 | EX27: 0.0 | EY27: 0.0 | FC27: Z0000001 | FD27: 1.0 | FE27: 1.0 | FF27: 92RRA00548AAA | FG27: 107316.0 | FH27: 1.0 | FI27: M | FJ27: 0.0 | FL27: 2.0 | FM27: 2026-10-02 | FP27: 0.0 | FR27: 0.0 | FT27: 2.0 | FU27: 2.0 | FW27: GBP
... A38: 100880219 | B38: REP | C38: 92RRA00548AAA | D38: R5B ERBIUM SPOOL ASSEMBLY - E2A | E38: 8000.0 | G38: 1 | H38: EA | I38: 46297 | J38: 0 | K38: 2026-10-02 | L38: TWRIGHT | O38: REL PRT PRC MANC SETC | Q38: 46297 | R38: 46303 | T38: ZSUBME | U38: 0.0 | Y38: 0:00:00 | AD38: 3.0 | AE38: 46286 | AF38: 10.0 | AG38: PP1 | AK38: 0.0 | AL38: 8000.0 | AO38: 0.0 | AR38: 0.0 | AS38: 10.0 | AT38: 14:22:54 | AV38: 7.0 | AW38: 1.0 | AX38: 5.0 | AZ38: 46295 | BC38: 0.0 | BE38: 0:00:00 | BF38: 0.0 | BJ38: 46302 | BK38: 24:00:00 | BL38: 24:00:00 | BM38: 1.0 | BR38: 46302 | BS38: 0:00:00 | BT38: 0:00:00 | BU38: 24:00:00 | BV38: 0.0 | BX38: 0 | CC38: PP-PC1 | CD38: 0.0 | CF38: 0.0 | CG38: PPP2 | CH38: PPP1 | CI38: 3000.0 | CM38: R5B ERBIUM SPOOL ASSEMBLY - E2A | CV38: 0.0 | DB38: 2013-01-01 | DD38: 46286 | DF38: 1.0 | DG38: P | DH38: 92RRA00548AAA | DI38: EA | DJ38: 50002963.0 | DK38: S | DL38: 99999999.0 | DM38: 0.0 | DN38: 8000.0 | DP38: 0:00:00 | DR38: 0:00:00 | DS38: 0.0 | DT38: 0.0 | DW38: 0.0 | EA38: % | EB38: 0.0 | EF38: 100880196.0 | EH38: 1.0 | EJ38: 0.0 | EK38: 153469766.0 | EM38: 0.0 | EN38: S9I00022645 | EP38: EA | EQ38: 1 | ER38: Production | ES38: 2026-03-01 | ET38: 1.0 | EU38: 1.0 | EV38: 1.0 | EX38: 0.0 | EY38: 0.0 | FC38: Z0000001 | FD38: 1.0 | FE38: 1.0 | FF38: 92RRA00548AAA | FG38: 107316.0 | FH38: 1.0 | FI38: M | FJ38: 0.0 | FL38: 2.0 | FM38: 2026-10-02 | FP38: 0.0 | FR38: 0.0 | FT38: 2.0 | FU38: 2.0 | FW38: GBP
A39: 100880222 | B39: REP | C39: 92YRA01548AAA | D39: R5B ERBIUM ASSEMBLY 1 | E39: 8000.0 | G39: 1 | H39: EA | I39: 46297 | J39: 0 | K39: 2026-10-02 | L39: TWRIGHT | M39: 46297 | N39: TWRIGHT | O39: REL PRT PCNF PRC MANC SETC | Q39: 46297 | R39: 46304 | T39: ZSUBME | U39: 0.0 | Y39: 15:03:10 | AD39: 3.0 | AE39: 46289 | AF39: 10.0 | AG39: PP1 | AK39: 0.0 | AL39: 8000.0 | AO39: 0.0 | AR39: 0.0 | AS39: 10.0 | AT39: 15:03:07 | AV39: 7.0 | AW39: 1.0 | AX39: 5.0 | AZ39: 46295 | BC39: 0.0 | BE39: 0:00:00 | BF39: 0.0 | BJ39: 46302 | BK39: 0:00:00 | BL39: 24:00:00 | BM39: 1.0 | BQ39: 2026-10-03 | BR39: 46302 | BS39: 07:46:53 | BT39: 0:00:00 | BU39: 24:00:00 | BV39: 0.0 | BX39: 0 | CC39: PP-PC1 | CD39: 0.0 | CF39: 0.0 | CG39: PPP2 | CH39: PPP1 | CI39: 3000.0 | CM39: R5B ERBIUM ASSEMBLY 1 | CV39: 0.0 | DB39: 2013-01-01 | DD39: 46289 | DF39: 1.0 | DG39: P | DH39: 92YRA01548AAA | DI39: EA | DJ39: 50002992.0 | DK39: S | DL39: 99999999.0 | DM39: 0.0 | DN39: 8000.0 | DP39: 24:00:00 | DR39: 0:00:00 | DS39: 0.0 | DT39: 0.0 | DW39: 0.0 | EA39: % | EB39: 0.0 | EH39: 2.0 | EJ39: 0.0 | EK39: 153455604.0 | EM39: 0.0 | EN39: S9I00022646 | EP39: EA | EQ39: 1 | ER39: Production | ES39: 2026-03-01 | ET39: 1.0 | EU39: 1.0 | EV39: 1.0 | EX39: 0.0 | EY39: 0.0 | FC39: Z0000001 | FD39: 1.0 | FE39: 1.0 | FF39: 92YRA01548AAA | FG39: 107317.0 | FH39: 1.0 | FI39: M | FJ39: 0.0 | FL39: 2.0 | FM39: 2026-10-02 | FP39: 0.0 | FR39: 0.0 | FT39: 2.0 | FU39: 2.0 | FW39: GBP
A40: 100880223 | B40: REP | C40: 92YRA01548AAA | D40: R5B ERBIUM ASSEMBLY 1 | E40: 8000.0 | G40: 1 | H40: EA | I40: 46297 | J40: 0 | K40: 2026-10-02 | L40: TWRIGHT | O40: REL PRT PCNF PRC MANC SETC | Q40: 46297 | R40: 46303 | T40: ZSUBME | U40: 0.0 | Y40: 0:00:00 | AD40: 3.0 | AE40: 46289 | AF40: 10.0 | AG40: PP1 | AK40: 0.0 | AL40: 8000.0 | AO40: 0.0 | AR40: 0.0 | AS40: 10.0 | AT40: 15:03:13 | AV40: 7.0 | AW40: 1.0 | AX40: 5.0 | AZ40: 46295 | BC40: 0.0 | BE40: 0:00:00 | BF40: 0.0 | BJ40: 46302 | BK40: 24:00:00 | BL40: 24:00:00 | BM40: 1.0 | BQ40: 2026-10-03 | BR40: 46302 | BS40: 07:46:54 | BT40: 0:00:00 | BU40: 24:00:00 | BV40: 0.0 | BX40: 0 | CC40: PP-PC1 | CD40: 0.0 | CF40: 0.0 | CG40: PPP2 | CH40: PPP1 | CI40: 3000.0 | CM40: R5B ERBIUM ASSEMBLY 1 | CV40: 0.0 | DB40: 2013-01-01 | DD40: 46289 | DF40: 1.0 | DG40: P | DH40: 92YRA01548AAA | DI40: EA | DJ40: 50002992.0 | DK40: S | DL40: 99999999.0 | DM40: 0.0 | DN40: 8000.0 | DP40: 24:00:00 | DR40: 0:00:00 | DS40: 0.0 | DT40: 0.0 | DW40: 0.0 | EA40: % | EB40: 0.0 | EF40: 100880222.0 | EH40: 2.0 | EJ40: 0.0 | EK40: 153469778.0 | EM40: 0.0 | EN40: S9I00022646 | EP40: EA | EQ40: 1 | ER40: Production | ES40: 2026-03-01 | ET40: 1.0 | EU40: 1.0 | EV40: 1.0 | EX40: 0.0 | EY40: 0.0 | FC40: Z0000001 | FD40: 1.0 | FE40: 1.0 | FF40: 92YRA01548AAA | FG40: 107317.0 | FH40: 1.0 | FI40: M | FJ40: 0.0 | FL40: 2.0 | FM40: 2026-10-02 | FP40: 0.0 | FR40: 0.0 | FT40: 2.0 | FU40: 2.0 | FW40: GBP
A41: 100880224 | B41: REP | C41: 92YRA01548AAA | D41: R5B ERBIUM ASSEMBLY 1 | E41: 8000.0 | G41: 1 | H41: EA | I41: 46297 | J41: 0 | K41: 2026-10-02 | L41: TWRIGHT | O41: REL PRT PCNF PRC MANC SETC | Q41: 46297 | R41: 46303 | T41: ZSUBME | U41: 0.0 | Y41: 0:00:00 | AD41: 3.0 | AE41: 46289 | AF41: 10.0 | AG41: PP1 | AK41: 0.0 | AL41: 8000.0 | AO41: 0.0 | AR41: 0.0 | AS41: 10.0 | AT41: 15:03:16 | AV41: 7.0 | AW41: 1.0 | AX41: 5.0 | AZ41: 46295 | BC41: 0.0 | BE41: 0:00:00 | BF41: 0.0 | BJ41: 46302 | BK41: 24:00:00 | BL41: 24:00:00 | BM41: 1.0 | BQ41: 2026-10-03 | BR41: 46302 | BS41: 07:46:54 | BT41: 0:00:00 | BU41: 24:00:00 | BV41: 0.0 | BX41: 0 | CC41: PP-PC1 | CD41: 0.0 | CF41: 0.0 | CG41: PPP2 | CH41: PPP1 | CI41: 3000.0 | CM41: R5B ERBIUM ASSEMBLY 1 | CV41: 0.0 | DB41: 2013-01-01 | DD41: 46289 | DF41: 1.0 | DG41: P | DH41: 92YRA01548AAA | DI41: EA | DJ41: 50002992.0 | DK41: S | DL41: 99999999.0 | DM41: 0.0 | DN41: 8000.0 | DP41: 24:00:00 | DR41: 0:00:00 | DS41: 0.0 | DT41: 0.0 | DW41: 0.0 | EA41: % | EB41: 0.0 | EF41: 100880222.0 | EH41: 2.0 | EJ41: 0.0 | EK41: 153469779.0 | EM41: 0.0 | EN41: S9I00022646 | EP41: EA | EQ41: 1 | ER41: Production | ES41: 2026-03-01 | ET41: 1.0 | EU41: 1.0 | EV41: 1.0 | EX41: 0.0 | EY41: 0.0 | FC41: Z0000001 | FD41: 1.0 | FE41: 1.0 | FF41: 92YRA01548AAA | FG41: 107317.0 | FH41: 1.0 | FI41: M | FJ41: 0.0 | FL41: 2.0 | FM41: 2026-10-02 | FP41: 0.0 | FR41: 0.0 | FT41: 2.0 | FU41: 2.0 | FW41: GBP
A42: 100880225 | B42: REP | C42: 92YRA02548AAA | D42: R5B ERBIUM ASSEMBLY 2 | E42: 8000.0 | G42: 1 | H42: EA | I42: 46297 | J42: 0 | K42: 2026-10-02 | L42: TWRIGHT | M42: 46297 | N42: TWRIGHT | O42: REL PRT PCNF PRC MANC SETC | Q42: 46297 | R42: 46304 | T42: ZSUBME | U42: 0.0 | Y42: 15:04:59 | AD42: 3.0 | AE42: 46289 | AF42: 10.0 | AG42: PP1 | AK42: 0.0 | AL42: 8000.0 | AO42: 0.0 | AR42: 0.0 | AS42: 10.0 | AT42: 15:04:57 | AV42: 7.0 | AW42: 1.0 | AX42: 5.0 | AZ42: 46295 | BC42: 0.0 | BE42: 0:00:00 | BF42: 0.0 | BJ42: 46302 | BK42: 0:00:00 | BL42: 24:00:00 | BM42: 1.0 | BQ42: 2026-10-03 | BR42: 46302 | BS42: 07:46:54 | BT42: 0:00:00 | BU42: 24:00:00 | BV42: 0.0 | BX42: 0 | CC42: PP-PC1 | CD42: 0.0 | CF42: 0.0 | CG42: PPP2 | CH42: PPP1 | CI42: 3000.0 | CM42: R5B ERBIUM ASSEMBLY 2 | CV42: 0.0 | DB42: 2013-01-01 | DD42: 46289 | DF42: 1.0 | DG42: P | DH42: 92YRA02548AAA | DI42: EA | DJ42: 50002992.0 | DK42: S | DL42: 99999999.0 | DM42: 0.0 | DN42: 8000.0 | DP42: 24:00:00 | DR42: 0:00:00 | DS42: 0.0 | DT42: 0.0 | DW42: 0.0 | EA42: % | EB42: 0.0 | EH42: 2.0 | EJ42: 0.0 | EK42: 153455626.0 | EM42: 0.0 | EN42: S9I00022647 | EP42: EA | EQ42: 1 | ER42: Production | ES42: 2026-03-01 | ET42: 1.0 | EU42: 1.0 | EV42: 1.0 | EX42: 0.0 | EY42: 0.0 | FC42: Z0000001 | FD42: 1.0 | FE42: 1.0 | FF42: 92YRA02548AAA | FG42: 107318.0 | FH42: 1.0 | FI42: M | FJ42: 0.0 | FL42: 2.0 | FM42: 2026-10-02 | FP42: 0.0 | FR42: 0.0 | FT42: 2.0 | FU42: 2.0 | FW42: GBP
A43: 100880226 | B43: REP | C43: 92YRA02548AAA | D43: R5B ERBIUM ASSEMBLY 2 | E43: 8000.0 | G43: 1 | H43: EA | I43: 46297 | J43: 0 | K43: 2026-10-02 | L43: TWRIGHT | O43: REL PRT PCNF PRC MANC SETC | Q43: 46297 | R43: 46303 | T43: ZSUBME | U43: 0.0 | Y43: 0:00:00 | AD43: 3.0 | AE43: 46289 | AF43: 10.0 | AG43: PP1 | AK43: 0.0 | AL43: 8000.0 | AO43: 0.0 | AR43: 0.0 | AS43: 10.0 | AT43: 15:05:03 | AV43: 7.0 | AW43: 1.0 | AX43: 5.0 | AZ43: 46295 | BC43: 0.0 | BE43: 0:00:00 | BF43: 0.0 | BJ43: 46302 | BK43: 24:00:00 | BL43: 24:00:00 | BM43: 1.0 | BQ43: 2026-10-03 | BR43: 46302 | BS43: 07:46:55 | BT43: 0:00:00 | BU43: 24:00:00 | BV43: 0.0 | BX43: 0 | CC43: PP-PC1 | CD43: 0.0 | CF43: 0.0 | CG43: PPP2 | CH43: PPP1 | CI43: 3000.0 | CM43: R5B ERBIUM ASSEMBLY 2 | CV43: 0.0 | DB43: 2013-01-01 | DD43: 46289 | DF43: 1.0 | DG43: P | DH43: 92YRA02548AAA | DI43: EA | DJ43: 50002992.0 | DK43: S | DL43: 99999999.0 | DM43: 0.0 | DN43: 8000.0 | DP43: 24:00:00 | DR43: 0:00:00 | DS43: 0.0 | DT43: 0.0 | DW43: 0.0 | EA43: % | EB43: 0.0 | EF43: 100880225.0 | EH43: 2.0 | EJ43: 0.0 | EK43: 153469781.0 | EM43: 0.0 | EN43: S9I00022647 | EP43: EA | EQ43: 1 | ER43: Production | ES43: 2026-03-01 | ET43: 1.0 | EU43: 1.0 | EV43: 1.0 | EX43: 0.0 | EY43: 0.0 | FC43: Z0000001 | FD43: 1.0 | FE43: 1.0 | FF43: 92YRA02548AAA | FG43: 107318.0 | FH43: 1.0 | FI43: M | FJ43: 0.0 | FL43: 2.0 | FM43: 2026-10-02 | FP43: 0.0 | FR43: 0.0 | FT43: 2.0 | FU43: 2.0 | FW43: GBP
A44: 100880227 | B44: REP | C44: 92YRA02548AAA | D44: R5B ERBIUM ASSEMBLY 2 | E44: 8000.0 | G44: 1 | H44: EA | I44: 46297 | J44: 0 | K44: 2026-10-02 | L44: TWRIGHT | O44: REL PRT PCNF PRC MANC SETC | Q44: 46297 | R44: 46303 | T44: ZSUBME | U44: 0.0 | Y44: 0:00:00 | AD44: 3.0 | AE44: 46289 | AF44: 10.0 | AG44: PP1 | AK44: 0.0 | AL44: 8000.0 | AO44: 0.0 | AR44: 0.0 | AS44: 10.0 | AT44: 15:05:07 | AV44: 7.0 | AW44: 1.0 | AX44: 5.0 | AZ44: 46295 | BC44: 0.0 | BE44: 0:00:00 | BF44: 0.0 | BJ44: 46302 | BK44: 24:00:00 | BL44: 24:00:00 | BM44: 1.0 | BQ44: 2026-10-03 | BR44: 46302 | BS44: 07:46:55 | BT44: 0:00:00 | BU44: 24:00:00 | BV44: 0.0 | BX44: 0 | CC44: PP-PC1 | CD44: 0.0 | CF44: 0.0 | CG44: PPP2 | CH44: PPP1 | CI44: 3000.0 | CM44: R5B ERBIUM ASSEMBLY 2 | CV44: 0.0 | DB44: 2013-01-01 | DD44: 46289 | DF44: 1.0 | DG44: P | DH44: 92YRA02548AAA | DI44: EA | DJ44: 50002992.0 | DK44: S | DL44: 99999999.0 | DM44: 0.0 | DN44: 8000.0 | DP44: 24:00:00 | DR44: 0:00:00 | DS44: 0.0 | DT44: 0.0 | DW44: 0.0 | EA44: % | EB44: 0.0 | EF44: 100880225.0 | EH44: 2.0 | EJ44: 0.0 | EK44: 153469782.0 | EM44: 0.0 | EN44: S9I00022647 | EP44: EA | EQ44: 1 | ER44: Production | ES44: 2026-03-01 | ET44: 1.0 | EU44: 1.0 | EV44: 1.0 | EX44: 0.0 | EY44: 0.0 | FC44: Z0000001 | FD44: 1.0 | FE44: 1.0 | FF44: 92YRA02548AAA | FG44: 107318.0 | FH44: 1.0 | FI44: M | FJ44: 0.0 | FL44: 2.0 | FM44: 2026-10-02 | FP44: 0.0 | FR44: 0.0 | FT44: 2.0 | FU44: 2.0 | FW44: GBP
A45: 100880228 | B45: REP | C45: 92YRA03548AAA | D45: R5B ERBIUM ASSEMBLY 3 | E45: 8000.0 | G45: 1 | H45: EA | I45: 46297 | J45: 0 | K45: 2026-10-02 | L45: TWRIGHT | M45: 46297 | N45: TWRIGHT | O45: REL PRT PCNF PRC MANC SETC | Q45: 46297 | R45: 46304 | T45: ZSUBME | U45: 0.0 | Y45: 15:07:31 | AD45: 3.0 | AE45: 46293 | AF45: 10.0 | AG45: PP1 | AK45: 0.0 | AL45: 8000.0 | AO45: 0.0 | AR45: 0.0 | AS45: 10.0 | AT45: 15:07:28 | AV45: 7.0 | AW45: 1.0 | AX45: 5.0 | AZ45: 46295 | BC45: 0.0 | BE45: 0:00:00 | BF45: 0.0 | BJ45: 46302 | BK45: 0:00:00 | BL45: 24:00:00 | BM45: 1.0 | BQ45: 2026-10-03 | BR45: 46302 | BS45: 07:46:55 | BT45: 0:00:00 | BU45: 24:00:00 | BV45: 0.0 | BX45: 0 | CC45: PP-PC1 | CD45: 0.0 | CF45: 0.0 | CG45: PPP2 | CH45: PPP1 | CI45: 3000.0 | CM45: R5B ERBIUM ASSEMBLY 3 | CV45: 0.0 | DB45: 2013-01-01 | DD45: 46293 | DF45: 1.0 | DG45: P | DH45: 92YRA03548AAA | DI45: EA | DJ45: 50002992.0 | DK45: S | DL45: 99999999.0 | DM45: 0.0 | DN45: 8000.0 | DP45: 24:00:00 | DR45: 0:00:00 | DS45: 0.0 | DT45: 0.0 | DW45: 0.0 | EA45: % | EB45: 0.0 | EH45: 2.0 | EJ45: 0.0 | EK45: 153455648.0 | EM45: 0.0 | EN45: S9I00022648 | EP45: EA | EQ45: 1 | ER45: Production | ES45: 2026-03-01 | ET45: 1.0 | EU45: 1.0 | EV45: 1.0 | EX45: 0.0 | EY45: 0.0 | FC45: Z0000001 | FD45: 1.0 | FE45: 1.0 | FF45: 92YRA03548AAA | FG45: 107319.0 | FH45: 1.0 | FI45: M | FJ45: 0.0 | FL45: 2.0 | FM45: 2026-10-02 | FP45: 0.0 | FR45: 0.0 | FT45: 2.0 | FU45: 2.0 | FW45: GBP
A46: 100880229 | B46: REP | C46: 92YRA03548AAA | D46: R5B ERBIUM ASSEMBLY 3 | E46: 8000.0 | G46: 1 | H46: EA | I46: 46297 | J46: 0 | K46: 2026-10-02 | L46: TWRIGHT | O46: REL PRT PCNF PRC MANC SETC | Q46: 46297 | R46: 46303 | T46: ZSUBME | U46: 0.0 | Y46: 0:00:00 | AD46: 3.0 | AE46: 46293 | AF46: 10.0 | AG46: PP1 | AK46: 0.0 | AL46: 8000.0 | AO46: 0.0 | AR46: 0.0 | AS46: 10.0 | AT46: 15:07:35 | AV46: 7.0 | AW46: 1.0 | AX46: 5.0 | AZ46: 46295 | BC46: 0.0 | BE46: 0:00:00 | BF46: 0.0 | BJ46: 46302 | BK46: 24:00:00 | BL46: 24:00:00 | BM46: 1.0 | BQ46: 2026-10-03 | BR46: 46302 | BS46: 07:46:56 | BT46: 0:00:00 | BU46: 24:00:00 | BV46: 0.0 | BX46: 0 | CC46: PP-PC1 | CD46: 0.0 | CF46: 0.0 | CG46: PPP2 | CH46: PPP1 | CI46: 3000.0 | CM46: R5B ERBIUM ASSEMBLY 3 | CV46: 0.0 | DB46: 2013-01-01 | DD46: 46293 | DF46: 1.0 | DG46: P | DH46: 92YRA03548AAA | DI46: EA | DJ46: 50002992.0 | DK46: S | DL46: 99999999.0 | DM46: 0.0 | DN46: 8000.0 | DP46: 24:00:00 | DR46: 0:00:00 | DS46: 0.0 | DT46: 0.0 | DW46: 0.0 | EA46: % | EB46: 0.0 | EF46: 100880228.0 | EH46: 2.0 | EJ46: 0.0 | EK46: 153469784.0 | EM46: 0.0 | EN46: S9I00022648 | EP46: EA | EQ46: 1 | ER46: Production | ES46: 2026-03-01 | ET46: 1.0 | EU46: 1.0 | EV46: 1.0 | EX46: 0.0 | EY46: 0.0 | FC46: Z0000001 | FD46: 1.0 | FE46: 1.0 | FF46: 92YRA03548AAA | FG46: 107319.0 | FH46: 1.0 | FI46: M | FJ46: 0.0 | FL46: 2.0 | FM46: 2026-10-02 | FP46: 0.0 | FR46: 0.0 | FT46: 2.0 | FU46: 2.0 | FW46: GBP
A47: 100880230 | B47: REP | C47: 92YRA03548AAA | D47: R5B ERBIUM ASSEMBLY 3 | E47: 8000.0 | G47: 1 | H47: EA | I47: 46297 | J47: 0 | K47: 2026-10-02 | L47: TWRIGHT | O47: REL PRT PCNF PRC MANC SETC | Q47: 46297 | R47: 46303 | T47: ZSUBME | U47: 0.0 | Y47: 0:00:00 | AD47: 3.0 | AE47: 46293 | AF47: 10.0 | AG47: PP1 | AK47: 0.0 | AL47: 8000.0 | AO47: 0.0 | AR47: 0.0 | AS47: 10.0 | AT47: 15:07:39 | AV47: 7.0 | AW47: 1.0 | AX47: 5.0 | AZ47: 46295 | BC47: 0.0 | BE47: 0:00:00 | BF47: 0.0 | BJ47: 46302 | BK47: 24:00:00 | BL47: 24:00:00 | BM47: 1.0 | BQ47: 2026-10-03 | BR47: 46302 | BS47: 07:46:56 | BT47: 0:00:00 | BU47: 24:00:00 | BV47: 0.0 | BX47: 0 | CC47: PP-PC1 | CD47: 0.0 | CF47: 0.0 | CG47: PPP2 | CH47: PPP1 | CI47: 3000.0 | CM47: R5B ERBIUM ASSEMBLY 3 | CV47: 0.0 | DB47: 2013-01-01 | DD47: 46293 | DF47: 1.0 | DG47: P | DH47: 92YRA03548AAA | DI47: EA | DJ47: 50002992.0 | DK47: S | DL47: 99999999.0 | DM47: 0.0 | DN47: 8000.0 | DP47: 24:00:00 | DR47: 0:00:00 | DS47: 0.0 | DT47: 0.0 | DW47: 0.0 | EA47: % | EB47: 0.0 | EF47: 100880228.0 | EH47: 2.0 | EJ47: 0.0 | EK47: 153469785.0 | EM47: 0.0 | EN47: S9I00022648 | EP47: EA | EQ47: 1 | ER47: Production | ES47: 2026-03-01 | ET47: 1.0 | EU47: 1.0 | EV47: 1.0 | EX47: 0.0 | EY47: 0.0 | FC47: Z0000001 | FD47: 1.0 | FE47: 1.0 | FF47: 92YRA03548AAA | FG47: 107319.0 | FH47: 1.0 | FI47: M | FJ47: 0.0 | FL47: 2.0 | FM47: 2026-10-02 | FP47: 0.0 | FR47: 0.0 | FT47: 2.0 | FU47: 2.0 | FW47: GBP
A48: 100880231 | B48: REP | C48: 92YRA04548AAA | D48: R5B ERBIUM ASSEMBLY 4 | E48: 8000.0 | G48: 1 | H48: EA | I48: 46297 | J48: 0 | K48: 2026-10-02 | L48: TWRIGHT | M48: 46297 | N48: TWRIGHT | O48: REL PRT PCNF PRC MANC SETC | Q48: 46297 | R48: 46304 | T48: ZSUBME | U48: 0.0 | Y48: 15:08:58 | AD48: 3.0 | AE48: 46289 | AF48: 10.0 | AG48: PP1 | AK48: 0.0 | AL48: 8000.0 | AO48: 0.0 | AR48: 0.0 | AS48: 10.0 | AT48: 15:08:55 | AV48: 7.0 | AW48: 1.0 | AX48: 5.0 | AZ48: 46295 | BC48: 0.0 | BE48: 0:00:00 | BF48: 0.0 | BJ48: 46302 | BK48: 0:00:00 | BL48: 24:00:00 | BM48: 1.0 | BQ48: 2026-10-03 | BR48: 46302 | BS48: 07:46:57 | BT48: 0:00:00 | BU48: 24:00:00 | BV48: 0.0 | BX48: 0 | CC48: PP-PC1 | CD48: 0.0 | CF48: 0.0 | CG48: PPP2 | CH48: PPP1 | CI48: 3000.0 | CM48: R5B ERBIUM ASSEMBLY 4 | CV48: 0.0 | DB48: 2013-01-01 | DD48: 46289 | DF48: 1.0 | DG48: P | DH48: 92YRA04548AAA | DI48: EA | DJ48: 50002992.0 | DK48: S | DL48: 99999999.0 | DM48: 0.0 | DN48: 8000.0 | DP48: 24:00:00 | DR48: 0:00:00 | DS48: 0.0 | DT48: 0.0 | DW48: 0.0 | EA48: % | EB48: 0.0 | EH48: 2.0 | EJ48: 0.0 | EK48: 153455669.0 | EM48: 0.0 | EN48: S9I00022649 | EP48: EA | EQ48: 1 | ER48: Production | ES48: 2026-03-01 | ET48: 1.0 | EU48: 1.0 | EV48: 1.0 | EX48: 0.0 | EY48: 0.0 | FC48: Z0000001 | FD48: 1.0 | FE48: 1.0 | FF48: 92YRA04548AAA | FG48: 107320.0 | FH48: 1.0 | FI48: M | FJ48: 0.0 | FL48: 2.0 | FM48: 2026-10-02 | FP48: 0.0 | FR48: 0.0 | FT48: 2.0 | FU48: 2.0 | FW48: GBP
A49: 100880232 | B49: REP | C49: 92YRA04548AAA | D49: R5B ERBIUM ASSEMBLY 4 | E49: 8000.0 | G49: 1 | H49: EA | I49: 46297 | J49: 0 | K49: 2026-10-02 | L49: TWRIGHT | O49: REL PRT PCNF PRC MANC SETC | Q49: 46297 | R49: 46303 | T49: ZSUBME | U49: 0.0 | Y49: 0:00:00 | AD49: 3.0 | AE49: 46289 | AF49: 10.0 | AG49: PP1 | AK49: 0.0 | AL49: 8000.0 | AO49: 0.0 | AR49: 0.0 | AS49: 10.0 | AT49: 15:09:02 | AV49: 7.0 | AW49: 1.0 | AX49: 5.0 | AZ49: 46295 | BC49: 0.0 | BE49: 0:00:00 | BF49: 0.0 | BJ49: 46302 | BK49: 24:00:00 | BL49: 24:00:00 | BM49: 1.0 | BQ49: 2026-10-03 | BR49: 46302 | BS49: 07:46:57 | BT49: 0:00:00 | BU49: 24:00:00 | BV49: 0.0 | BX49: 0 | CC49: PP-PC1 | CD49: 0.0 | CF49: 0.0 | CG49: PPP2 | CH49: PPP1 | CI49: 3000.0 | CM49: R5B ERBIUM ASSEMBLY 4 | CV49: 0.0 | DB49: 2013-01-01 | DD49: 46289 | DF49: 1.0 | DG49: P | DH49: 92YRA04548AAA | DI49: EA | DJ49: 50002992.0 | DK49: S | DL49: 99999999.0 | DM49: 0.0 | DN49: 8000.0 | DP49: 24:00:00 | DR49: 0:00:00 | DS49: 0.0 | DT49: 0.0 | DW49: 0.0 | EA49: % | EB49: 0.0 | EF49: 100880231.0 | EH49: 2.0 | EJ49: 0.0 | EK49: 153469787.0 | EM49: 0.0 | EN49: S9I00022649 | EP49: EA | EQ49: 1 | ER49: Production | ES49: 2026-03-01 | ET49: 1.0 | EU49: 1.0 | EV49: 1.0 | EX49: 0.0 | EY49: 0.0 | FC49: Z0000001 | FD49: 1.0 | FE49: 1.0 | FF49: 92YRA04548AAA | FG49: 107320.0 | FH49: 1.0 | FI49: M | FJ49: 0.0 | FL49: 2.0 | FM49: 2026-10-02 | FP49: 0.0 | FR49: 0.0 | FT49: 2.0 | FU49: 2.0 | FW49: GBP
A50: 100880233 | B50: REP | C50: 92YRA04548AAA | D50: R5B ERBIUM ASSEMBLY 4 | E50: 8000.0 | G50: 1 | H50: EA | I50: 46297 | J50: 0 | K50: 2026-10-02 | L50: TWRIGHT | O50: REL PRT PCNF PRC MANC SETC | Q50: 46297 | R50: 46303 | T50: ZSUBME | U50: 0.0 | Y50: 0:00:00 | AD50: 3.0 | AE50: 46289 | AF50: 10.0 | AG50: PP1 | AK50: 0.0 | AL50: 8000.0 | AO50: 0.0 | AR50: 0.0 | AS50: 10.0 | AT50: 15:09:05 | AV50: 7.0 | AW50: 1.0 | AX50: 5.0 | AZ50: 46295 | BC50: 0.0 | BE50: 0:00:00 | BF50: 0.0 | BJ50: 46302 | BK50: 24:00:00 | BL50: 24:00:00 | BM50: 1.0 | BQ50: 2026-10-03 | BR50: 46302 | BS50: 07:46:57 | BT50: 0:00:00 | BU50: 24:00:00 | BV50: 0.0 | BX50: 0 | CC50: PP-PC1 | CD50: 0.0 | CF50: 0.0 | CG50: PPP2 | CH50: PPP1 | CI50: 3000.0 | CM50: R5B ERBIUM ASSEMBLY 4 | CV50: 0.0 | DB50: 2013-01-01 | DD50: 46289 | DF50: 1.0 | DG50: P | DH50: 92YRA04548AAA | DI50: EA | DJ50: 50002992.0 | DK50: S | DL50: 99999999.0 | DM50: 0.0 | DN50: 8000.0 | DP50: 24:00:00 | DR50: 0:00:00 | DS50: 0.0 | DT50: 0.0 | DW50: 0.0 | EA50: % | EB50: 0.0 | EF50: 100880231.0 | EH50: 2.0 | EJ50: 0.0 | EK50: 153469788.0 | EM50: 0.0 | EN50: S9I00022649 | EP50: EA | EQ50: 1 | ER50: Production | ES50: 2026-03-01 | ET50: 1.0 | EU50: 1.0 | EV50: 1.0 | EX50: 0.0 | EY50: 0.0 | FC50: Z0000001 | FD50: 1.0 | FE50: 1.0 | FF50: 92YRA04548AAA | FG50: 107320.0 | FH50: 1.0 | FI50: M | FJ50: 0.0 | FL50: 2.0 | FM50: 2026-10-02 | FP50: 0.0 | FR50: 0.0 | FT50: 2.0 | FU50: 2.0 | FW50: GBP
A51: 100880234 | B51: REP | C51: 92UAP04548BAA | D51: R5B BOAT 1 ASSY (4P-4FP) L - E2A | E51: 8000.0 | G51: 1 | H51: EA | I51: 46297 | J51: 0 | K51: 2026-10-02 | L51: TWRIGHT | M51: 46297 | N51: TWRIGHT | O51: REL PRT PRC MANC SETC | Q51: 46297 | R51: 46325 | T51: ZSUBME | U51: 0.0 | Y51: 15:16:22 | AD51: 3.0 | AE51: 46268 | AF51: 10.0 | AG51: PP1 | AK51: 0.0 | AL51: 8000.0 | AO51: 0.0 | AR51: 0.0 | AS51: 10.0 | AT51: 15:16:19 | AV51: 7.0 | AW51: 1.0 | AX51: 5.0 | AZ51: 46316 | BC51: 0.0 | BE51: 0:00:00 | BF51: 0.0 | BJ51: 46323 | BK51: 0:00:00 | BL51: 24:00:00 | BM51: 1.0 | BR51: 46323 | BS51: 0:00:00 | BT51: 0:00:00 | BU51: 24:00:00 | BV51: 0.0 | BX51: 0 | CC51: PP-PC1 | CD51: 0.0 | CF51: 0.0 | CG51: PPP2 | CH51: PPP1 | CI51: 3000.0 | CM51: R5B BOAT 1 ASSY (4P-4FP) L - E2A | CV51: 0.0 | DB51: 2013-01-01 | DD51: 46268 | DF51: 1.0 | DG51: P | DH51: 92UAP04548BAA | DI51: EA | DJ51: 50002990.0 | DK51: S | DL51: 99999999.0 | DM51: 0.0 | DN51: 8000.0 | DP51: 0:00:00 | DR51: 0:00:00 | DS51: 0.0 | DT51: 0.0 | DW51: 0.0 | EA51: % | EB51: 0.0 | EH51: 1.0 | EJ51: 0.0 | EK51: 153453354.0 | EM51: 0.0 | EN51: S9I00022652 | EP51: EA | EQ51: 1 | ER51: Production | ES51: 2026-03-01 | ET51: 1.0 | EU51: 1.0 | EV51: 1.0 | EX51: 0.0 | EY51: 0.0 | FC51: Z0000001 | FD51: 1.0 | FE51: 1.0 | FF51: 92UAP04548BAA | FG51: 107323.0 | FH51: 1.0 | FI51: M | FJ51: 0.0 | FL51: 2.0 | FM51: 2026-10-02 | FP51: 0.0 | FR51: 0.0 | FT51: 2.0 | FU51: 2.0 | FW51: GBP | FX51: MNT_SU
A52: 100880235 | B52: REP | C52: 92UAP04548BBA | D52: R5B BOAT 2 ASSY (4P-4FP) L - E2A | E52: 8000.0 | G52: 1 | H52: EA | I52: 46297 | J52: 0 | K52: 2026-10-02 | L52: TWRIGHT | M52: 46297 | N52: TWRIGHT | O52: REL PRT PRC MANC SETC | Q52: 46297 | R52: 46325 | T52: ZSUBME | U52: 0.0 | Y52: 15:22:13 | AD52: 3.0 | AE52: 46268 | AF52: 10.0 | AG52: PP1 | AK52: 0.0 | AL52: 8000.0 | AO52: 0.0 | AR52: 0.0 | AS52: 10.0 | AT52: 15:22:10 | AV52: 7.0 | AW52: 1.0 | AX52: 5.0 | AZ52: 46316 | BC52: 0.0 | BE52: 0:00:00 | BF52: 0.0 | BJ52: 46323 | BK52: 0:00:00 | BL52: 24:00:00 | BM52: 1.0 | BR52: 46323 | BS52: 0:00:00 | BT52: 0:00:00 | BU52: 24:00:00 | BV52: 0.0 | BX52: 0 | CC52: PP-PC1 | CD52: 0.0 | CF52: 0.0 | CG52: PPP2 | CH52: PPP1 | CI52: 3000.0 | CM52: R5B BOAT 2 ASSY (4P-4FP) L - E2A | CV52: 0.0 | DB52: 2013-01-01 | DD52: 46268 | DF52: 1.0 | DG52: P | DH52: 92UAP04548BBA | DI52: EA | DJ52: 50002990.0 | DK52: S | DL52: 99999999.0 | DM52: 0.0 | DN52: 8000.0 | DP52: 0:00:00 | DR52: 0:00:00 | DS52: 0.0 | DT52: 0.0 | DW52: 0.0 | EA52: % | EB52: 0.0 | EH52: 1.0 | EJ52: 0.0 | EK52: 153453379.0 | EM52: 0.0 | EN52: S9I00022653 | EP52: EA | EQ52: 1 | ER52: Production | ES52: 2026-03-01 | ET52: 1.0 | EU52: 1.0 | EV52: 1.0 | EX52: 0.0 | EY52: 0.0 | FC52: Z0000001 | FD52: 1.0 | FE52: 1.0 | FF52: 92UAP04548BBA | FG52: 107341.0 | FH52: 1.0 | FI52: M | FJ52: 0.0 | FL52: 2.0 | FM52: 2026-10-02 | FP52: 0.0 | FR52: 0.0 | FT52: 2.0 | FU52: 2.0 | FW52: GBP | FX52: MNT_SU
A53: 100880236 | B53: REP | C53: 92UAP04548BCA | D53: R5B BOAT 3 ASSY (4P-4FP) L - E2A | E53: 8000.0 | G53: 1 | H53: EA | I53: 46297 | J53: 0 | K53: 2026-10-02 | L53: TWRIGHT | M53: 46297 | N53: TWRIGHT | O53: REL PRT PRC MANC SETC | Q53: 46297 | R53: 46325 | T53: ZSUBME | U53: 0.0 | Y53: 15:25:10 | AD53: 3.0 | AE53: 46268 | AF53: 10.0 | AG53: PP1 | AK53: 0.0 | AL53: 8000.0 | AO53: 0.0 | AR53: 0.0 | AS53: 10.0 | AT53: 15:25:07 | AV53: 7.0 | AW53: 1.0 | AX53: 5.0 | AZ53: 46316 | BC53: 0.0 | BE53: 0:00:00 | BF53: 0.0 | BJ53: 46323 | BK53: 0:00:00 | BL53: 24:00:00 | BM53: 1.0 | BR53: 46323 | BS53: 0:00:00 | BT53: 0:00:00 | BU53: 24:00:00 | BV53: 0.0 | BX53: 0 | CC53: PP-PC1 | CD53: 0.0 | CF53: 0.0 | CG53: PPP2 | CH53: PPP1 | CI53: 3000.0 | CM53: R5B BOAT 3 ASSY (4P-4FP) L - E2A | CV53: 0.0 | DB53: 2013-01-01 | DD53: 46268 | DF53: 1.0 | DG53: P | DH53: 92UAP04548BCA | DI53: EA | DJ53: 50002990.0 | DK53: S | DL53: 99999999.0 | DM53: 0.0 | DN53: 8000.0 | DP53: 0:00:00 | DR53: 0:00:00 | DS53: 0.0 | DT53: 0.0 | DW53: 0.0 | EA53: % | EB53: 0.0 | EH53: 1.0 | EJ53: 0.0 | EK53: 153453400.0 | EM53: 0.0 | EN53: S9I00022690 | EP53: EA | EQ53: 1 | ER53: Production | ES53: 2026-03-01 | ET53: 1.0 | EU53: 1.0 | EV53: 1.0 | EX53: 0.0 | EY53: 0.0 | FC53: Z0000001 | FD53: 1.0 | FE53: 1.0 | FF53: 92UAP04548BCA | FG53: 107349.0 | FH53: 1.0 | FI53: M | FJ53: 0.0 | FL53: 2.0 | FM53: 2026-10-02 | FP53: 0.0 | FR53: 0.0 | FT53: 2.0 | FU53: 2.0 | FW53: GBP | FX53: MNT_SU
A54: 100880245 | B54: REP | C54: 92YLS00548BAA | D54: R5B LASER ASSEMBLY 4P BOAT 1 - E2A | E54: 8000.0 | G54: 1 | H54: EA | I54: 46297 | J54: 0 | K54: 2026-10-02 | L54: TWRIGHT | M54: 46297 | N54: TWRIGHT | O54: REL PRT PRC MANC SETC | Q54: 46297 | R54: 46304 | T54: ZSUBME | U54: 0.0 | Y54: 16:51:22 | AD54: 3.0 | AE54: 46287 | AF54: 10.0 | AG54: PP1 | AK54: 0.0 | AL54: 8000.0 | AO54: 0.0 | AR54: 0.0 | AS54: 10.0 | AT54: 16:51:19 | AV54: 7.0 | AW54: 1.0 | AX54: 5.0 | AZ54: 46289 | BC54: 0.0 | BE54: 0:00:00 | BF54: 0.0 | BJ54: 46302 | BK54: 0:00:00 | BL54: 24:00:00 | BM54: 1.0 | BR54: 46296 | BS54: 0:00:00 | BT54: 0:00:00 | BU54: 0:00:00 | BV54: 0.0 | BX54: 0 | CC54: PP-PC1 | CD54: 0.0 | CF54: 0.0 | CG54: PPP2 | CH54: PPP1 | CI54: 3000.0 | CM54: R5B LASER ASSEMBLY 4P BOAT 1 - E2A | CV54: 0.0 | DB54: 2013-01-01 | DD54: 46287 | DF54: 1.0 | DG54: P | DH54: 92YLS00548BAA | DI54: EA | DJ54: 50003000.0 | DK54: S | DL54: 99999999.0 | DM54: 0.0 | DN54: 8000.0 | DP54: 0:00:00 | DR54: 0:00:00 | DS54: 0.0 | DT54: 0.0 | DW54: 0.0 | EA54: % | EB54: 0.0 | EH54: 1.0 | EJ54: 0.0 | EK54: 153458218.0 | EM54: 0.0 | EN54: S9I00022630 | EP54: EA | EQ54: 1 | ER54: Production | ES54: 2026-02-01 | ET54: 1.0 | EU54: 1.0 | EV54: 1.0 | EX54: 0.0 | EY54: 0.0 | FC54: Z0000001 | FD54: 1.0 | FE54: 1.0 | FF54: 92YLS00548BAA | FG54: 107280.0 | FH54: 1.0 | FI54: M | FJ54: 0.0 | FL54: 2.0 | FM54: 2026-10-02 | FP54: 0.0 | FR54: 0.0 | FT54: 2.0 | FU54: 2.0 | FW54: GBP
A55: 100880246 | B55: REP | C55: 92YLS00548BBA | D55: R5B LASER ASSEMBLY 4P BOAT 2/3 - E2A | E55: 8000.0 | G55: 1 | H55: EA | I55: 46297 | J55: 0 | K55: 2026-10-02 | L55: TWRIGHT | M55: 46297 | N55: TWRIGHT | O55: REL PRT PRC MANC SETC | Q55: 46297 | R55: 46304 | T55: ZSUBME | U55: 0.0 | Y55: 16:58:32 | AD55: 3.0 | AE55: 46287 | AF55: 10.0 | AG55: PP1 | AK55: 0.0 | AL55: 8000.0 | AO55: 0.0 | AR55: 0.0 | AS55: 10.0 | AT55: 16:58:29 | AV55: 7.0 | AW55: 1.0 | AX55: 5.0 | AZ55: 46289 | BC55: 0.0 | BE55: 0:00:00 | BF55: 0.0 | BJ55: 46302 | BK55: 0:00:00 | BL55: 24:00:00 | BM55: 1.0 | BR55: 46296 | BS55: 0:00:00 | BT55: 0:00:00 | BU55: 0:00:00 | BV55: 0.0 | BX55: 0 | CC55: PP-PC1 | CD55: 0.0 | CF55: 0.0 | CG55: PPP2 | CH55: PPP1 | CI55: 3000.0 | CM55: R5B LASER ASSEMBLY 4P BOAT 2/3 - E2A | CV55: 0.0 | DB55: 2013-01-01 | DD55: 46287 | DF55: 1.0 | DG55: P | DH55: 92YLS00548BBA | DI55: EA | DJ55: 50003001.0 | DK55: S | DL55: 99999999.0 | DM55: 0.0 | DN55: 8000.0 | DP55: 0:00:00 | DR55: 0:00:00 | DS55: 0.0 | DT55: 0.0 | DW55: 0.0 | EA55: % | EB55: 0.0 | EH55: 1.0 | EJ55: 0.0 | EK55: 153458241.0 | EM55: 0.0 | EN55: S9I00022633 | EP55: EA | EQ55: 1 | ER55: Production | ES55: 2026-02-01 | ET55: 1.0 | EU55: 1.0 | EV55: 1.0 | EX55: 0.0 | EY55: 0.0 | FC55: Z0000001 | FD55: 1.0 | FE55: 1.0 | FF55: 92YLS00548BBA | FG55: 107294.0 | FH55: 1.0 | FI55: M | FJ55: 0.0 | FL55: 2.0 | FM55: 2026-10-02 | FP55: 0.0 | FR55: 0.0 | FT55: 2.0 | FU55: 2.0 | FW55: GBP
A56: 100880247 | B56: REP | C56: 92YLS00548BBA | D56: R5B LASER ASSEMBLY 4P BOAT 2/3 - E2A | E56: 8000.0 | G56: 1 | H56: EA | I56: 46297 | J56: 0 | K56: 2026-10-02 | L56: TWRIGHT | O56: REL PRT PRC MANC SETC | Q56: 46297 | R56: 46303 | T56: ZSUBME | U56: 0.0 | Y56: 0:00:00 | AD56: 3.0 | AE56: 46287 | AF56: 10.0 | AG56: PP1 | AK56: 0.0 | AL56: 8000.0 | AO56: 0.0 | AR56: 0.0 | AS56: 10.0 | AT56: 16:58:35 | AV56: 7.0 | AW56: 1.0 | AX56: 5.0 | AZ56: 46289 | BC56: 0.0 | BE56: 0:00:00 | BF56: 0.0 | BJ56: 46302 | BK56: 24:00:00 | BL56: 24:00:00 | BM56: 1.0 | BR56: 46296 | BS56: 0:00:00 | BT56: 0:00:00 | BU56: 0:00:00 | BV56: 0.0 | BX56: 0 | CC56: PP-PC1 | CD56: 0.0 | CF56: 0.0 | CG56: PPP2 | CH56: PPP1 | CI56: 3000.0 | CM56: R5B LASER ASSEMBLY 4P BOAT 2/3 - E2A | CV56: 0.0 | DB56: 2013-01-01 | DD56: 46287 | DF56: 1.0 | DG56: P | DH56: 92YLS00548BBA | DI56: EA | DJ56: 50003001.0 | DK56: S | DL56: 99999999.0 | DM56: 0.0 | DN56: 8000.0 | DP56: 0:00:00 | DR56: 0:00:00 | DS56: 0.0 | DT56: 0.0 | DW56: 0.0 | EA56: % | EB56: 0.0 | EF56: 100880246.0 | EH56: 1.0 | EJ56: 0.0 | EK56: 153469803.0 | EM56: 0.0 | EN56: S9I00022633 | EP56: EA | EQ56: 1 | ER56: Production | ES56: 2026-02-01 | ET56: 1.0 | EU56: 1.0 | EV56: 1.0 | EX56: 0.0 | EY56: 0.0 | FC56: Z0000001 | FD56: 1.0 | FE56: 1.0 | FF56: 92YLS00548BBA | FG56: 107294.0 | FH56: 1.0 | FI56: M | FJ56: 0.0 | FL56: 2.0 | FM56: 2026-10-02 | FP56: 0.0 | FR56: 0.0 | FT56: 2.0 | FU56: 2.0 | FW56: GBP
A57: 100880248 | B57: REP | C57: 91YAF03404AAA | D57: R5B PSB SUB ASSEMBLY 4P-4FP | E57: 8000.0 | G57: 1 | H57: EA | I57: 46297 | J57: 0 | K57: 2026-10-02 | L57: TWRIGHT | M57: 46297 | N57: TWRIGHT | O57: REL PRT PRC MANC SETC | Q57: 46297 | R57: 46304 | T57: ZSUBME | U57: 0.0 | Y57: 17:33:18 | AD57: 3.0 | AE57: 46279 | AF57: 10.0 | AG57: PP1 | AK57: 0.0 | AL57: 8000.0 | AO57: 0.0 | AR57: 0.0 | AS57: 10.0 | AT57: 17:33:15 | AV57: 7.0 | AW57: 1.0 | AX57: 5.0 | AZ57: 46289 | BC57: 0.0 | BE57: 0:00:00 | BF57: 0.0 | BJ57: 46302 | BK57: 0:00:00 | BL57: 24:00:00 | BM57: 1.0 | BR57: 46296 | BS57: 0:00:00 | BT57: 0:00:00 | BU57: 0:00:00 | BV57: 0.0 | BX57: 0 | CC57: PP-PC1 | CD57: 0.0 | CF57: 0.0 | CG57: PPP2 | CH57: PPP1 | CI57: 3000.0 | CM57: R5B PSB SUB ASSEMBLY 4P-4FP | CV57: 0.0 | DB57: 2013-01-01 | DD57: 46279 | DF57: 1.0 | DG57: P | DH57: 91YAF03404AAA | DI57: EA | DJ57: 50002999.0 | DK57: S | DL57: 99999999.0 | DM57: 0.0 | DN57: 8000.0 | DP57: 0:00:00 | DR57: 0:00:00 | DS57: 0.0 | DT57: 0.0 | DW57: 0.0 | EA57: % | EB57: 0.0 | EH57: 1.0 | EJ57: 0.0 | EK57: 153459990.0 | EM57: 0.0 | EN57: S9I00020481 | EP57: EA | EQ57: 1 | ER57: Production | ES57: 2025-06-23 | ET57: 1.0 | EU57: 1.0 | EV57: 1.0 | EX57: 0.0 | EY57: 0.0 | FC57: Z0000001 | FD57: 1.0 | FE57: 1.0 | FF57: 91YAF03404AAA | FG57: 104710.0 | FH57: 1.0 | FI57: M | FJ57: 0.0 | FL57: 2.0 | FM57: 2026-10-02 | FP57: 0.0 | FR57: 0.0 | FT57: 2.0 | FU57: 2.0 | FW57: GBP
A58: 100880249 | B58: REP | C58: 91YAF03404AAA | D58: R5B PSB SUB ASSEMBLY 4P-4FP | E58: 8000.0 | G58: 1 | H58: EA | I58: 46297 | J58: 0 | K58: 2026-10-02 | L58: TWRIGHT | O58: REL PRT PRC MANC SETC | Q58: 46297 | R58: 46303 | T58: ZSUBME | U58: 0.0 | Y58: 0:00:00 | AD58: 3.0 | AE58: 46279 | AF58: 10.0 | AG58: PP1 | AK58: 0.0 | AL58: 8000.0 | AO58: 0.0 | AR58: 0.0 | AS58: 10.0 | AT58: 17:33:21 | AV58: 7.0 | AW58: 1.0 | AX58: 5.0 | AZ58: 46289 | BC58: 0.0 | BE58: 0:00:00 | BF58: 0.0 | BJ58: 46302 | BK58: 24:00:00 | BL58: 24:00:00 | BM58: 1.0 | BR58: 46296 | BS58: 0:00:00 | BT58: 0:00:00 | BU58: 0:00:00 | BV58: 0.0 | BX58: 0 | CC58: PP-PC1 | CD58: 0.0 | CF58: 0.0 | CG58: PPP2 | CH58: PPP1 | CI58: 3000.0 | CM58: R5B PSB SUB ASSEMBLY 4P-4FP | CV58: 0.0 | DB58: 2013-01-01 | DD58: 46279 | DF58: 1.0 | DG58: P | DH58: 91YAF03404AAA | DI58: EA | DJ58: 50002999.0 | DK58: S | DL58: 99999999.0 | DM58: 0.0 | DN58: 8000.0 | DP58: 0:00:00 | DR58: 0:00:00 | DS58: 0.0 | DT58: 0.0 | DW58: 0.0 | EA58: % | EB58: 0.0 | EF58: 100880248.0 | EH58: 1.0 | EJ58: 0.0 | EK58: 153469805.0 | EM58: 0.0 | EN58: S9I00020481 | EP58: EA | EQ58: 1 | ER58: Production | ES58: 2025-06-23 | ET58: 1.0 | EU58: 1.0 | EV58: 1.0 | EX58: 0.0 | EY58: 0.0 | FC58: Z0000001 | FD58: 1.0 | FE58: 1.0 | FF58: 91YAF03404AAA | FG58: 104710.0 | FH58: 1.0 | FI58: M | FJ58: 0.0 | FL58: 2.0 | FM58: 2026-10-02 | FP58: 0.0 | FR58: 0.0 | FT58: 2.0 | FU58: 2.0 | FW58: GBP
A59: 100880250 | B59: REP | C59: 91YAF03404AAA | D59: R5B PSB SUB ASSEMBLY 4P-4FP | E59: 8000.0 | G59: 1 | H59: EA | I59: 46297 | J59: 0 | K59: 2026-10-02 | L59: TWRIGHT | O59: REL PRT PRC MANC SETC | Q59: 46297 | R59: 46303 | T59: ZSUBME | U59: 0.0 | Y59: 0:00:00 | AD59: 3.0 | AE59: 46279 | AF59: 10.0 | AG59: PP1 | AK59: 0.0 | AL59: 8000.0 | AO59: 0.0 | AR59: 0.0 | AS59: 10.0 | AT59: 17:33:25 | AV59: 7.0 | AW59: 1.0 | AX59: 5.0 | AZ59: 46289 | BC59: 0.0 | BE59: 0:00:00 | BF59: 0.0 | BJ59: 46302 | BK59: 24:00:00 | BL59: 24:00:00 | BM59: 1.0 | BR59: 46296 | BS59: 0:00:00 | BT59: 0:00:00 | BU59: 0:00:00 | BV59: 0.0 | BX59: 0 | CC59: PP-PC1 | CD59: 0.0 | CF59: 0.0 | CG59: PPP2 | CH59: PPP1 | CI59: 3000.0 | CM59: R5B PSB SUB ASSEMBLY 4P-4FP | CV59: 0.0 | DB59: 2013-01-01 | DD59: 46279 | DF59: 1.0 | DG59: P | DH59: 91YAF03404AAA | DI59: EA | DJ59: 50002999.0 | DK59: S | DL59: 99999999.0 | DM59: 0.0 | DN59: 8000.0 | DP59: 0:00:00 | DR59: 0:00:00 | DS59: 0.0 | DT59: 0.0 | DW59: 0.0 | EA59: % | EB59: 0.0 | EF59: 100880248.0 | EH59: 1.0 | EJ59: 0.0 | EK59: 153469806.0 | EM59: 0.0 | EN59: S9I00020481 | EP59: EA | EQ59: 1 | ER59: Production | ES59: 2025-06-23 | ET59: 1.0 | EU59: 1.0 | EV59: 1.0 | EX59: 0.0 | EY59: 0.0 | FC59: Z0000001 | FD59: 1.0 | FE59: 1.0 | FF59: 91YAF03404AAA | FG59: 104710.0 | FH59: 1.0 | FI59: M | FJ59: 0.0 | FL59: 2.0 | FM59: 2026-10-02 | FP59: 0.0 | FR59: 0.0 | FT59: 2.0 | FU59: 2.0 | FW59: GBP
A60: 100880251 | B60: REP | C60: 92YFD04548BAA | D60: R5B OPF ASSEMBLY (4P-4FP) BOAT 1 - E2A | E60: 8000.0 | G60: 1 | H60: EA | I60: 46297 | J60: 0 | K60: 2026-10-02 | L60: TWRIGHT | M60: 46297 | N60: TWRIGHT | O60: REL PRT PRC MANC SETC | Q60: 46297 | R60: 46304 | T60: ZSUBME | U60: 0.0 | Y60: 17:37:13 | AD60: 3.0 | AE60: 46286 | AF60: 10.0 | AG60: PP1 | AK60: 0.0 | AL60: 8000.0 | AO60: 0.0 | AR60: 0.0 | AS60: 10.0 | AT60: 17:37:10 | AV60: 7.0 | AW60: 1.0 | AX60: 5.0 | AZ60: 46289 | BC60: 0.0 | BE60: 0:00:00 | BF60: 0.0 | BJ60: 46302 | BK60: 0:00:00 | BL60: 24:00:00 | BM60: 1.0 | BR60: 46296 | BS60: 0:00:00 | BT60: 0:00:00 | BU60: 0:00:00 | BV60: 0.0 | BX60: 0 | CC60: PP-PC1 | CD60: 0.0 | CF60: 0.0 | CG60: PPP2 | CH60: PPP1 | CI60: 3000.0 | CM60: R5B OPF ASSEMBLY (4P-4FP) BOAT 1 - E2A | CV60: 0.0 | DB60: 2013-01-01 | DD60: 46286 | DF60: 1.0 | DG60: P | DH60: 92YFD04548BAA | DI60: EA | DJ60: 50003002.0 | DK60: S | DL60: 99999999.0 | DM60: 0.0 | DN60: 8000.0 | DP60: 0:00:00 | DR60: 0:00:00 | DS60: 0.0 | DT60: 0.0 | DW60: 0.0 | EA60: % | EB60: 0.0 | EH60: 1.0 | EJ60: 0.0 | EK60: 153455393.0 | EM60: 0.0 | EN60: S9I00022650 | EP60: EA | EQ60: 1 | ER60: Production | ES60: 2026-02-01 | ET60: 1.0 | EU60: 1.0 | EV60: 1.0 | EX60: 0.0 | EY60: 0.0 | FC60: Z0000001 | FD60: 1.0 | FE60: 1.0 | FF60: 92YFD04548BAA | FG60: 107321.0 | FH60: 1.0 | FI60: M | FJ60: 0.0 | FL60: 2.0 | FM60: 2026-10-02 | FP60: 0.0 | FR60: 0.0 | FT60: 2.0 | FU60: 2.0 | FW60: GBP
A61: 100880252 | B61: REP | C61: 92YFD04548BBA | D61: R5B OPF ASSEMBLY (4P-4FP) BOAT 2/3 - E2A | E61: 8000.0 | G61: 1 | H61: EA | I61: 46297 | J61: 0 | K61: 2026-10-02 | L61: TWRIGHT | M61: 46297 | N61: TWRIGHT | O61: REL PRT PRC MANC SETC | Q61: 46297 | R61: 46304 | T61: ZSUBME | U61: 0.0 | Y61: 17:39:46 | AD61: 3.0 | AE61: 46286 | AF61: 10.0 | AG61: PP1 | AK61: 0.0 | AL61: 8000.0 | AO61: 0.0 | AR61: 0.0 | AS61: 10.0 | AT61: 17:39:44 | AV61: 7.0 | AW61: 1.0 | AX61: 5.0 | AZ61: 46289 | BC61: 0.0 | BE61: 0:00:00 | BF61: 0.0 | BJ61: 46302 | BK61: 0:00:00 | BL61: 24:00:00 | BM61: 1.0 | BR61: 46296 | BS61: 0:00:00 | BT61: 0:00:00 | BU61: 0:00:00 | BV61: 0.0 | BX61: 0 | CC61: PP-PC1 | CD61: 0.0 | CF61: 0.0 | CG61: PPP2 | CH61: PPP1 | CI61: 3000.0 | CM61: R5B OPF ASSEMBLY (4P-4FP) BOAT 2/3 - E2A | CV61: 0.0 | DB61: 2013-01-01 | DD61: 46286 | DF61: 1.0 | DG61: P | DH61: 92YFD04548BBA | DI61: EA | DJ61: 50003002.0 | DK61: S | DL61: 99999999.0 | DM61: 0.0 | DN61: 8000.0 | DP61: 0:00:00 | DR61: 0:00:00 | DS61: 0.0 | DT61: 0.0 | DW61: 0.0 | EA61: % | EB61: 0.0 | EH61: 1.0 | EJ61: 0.0 | EK61: 153455418.0 | EM61: 0.0 | EN61: S9I00022651 | EP61: EA | EQ61: 1 | ER61: Production | ES61: 2026-02-01 | ET61: 1.0 | EU61: 1.0 | EV61: 1.0 | EX61: 0.0 | EY61: 0.0 | FC61: Z0000001 | FD61: 1.0 | FE61: 1.0 | FF61: 92YFD04548BBA | FG61: 107322.0 | FH61: 1.0 | FI61: M | FJ61: 0.0 | FL61: 2.0 | FM61: 2026-10-02 | FP61: 0.0 | FR61: 0.0 | FT61: 2.0 | FU61: 2.0 | FW61: GBP
A62: 100880253 | B62: REP | C62: 92YFD04548BBA | D62: R5B OPF ASSEMBLY (4P-4FP) BOAT 2/3 - E2A | E62: 8000.0 | G62: 1 | H62: EA | I62: 46297 | J62: 0 | K62: 2026-10-02 | L62: TWRIGHT | O62: REL PRT PRC MANC SETC | Q62: 46297 | R62: 46303 | T62: ZSUBME | U62: 0.0 | Y62: 0:00:00 | AD62: 3.0 | AE62: 46286 | AF62: 10.0 | AG62: PP1 | AK62: 0.0 | AL62: 8000.0 | AO62: 0.0 | AR62: 0.0 | AS62: 10.0 | AT62: 17:39:50 | AV62: 7.0 | AW62: 1.0 | AX62: 5.0 | AZ62: 46289 | BC62: 0.0 | BE62: 0:00:00 | BF62: 0.0 | BJ62: 46302 | BK62: 24:00:00 | BL62: 24:00:00 | BM62: 1.0 | BR62: 46296 | BS62: 0:00:00 | BT62: 0:00:00 | BU62: 0:00:00 | BV62: 0.0 | BX62: 0 | CC62: PP-PC1 | CD62: 0.0 | CF62: 0.0 | CG62: PPP2 | CH62: PPP1 | CI62: 3000.0 | CM62: R5B OPF ASSEMBLY (4P-4FP) BOAT 2/3 - E2A | CV62: 0.0 | DB62: 2013-01-01 | DD62: 46286 | DF62: 1.0 | DG62: P | DH62: 92YFD04548BBA | DI62: EA | DJ62: 50003002.0 | DK62: S | DL62: 99999999.0 | DM62: 0.0 | DN62: 8000.0 | DP62: 0:00:00 | DR62: 0:00:00 | DS62: 0.0 | DT62: 0.0 | DW62: 0.0 | EA62: % | EB62: 0.0 | EF62: 100880252.0 | EH62: 1.0 | EJ62: 0.0 | EK62: 153469809.0 | EM62: 0.0 | EN62: S9I00022651 | EP62: EA | EQ62: 1 | ER62: Production | ES62: 2026-02-01 | ET62: 1.0 | EU62: 1.0 | EV62: 1.0 | EX62: 0.0 | EY62: 0.0 | FC62: Z0000001 | FD62: 1.0 | FE62: 1.0 | FF62: 92YFD04548BBA | FG62: 107322.0 | FH62: 1.0 | FI62: M | FJ62: 0.0 | FL62: 2.0 | FM62: 2026-10-02 | FP62: 0.0 | FR62: 0.0 | FT62: 2.0 | FU62: 2.0 | FW62: GBP
A63: 100880254 | B63: REP | C63: 92YWS04548AAA | D63: R5B 4FP POB LUMENTUM SUB ASSEMBLY - E2A | E63: 8000.0 | G63: 1 | H63: EA | I63: 46297 | J63: 0 | K63: 2026-10-02 | L63: TWRIGHT | M63: 46297 | N63: TWRIGHT | O63: REL PRT PRC MANC SETC | Q63: 46297 | R63: 46304 | T63: ZSUBME | U63: 0.0 | Y63: 17:43:19 | AD63: 3.0 | AE63: 46286 | AF63: 10.0 | AG63: PP1 | AK63: 0.0 | AL63: 8000.0 | AO63: 0.0 | AR63: 0.0 | AS63: 10.0 | AT63: 17:43:16 | AV63: 7.0 | AW63: 1.0 | AX63: 5.0 | AZ63: 46295 | BC63: 0.0 | BE63: 0:00:00 | BF63: 0.0 | BJ63: 46302 | BK63: 0:00:00 | BL63: 24:00:00 | BM63: 1.0 | BR63: 46302 | BS63: 0:00:00 | BT63: 0:00:00 | BU63: 24:00:00 | BV63: 0.0 | BX63: 0 | CC63: PP-PC1 | CD63: 0.0 | CF63: 0.0 | CG63: PPP2 | CH63: PPP1 | CI63: 3000.0 | CM63: R5B 4FP POB LUMENTUM SUB ASSEMBLY - E2A | CV63: 0.0 | DB63: 2013-01-01 | DD63: 46286 | DF63: 1.0 | DG63: P | DH63: 92YWS04548AAA | DI63: EA | DJ63: 50002991.0 | DK63: S | DL63: 99999999.0 | DM63: 0.0 | DN63: 8000.0 | DP63: 0:00:00 | DR63: 0:00:00 | DS63: 0.0 | DT63: 0.0 | DW63: 0.0 | EA63: % | EB63: 0.0 | EH63: 1.0 | EJ63: 0.0 | EK63: 153455696.0 | EM63: 0.0 | EN63: S9I00022614 | EP63: EA | EQ63: 1 | ER63: Production | ES63: 2026-02-13 | ET63: 1.0 | EU63: 1.0 | EV63: 1.0 | EX63: 0.0 | EY63: 0.0 | FC63: Z0000001 | FD63: 1.0 | FE63: 1.0 | FF63: 92YWS04548AAA | FG63: 107275.0 | FH63: 1.0 | FI63: M | FJ63: 0.0 | FL63: 2.0 | FM63: 2026-10-02 | FP63: 0.0 | FR63: 0.0 | FT63: 2.0 | FU63: 2.0 | FW63: GBP
A64: 100880255 | B64: REP | C64: 92YWS04548AAA | D64: R5B 4FP POB LUMENTUM SUB ASSEMBLY - E2A | E64: 8000.0 | G64: 1 | H64: EA | I64: 46297 | J64: 0 | K64: 2026-10-02 | L64: TWRIGHT | O64: REL PRT PRC MANC SETC | Q64: 46297 | R64: 46303 | T64: ZSUBME | U64: 0.0 | Y64: 0:00:00 | AD64: 3.0 | AE64: 46286 | AF64: 10.0 | AG64: PP1 | AK64: 0.0 | AL64: 8000.0 | AO64: 0.0 | AR64: 0.0 | AS64: 10.0 | AT64: 17:43:22 | AV64: 7.0 | AW64: 1.0 | AX64: 5.0 | AZ64: 46295 | BC64: 0.0 | BE64: 0:00:00 | BF64: 0.0 | BJ64: 46302 | BK64: 24:00:00 | BL64: 24:00:00 | BM64: 1.0 | BR64: 46302 | BS64: 0:00:00 | BT64: 0:00:00 | BU64: 24:00:00 | BV64: 0.0 | BX64: 0 | CC64: PP-PC1 | CD64: 0.0 | CF64: 0.0 | CG64: PPP2 | CH64: PPP1 | CI64: 3000.0 | CM64: R5B 4FP POB LUMENTUM SUB ASSEMBLY - E2A | CV64: 0.0 | DB64: 2013-01-01 | DD64: 46286 | DF64: 1.0 | DG64: P | DH64: 92YWS04548AAA | DI64: EA | DJ64: 50002991.0 | DK64: S | DL64: 99999999.0 | DM64: 0.0 | DN64: 8000.0 | DP64: 0:00:00 | DR64: 0:00:00 | DS64: 0.0 | DT64: 0.0 | DW64: 0.0 | EA64: % | EB64: 0.0 | EF64: 100880254.0 | EH64: 1.0 | EJ64: 0.0 | EK64: 153469811.0 | EM64: 0.0 | EN64: S9I00022614 | EP64: EA | EQ64: 1 | ER64: Production | ES64: 2026-02-13 | ET64: 1.0 | EU64: 1.0 | EV64: 1.0 | EX64: 0.0 | EY64: 0.0 | FC64: Z0000001 | FD64: 1.0 | FE64: 1.0 | FF64: 92YWS04548AAA | FG64: 107275.0 | FH64: 1.0 | FI64: M | FJ64: 0.0 | FL64: 2.0 | FM64: 2026-10-02 | FP64: 0.0 | FR64: 0.0 | FT64: 2.0 | FU64: 2.0 | FW64: GBP
A65: 100880256 | B65: REP | C65: 92YWS04548AAA | D65: R5B 4FP POB LUMENTUM SUB ASSEMBLY - E2A | E65: 8000.0 | G65: 1 | H65: EA | I65: 46297 | J65: 0 | K65: 2026-10-02 | L65: TWRIGHT | O65: REL PRT PRC MANC SETC | Q65: 46297 | R65: 46303 | T65: ZSUBME | U65: 0.0 | Y65: 0:00:00 | AD65: 3.0 | AE65: 46286 | AF65: 10.0 | AG65: PP1 | AK65: 0.0 | AL65: 8000.0 | AO65: 0.0 | AR65: 0.0 | AS65: 10.0 | AT65: 17:43:26 | AV65: 7.0 | AW65: 1.0 | AX65: 5.0 | AZ65: 46295 | BC65: 0.0 | BE65: 0:00:00 | BF65: 0.0 | BJ65: 46302 | BK65: 24:00:00 | BL65: 24:00:00 | BM65: 1.0 | BR65: 46302 | BS65: 0:00:00 | BT65: 0:00:00 | BU65: 24:00:00 | BV65: 0.0 | BX65: 0 | CC65: PP-PC1 | CD65: 0.0 | CF65: 0.0 | CG65: PPP2 | CH65: PPP1 | CI65: 3000.0 | CM65: R5B 4FP POB LUMENTUM SUB ASSEMBLY - E2A | CV65: 0.0 | DB65: 2013-01-01 | DD65: 46286 | DF65: 1.0 | DG65: P | DH65: 92YWS04548AAA | DI65: EA | DJ65: 50002991.0 | DK65: S | DL65: 99999999.0 | DM65: 0.0 | DN65: 8000.0 | DP65: 0:00:00 | DR65: 0:00:00 | DS65: 0.0 | DT65: 0.0 | DW65: 0.0 | EA65: % | EB65: 0.0 | EF65: 100880254.0 | EH65: 1.0 | EJ65: 0.0 | EK65: 153469812.0 | EM65: 0.0 | EN65: S9I00022614 | EP65: EA | EQ65: 1 | ER65: Production | ES65: 2026-02-13 | ET65: 1.0 | EU65: 1.0 | EV65: 1.0 | EX65: 0.0 | EY65: 0.0 | FC65: Z0000001 | FD65: 1.0 | FE65: 1.0 | FF65: 92YWS04548AAA | FG65: 107275.0 | FH65: 1.0 | FI65: M | FJ65: 0.0 | FL65: 2.0 | FM65: 2026-10-02 | FP65: 0.0 | FR65: 0.0 | FT65: 2.0 | FU65: 2.0 | FW65: GBP
A66: 100880257 | B66: REP | C66: 92RRA00548AAA | D66: R5B ERBIUM SPOOL ASSEMBLY - E2A | E66: 8000.0 | G66: 1 | H66: EA | I66: 46297 | J66: 0 | K66: 2026-10-02 | L66: TWRIGHT | M66: 46297 | N66: TWRIGHT | O66: REL PRT PRC MANC SETC | Q66: 46297 | R66: 46304 | T66: ZSUBME | U66: 0.0 | Y66: 17:51:06 | AD66: 3.0 | AE66: 46294 | AF66: 10.0 | AG66: PP1 | AK66: 0.0 | AL66: 8000.0 | AO66: 0.0 | AR66: 0.0 | AS66: 10.0 | AT66: 17:51:03 | AV66: 7.0 | AW66: 1.0 | AX66: 5.0 | AZ66: 46295 | BC66: 0.0 | BE66: 0:00:00 | BF66: 0.0 | BJ66: 46302 | BK66: 0:00:00 | BL66: 24:00:00 | BM66: 1.0 | BR66: 46302 | BS66: 0:00:00 | BT66: 0:00:00 | BU66: 24:00:00 | BV66: 0.0 | BX66: 0 | CC66: PP-PC1 | CD66: 0.0 | CF66: 0.0 | CG66: PPP2 | CH66: PPP1 | CI66: 3000.0 | CM66: R5B ERBIUM SPOOL ASSEMBLY - E2A | CV66: 0.0 | DB66: 2013-01-01 | DD66: 46294 | DF66: 1.0 | DG66: P | DH66: 92RRA00548AAA | DI66: EA | DJ66: 50002963.0 | DK66: S | DL66: 99999999.0 | DM66: 0.0 | DN66: 8000.0 | DP66: 0:00:00 | DR66: 0:00:00 | DS66: 0.0 | DT66: 0.0 | DW66: 0.0 | EA66: % | EB66: 0.0 | EH66: 1.0 | EJ66: 0.0 | EK66: 153458137.0 | EM66: 0.0 | EN66: S9I00022645 | EP66: EA | EQ66: 1 | ER66: Production | ES66: 2026-03-01 | ET66: 1.0 | EU66: 1.0 | EV66: 1.0 | EX66: 0.0 | EY66: 0.0 | FC66: Z0000001 | FD66: 1.0 | FE66: 1.0 | FF66: 92RRA00548AAA | FG66: 107316.0 | FH66: 1.0 | FI66: M | FJ66: 0.0 | FL66: 2.0 | FM66: 2026-10-02 | FP66: 0.0 | FR66: 0.0 | FT66: 2.0 | FU66: 2.0 | FW66: GBP
A67: 100880258 | B67: REP | C67: 92RRA00548AAA | D67: R5B ERBIUM SPOOL ASSEMBLY - E2A | E67: 8000.0 | G67: 1 | H67: EA | I67: 46297 | J67: 0 | K67: 2026-10-02 | L67: TWRIGHT | O67: REL PRT PRC MANC SETC | Q67: 46297 | R67: 46303 | T67: ZSUBME | U67: 0.0 | Y67: 0:00:00 | AD67: 3.0 | AE67: 46294 | AF67: 10.0 | AG67: PP1 | AK67: 0.0 | AL67: 8000.0 | AO67: 0.0 | AR67: 0.0 | AS67: 10.0 | AT67: 17:51:10 | AV67: 7.0 | AW67: 1.0 | AX67: 5.0 | AZ67: 46295 | BC67: 0.0 | BE67: 0:00:00 | BF67: 0.0 | BJ67: 46302 | BK67: 24:00:00 | BL67: 24:00:00 | BM67: 1.0 | BR67: 46302 | BS67: 0:00:00 | BT67: 0:00:00 | BU67: 24:00:00 | BV67: 0.0 | BX67: 0 | CC67: PP-PC1 | CD67: 0.0 | CF67: 0.0 | CG67: PPP2 | CH67: PPP1 | CI67: 3000.0 | CM67: R5B ERBIUM SPOOL ASSEMBLY - E2A | CV67: 0.0 | DB67: 2013-01-01 | DD67: 46294 | DF67: 1.0 | DG67: P | DH67: 92RRA00548AAA | DI67: EA | DJ67: 50002963.0 | DK67: S | DL67: 99999999.0 | DM67: 0.0 | DN67: 8000.0 | DP67: 0:00:00 | DR67: 0:00:00 | DS67: 0.0 | DT67: 0.0 | DW67: 0.0 | EA67: % | EB67: 0.0 | EF67: 100880257.0 | EH67: 1.0 | EJ67: 0.0 | EK67: 153469814.0 | EM67: 0.0 | EN67: S9I00022645 | EP67: EA | EQ67: 1 | ER67: Production | ES67: 2026-03-01 | ET67: 1.0 | EU67: 1.0 | EV67: 1.0 | EX67: 0.0 | EY67: 0.0 | FC67: Z0000001 | FD67: 1.0 | FE67: 1.0 | FF67: 92RRA00548AAA | FG67: 107316.0 | FH67: 1.0 | FI67: M | FJ67: 0.0 | FL67: 2.0 | FM67: 2026-10-02 | FP67: 0.0 | FR67: 0.0 | FT67: 2.0 | FU67: 2.0 | FW67: GBP
A68: 100880259 | B68: REP | C68: 92RRA00548AAA | D68: R5B ERBIUM SPOOL ASSEMBLY - E2A | E68: 8000.0 | G68: 1 | H68: EA | I68: 46297 | J68: 0 | K68: 2026-10-02 | L68: TWRIGHT | O68: REL PRT PRC MANC SETC | Q68: 46297 | R68: 46303 | T68: ZSUBME | U68: 0.0 | Y68: 0:00:00 | AD68: 3.0 | AE68: 46294 | AF68: 10.0 | AG68: PP1 | AK68: 0.0 | AL68: 8000.0 | AO68: 0.0 | AR68: 0.0 | AS68: 10.0 | AT68: 17:51:13 | AV68: 7.0 | AW68: 1.0 | AX68: 5.0 | AZ68: 46295 | BC68: 0.0 | BE68: 0:00:00 | BF68: 0.0 | BJ68: 46302 | BK68: 24:00:00 | BL68: 24:00:00 | BM68: 1.0 | BR68: 46302 | BS68: 0:00:00 | BT68: 0:00:00 | BU68: 24:00:00 | BV68: 0.0 | BX68: 0 | CC68: PP-PC1 | CD68: 0.0 | CF68: 0.0 | CG68: PPP2 | CH68: PPP1 | CI68: 3000.0 | CM68: R5B ERBIUM SPOOL ASSEMBLY - E2A | CV68: 0.0 | DB68: 2013-01-01 | DD68: 46294 | DF68: 1.0 | DG68: P | DH68: 92RRA00548AAA | DI68: EA | DJ68: 50002963.0 | DK68: S | DL68: 99999999.0 | DM68: 0.0 | DN68: 8000.0 | DP68: 0:00:00 | DR68: 0:00:00 | DS68: 0.0 | DT68: 0.0 | DW68: 0.0 | EA68: % | EB68: 0.0 | EF68: 100880257.0 | EH68: 1.0 | EJ68: 0.0 | EK68: 153469815.0 | EM68: 0.0 | EN68: S9I00022645 | EP68: EA | EQ68: 1 | ER68: Production | ES68: 2026-03-01 | ET68: 1.0 | EU68: 1.0 | EV68: 1.0 | EX68: 0.0 | EY68: 0.0 | FC68: Z0000001 | FD68: 1.0 | FE68: 1.0 | FF68: 92RRA00548AAA | FG68: 107316.0 | FH68: 1.0 | FI68: M | FJ68: 0.0 | FL68: 2.0 | FM68: 2026-10-02 | FP68: 0.0 | FR68: 0.0 | FT68: 2.0 | FU68: 2.0 | FW68: GBP
A69: 100880260 | B69: REP | C69: 92RRA00548AAA | D69: R5B ERBIUM SPOOL ASSEMBLY - E2A | E69: 8000.0 | G69: 1 | H69: EA | I69: 46297 | J69: 0 | K69: 2026-10-02 | L69: TWRIGHT | O69: REL PRT PRC MANC SETC | Q69: 46297 | R69: 46303 | T69: ZSUBME | U69: 0.0 | Y69: 0:00:00 | AD69: 3.0 | AE69: 46294 | AF69: 10.0 | AG69: PP1 | AK69: 0.0 | AL69: 8000.0 | AO69: 0.0 | AR69: 0.0 | AS69: 10.0 | AT69: 17:51:16 | AV69: 7.0 | AW69: 1.0 | AX69: 5.0 | AZ69: 46295 | BC69: 0.0 | BE69: 0:00:00 | BF69: 0.0 | BJ69: 46302 | BK69: 24:00:00 | BL69: 24:00:00 | BM69: 1.0 | BR69: 46302 | BS69: 0:00:00 | BT69: 0:00:00 | BU69: 24:00:00 | BV69: 0.0 | BX69: 0 | CC69: PP-PC1 | CD69: 0.0 | CF69: 0.0 | CG69: PPP2 | CH69: PPP1 | CI69: 3000.0 | CM69: R5B ERBIUM SPOOL ASSEMBLY - E2A | CV69: 0.0 | DB69: 2013-01-01 | DD69: 46294 | DF69: 1.0 | DG69: P | DH69: 92RRA00548AAA | DI69: EA | DJ69: 50002963.0 | DK69: S | DL69: 99999999.0 | DM69: 0.0 | DN69: 8000.0 | DP69: 0:00:00 | DR69: 0:00:00 | DS69: 0.0 | DT69: 0.0 | DW69: 0.0 | EA69: % | EB69: 0.0 | EF69: 100880257.0 | EH69: 1.0 | EJ69: 0.0 | EK69: 153469816.0 | EM69: 0.0 | EN69: S9I00022645 | EP69: EA | EQ69: 1 | ER69: Production | ES69: 2026-03-01 | ET69: 1.0 | EU69: 1.0 | EV69: 1.0 | EX69: 0.0 | EY69: 0.0 | FC69: Z0000001 | FD69: 1.0 | FE69: 1.0 | FF69: 92RRA00548AAA | FG69: 107316.0 | FH69: 1.0 | FI69: M | FJ69: 0.0 | FL69: 2.0 | FM69: 2026-10-02 | FP69: 0.0 | FR69: 0.0 | FT69: 2.0 | FU69: 2.0 | FW69: GBP
A70: 100880261 | B70: REP | C70: 92RRA00548AAA | D70: R5B ERBIUM SPOOL ASSEMBLY - E2A | E70: 8000.0 | G70: 1 | H70: EA | I70: 46297 | J70: 0 | K70: 2026-10-02 | L70: TWRIGHT | O70: REL PRT PRC MANC SETC | Q70: 46297 | R70: 46303 | T70: ZSUBME | U70: 0.0 | Y70: 0:00:00 | AD70: 3.0 | AE70: 46294 | AF70: 10.0 | AG70: PP1 | AK70: 0.0 | AL70: 8000.0 | AO70: 0.0 | AR70: 0.0 | AS70: 10.0 | AT70: 17:51:19 | AV70: 7.0 | AW70: 1.0 | AX70: 5.0 | AZ70: 46295 | BC70: 0.0 | BE70: 0:00:00 | BF70: 0.0 | BJ70: 46302 | BK70: 24:00:00 | BL70: 24:00:00 | BM70: 1.0 | BR70: 46302 | BS70: 0:00:00 | BT70: 0:00:00 | BU70: 24:00:00 | BV70: 0.0 | BX70: 0 | CC70: PP-PC1 | CD70: 0.0 | CF70: 0.0 | CG70: PPP2 | CH70: PPP1 | CI70: 3000.0 | CM70: R5B ERBIUM SPOOL ASSEMBLY - E2A | CV70: 0.0 | DB70: 2013-01-01 | DD70: 46294 | DF70: 1.0 | DG70: P | DH70: 92RRA00548AAA | DI70: EA | DJ70: 50002963.0 | DK70: S | DL70: 99999999.0 | DM70: 0.0 | DN70: 8000.0 | DP70: 0:00:00 | DR70: 0:00:00 | DS70: 0.0 | DT70: 0.0 | DW70: 0.0 | EA70: % | EB70: 0.0 | EF70: 100880257.0 | EH70: 1.0 | EJ70: 0.0 | EK70: 153469817.0 | EM70: 0.0 | EN70: S9I00022645 | EP70: EA | EQ70: 1 | ER70: Production | ES70: 2026-03-01 | ET70: 1.0 | EU70: 1.0 | EV70: 1.0 | EX70: 0.0 | EY70: 0.0 | FC70: Z0000001 | FD70: 1.0 | FE70: 1.0 | FF70: 92RRA00548AAA | FG70: 107316.0 | FH70: 1.0 | FI70: M | FJ70: 0.0 | FL70: 2.0 | FM70: 2026-10-02 | FP70: 0.0 | FR70: 0.0 | FT70: 2.0 | FU70: 2.0 | FW70: GBP
A71: 100880262 | B71: REP | C71: 92RRA00548AAA | D71: R5B ERBIUM SPOOL ASSEMBLY - E2A | E71: 8000.0 | G71: 1 | H71: EA | I71: 46297 | J71: 0 | K71: 2026-10-02 | L71: TWRIGHT | O71: REL PRT PRC MANC SETC | Q71: 46297 | R71: 46303 | T71: ZSUBME | U71: 0.0 | Y71: 0:00:00 | AD71: 3.0 | AE71: 46294 | AF71: 10.0 | AG71: PP1 | AK71: 0.0 | AL71: 8000.0 | AO71: 0.0 | AR71: 0.0 | AS71: 10.0 | AT71: 17:51:22 | AV71: 7.0 | AW71: 1.0 | AX71: 5.0 | AZ71: 46295 | BC71: 0.0 | BE71: 0:00:00 | BF71: 0.0 | BJ71: 46302 | BK71: 24:00:00 | BL71: 24:00:00 | BM71: 1.0 | BR71: 46302 | BS71: 0:00:00 | BT71: 0:00:00 | BU71: 24:00:00 | BV71: 0.0 | BX71: 0 | CC71: PP-PC1 | CD71: 0.0 | CF71: 0.0 | CG71: PPP2 | CH71: PPP1 | CI71: 3000.0 | CM71: R5B ERBIUM SPOOL ASSEMBLY - E2A | CV71: 0.0 | DB71: 2013-01-01 | DD71: 46294 | DF71: 1.0 | DG71: P | DH71: 92RRA00548AAA | DI71: EA | DJ71: 50002963.0 | DK71: S | DL71: 99999999.0 | DM71: 0.0 | DN71: 8000.0 | DP71: 0:00:00 | DR71: 0:00:00 | DS71: 0.0 | DT71: 0.0 | DW71: 0.0 | EA71: % | EB71: 0.0 | EF71: 100880257.0 | EH71: 1.0 | EJ71: 0.0 | EK71: 153469818.0 | EM71: 0.0 | EN71: S9I00022645 | EP71: EA | EQ71: 1 | ER71: Production | ES71: 2026-03-01 | ET71: 1.0 | EU71: 1.0 | EV71: 1.0 | EX71: 0.0 | EY71: 0.0 | FC71: Z0000001 | FD71: 1.0 | FE71: 1.0 | FF71: 92RRA00548AAA | FG71: 107316.0 | FH71: 1.0 | FI71: M | FJ71: 0.0 | FL71: 2.0 | FM71: 2026-10-02 | FP71: 0.0 | FR71: 0.0 | FT71: 2.0 | FU71: 2.0 | FW71: GBP
A72: 100880263 | B72: REP | C72: 92RRA00548AAA | D72: R5B ERBIUM SPOOL ASSEMBLY - E2A | E72: 8000.0 | G72: 1 | H72: EA | I72: 46297 | J72: 0 | K72: 2026-10-02 | L72: TWRIGHT | O72: REL PRT PRC MANC SETC | Q72: 46297 | R72: 46303 | T72: ZSUBME | U72: 0.0 | Y72: 0:00:00 | AD72: 3.0 | AE72: 46294 | AF72: 10.0 | AG72: PP1 | AK72: 0.0 | AL72: 8000.0 | AO72: 0.0 | AR72: 0.0 | AS72: 10.0 | AT72: 17:51:25 | AV72: 7.0 | AW72: 1.0 | AX72: 5.0 | AZ72: 46295 | BC72: 0.0 | BE72: 0:00:00 | BF72: 0.0 | BJ72: 46302 | BK72: 24:00:00 | BL72: 24:00:00 | BM72: 1.0 | BR72: 46302 | BS72: 0:00:00 | BT72: 0:00:00 | BU72: 24:00:00 | BV72: 0.0 | BX72: 0 | CC72: PP-PC1 | CD72: 0.0 | CF72: 0.0 | CG72: PPP2 | CH72: PPP1 | CI72: 3000.0 | CM72: R5B ERBIUM SPOOL ASSEMBLY - E2A | CV72: 0.0 | DB72: 2013-01-01 | DD72: 46294 | DF72: 1.0 | DG72: P | DH72: 92RRA00548AAA | DI72: EA | DJ72: 50002963.0 | DK72: S | DL72: 99999999.0 | DM72: 0.0 | DN72: 8000.0 | DP72: 0:00:00 | DR72: 0:00:00 | DS72: 0.0 | DT72: 0.0 | DW72: 0.0 | EA72: % | EB72: 0.0 | EF72: 100880257.0 | EH72: 1.0 | EJ72: 0.0 | EK72: 153469819.0 | EM72: 0.0 | EN72: S9I00022645 | EP72: EA | EQ72: 1 | ER72: Production | ES72: 2026-03-01 | ET72: 1.0 | EU72: 1.0 | EV72: 1.0 | EX72: 0.0 | EY72: 0.0 | FC72: Z0000001 | FD72: 1.0 | FE72: 1.0 | FF72: 92RRA00548AAA | FG72: 107316.0 | FH72: 1.0 | FI72: M | FJ72: 0.0 | FL72: 2.0 | FM72: 2026-10-02 | FP72: 0.0 | FR72: 0.0 | FT72: 2.0 | FU72: 2.0 | FW72: GBP
A73: 100880264 | B73: REP | C73: 92RRA00548AAA | D73: R5B ERBIUM SPOOL ASSEMBLY - E2A | E73: 8000.0 | G73: 1 | H73: EA | I73: 46297 | J73: 0 | K73: 2026-10-02 | L73: TWRIGHT | O73: REL PRT PRC MANC SETC | Q73: 46297 | R73: 46303 | T73: ZSUBME | U73: 0.0 | Y73: 0:00:00 | AD73: 3.0 | AE73: 46294 | AF73: 10.0 | AG73: PP1 | AK73: 0.0 | AL73: 8000.0 | AO73: 0.0 | AR73: 0.0 | AS73: 10.0 | AT73: 17:51:28 | AV73: 7.0 | AW73: 1.0 | AX73: 5.0 | AZ73: 46295 | BC73: 0.0 | BE73: 0:00:00 | BF73: 0.0 | BJ73: 46302 | BK73: 24:00:00 | BL73: 24:00:00 | BM73: 1.0 | BR73: 46302 | BS73: 0:00:00 | BT73: 0:00:00 | BU73: 24:00:00 | BV73: 0.0 | BX73: 0 | CC73: PP-PC1 | CD73: 0.0 | CF73: 0.0 | CG73: PPP2 | CH73: PPP1 | CI73: 3000.0 | CM73: R5B ERBIUM SPOOL ASSEMBLY - E2A | CV73: 0.0 | DB73: 2013-01-01 | DD73: 46294 | DF73: 1.0 | DG73: P | DH73: 92RRA00548AAA | DI73: EA | DJ73: 50002963.0 | DK73: S | DL73: 99999999.0 | DM73: 0.0 | DN73: 8000.0 | DP73: 0:00:00 | DR73: 0:00:00 | DS73: 0.0 | DT73: 0.0 | DW73: 0.0 | EA73: % | EB73: 0.0 | EF73: 100880257.0 | EH73: 1.0 | EJ73: 0.0 | EK73: 153469820.0 | EM73: 0.0 | EN73: S9I00022645 | EP73: EA | EQ73: 1 | ER73: Production | ES73: 2026-03-01 | ET73: 1.0 | EU73: 1.0 | EV73: 1.0 | EX73: 0.0 | EY73: 0.0 | FC73: Z0000001 | FD73: 1.0 | FE73: 1.0 | FF73: 92RRA00548AAA | FG73: 107316.0 | FH73: 1.0 | FI73: M | FJ73: 0.0 | FL73: 2.0 | FM73: 2026-10-02 | FP73: 0.0 | FR73: 0.0 | FT73: 2.0 | FU73: 2.0 | FW73: GBP
A74: 100880265 | B74: REP | C74: 92RRA00548AAA | D74: R5B ERBIUM SPOOL ASSEMBLY - E2A | E74: 8000.0 | G74: 1 | H74: EA | I74: 46297 | J74: 0 | K74: 2026-10-02 | L74: TWRIGHT | O74: REL PRT PRC MANC SETC | Q74: 46297 | R74: 46303 | T74: ZSUBME | U74: 0.0 | Y74: 0:00:00 | AD74: 3.0 | AE74: 46294 | AF74: 10.0 | AG74: PP1 | AK74: 0.0 | AL74: 8000.0 | AO74: 0.0 | AR74: 0.0 | AS74: 10.0 | AT74: 17:51:31 | AV74: 7.0 | AW74: 1.0 | AX74: 5.0 | AZ74: 46295 | BC74: 0.0 | BE74: 0:00:00 | BF74: 0.0 | BJ74: 46302 | BK74: 24:00:00 | BL74: 24:00:00 | BM74: 1.0 | BR74: 46302 | BS74: 0:00:00 | BT74: 0:00:00 | BU74: 24:00:00 | BV74: 0.0 | BX74: 0 | CC74: PP-PC1 | CD74: 0.0 | CF74: 0.0 | CG74: PPP2 | CH74: PPP1 | CI74: 3000.0 | CM74: R5B ERBIUM SPOOL ASSEMBLY - E2A | CV74: 0.0 | DB74: 2013-01-01 | DD74: 46294 | DF74: 1.0 | DG74: P | DH74: 92RRA00548AAA | DI74: EA | DJ74: 50002963.0 | DK74: S | DL74: 99999999.0 | DM74: 0.0 | DN74: 8000.0 | DP74: 0:00:00 | DR74: 0:00:00 | DS74: 0.0 | DT74: 0.0 | DW74: 0.0 | EA74: % | EB74: 0.0 | EF74: 100880257.0 | EH74: 1.0 | EJ74: 0.0 | EK74: 153469821.0 | EM74: 0.0 | EN74: S9I00022645 | EP74: EA | EQ74: 1 | ER74: Production | ES74: 2026-03-01 | ET74: 1.0 | EU74: 1.0 | EV74: 1.0 | EX74: 0.0 | EY74: 0.0 | FC74: Z0000001 | FD74: 1.0 | FE74: 1.0 | FF74: 92RRA00548AAA | FG74: 107316.0 | FH74: 1.0 | FI74: M | FJ74: 0.0 | FL74: 2.0 | FM74: 2026-10-02 | FP74: 0.0 | FR74: 0.0 | FT74: 2.0 | FU74: 2.0 | FW74: GBP
A75: 100880266 | B75: REP | C75: 92RRA00548AAA | D75: R5B ERBIUM SPOOL ASSEMBLY - E2A | E75: 8000.0 | G75: 1 | H75: EA | I75: 46297 | J75: 0 | K75: 2026-10-02 | L75: TWRIGHT | O75: REL PRT PRC MANC SETC | Q75: 46297 | R75: 46303 | T75: ZSUBME | U75: 0.0 | Y75: 0:00:00 | AD75: 3.0 | AE75: 46294 | AF75: 10.0 | AG75: PP1 | AK75: 0.0 | AL75: 8000.0 | AO75: 0.0 | AR75: 0.0 | AS75: 10.0 | AT75: 17:51:34 | AV75: 7.0 | AW75: 1.0 | AX75: 5.0 | AZ75: 46295 | BC75: 0.0 | BE75: 0:00:00 | BF75: 0.0 | BJ75: 46302 | BK75: 24:00:00 | BL75: 24:00:00 | BM75: 1.0 | BR75: 46302 | BS75: 0:00:00 | BT75: 0:00:00 | BU75: 24:00:00 | BV75: 0.0 | BX75: 0 | CC75: PP-PC1 | CD75: 0.0 | CF75: 0.0 | CG75: PPP2 | CH75: PPP1 | CI75: 3000.0 | CM75: R5B ERBIUM SPOOL ASSEMBLY - E2A | CV75: 0.0 | DB75: 2013-01-01 | DD75: 46294 | DF75: 1.0 | DG75: P | DH75: 92RRA00548AAA | DI75: EA | DJ75: 50002963.0 | DK75: S | DL75: 99999999.0 | DM75: 0.0 | DN75: 8000.0 | DP75: 0:00:00 | DR75: 0:00:00 | DS75: 0.0 | DT75: 0.0 | DW75: 0.0 | EA75: % | EB75: 0.0 | EF75: 100880257.0 | EH75: 1.0 | EJ75: 0.0 | EK75: 153469822.0 | EM75: 0.0 | EN75: S9I00022645 | EP75: EA | EQ75: 1 | ER75: Production | ES75: 2026-03-01 | ET75: 1.0 | EU75: 1.0 | EV75: 1.0 | EX75: 0.0 | EY75: 0.0 | FC75: Z0000001 | FD75: 1.0 | FE75: 1.0 | FF75: 92RRA00548AAA | FG75: 107316.0 | FH75: 1.0 | FI75: M | FJ75: 0.0 | FL75: 2.0 | FM75: 2026-10-02 | FP75: 0.0 | FR75: 0.0 | FT75: 2.0 | FU75: 2.0 | FW75: GBP
A76: 100880267 | B76: REP | C76: 92RRA00548AAA | D76: R5B ERBIUM SPOOL ASSEMBLY - E2A | E76: 8000.0 | G76: 1 | H76: EA | I76: 46297 | J76: 0 | K76: 2026-10-02 | L76: TWRIGHT | O76: REL PRT PRC MANC SETC | Q76: 46297 | R76: 46303 | T76: ZSUBME | U76: 0.0 | Y76: 0:00:00 | AD76: 3.0 | AE76: 46294 | AF76: 10.0 | AG76: PP1 | AK76: 0.0 | AL76: 8000.0 | AO76: 0.0 | AR76: 0.0 | AS76: 10.0 | AT76: 17:51:37 | AV76: 7.0 | AW76: 1.0 | AX76: 5.0 | AZ76: 46295 | BC76: 0.0 | BE76: 0:00:00 | BF76: 0.0 | BJ76: 46302 | BK76: 24:00:00 | BL76: 24:00:00 | BM76: 1.0 | BR76: 46302 | BS76: 0:00:00 | BT76: 0:00:00 | BU76: 24:00:00 | BV76: 0.0 | BX76: 0 | CC76: PP-PC1 | CD76: 0.0 | CF76: 0.0 | CG76: PPP2 | CH76: PPP1 | CI76: 3000.0 | CM76: R5B ERBIUM SPOOL ASSEMBLY - E2A | CV76: 0.0 | DB76: 2013-01-01 | DD76: 46294 | DF76: 1.0 | DG76: P | DH76: 92RRA00548AAA | DI76: EA | DJ76: 50002963.0 | DK76: S | DL76: 99999999.0 | DM76: 0.0 | DN76: 8000.0 | DP76: 0:00:00 | DR76: 0:00:00 | DS76: 0.0 | DT76: 0.0 | DW76: 0.0 | EA76: % | EB76: 0.0 | EF76: 100880257.0 | EH76: 1.0 | EJ76: 0.0 | EK76: 153469823.0 | EM76: 0.0 | EN76: S9I00022645 | EP76: EA | EQ76: 1 | ER76: Production | ES76: 2026-03-01 | ET76: 1.0 | EU76: 1.0 | EV76: 1.0 | EX76: 0.0 | EY76: 0.0 | FC76: Z0000001 | FD76: 1.0 | FE76: 1.0 | FF76: 92RRA00548AAA | FG76: 107316.0 | FH76: 1.0 | FI76: M | FJ76: 0.0 | FL76: 2.0 | FM76: 2026-10-02 | FP76: 0.0 | FR76: 0.0 | FT76: 2.0 | FU76: 2.0 | FW76: GBP
A77: 100880268 | B77: REP | C77: 92RRA00548AAA | D77: R5B ERBIUM SPOOL ASSEMBLY - E2A | E77: 8000.0 | G77: 1 | H77: EA | I77: 46297 | J77: 0 | K77: 2026-10-02 | L77: TWRIGHT | O77: REL PRT PRC MANC SETC | Q77: 46297 | R77: 46303 | T77: ZSUBME | U77: 0.0 | Y77: 0:00:00 | AD77: 3.0 | AE77: 46294 | AF77: 10.0 | AG77: PP1 | AK77: 0.0 | AL77: 8000.0 | AO77: 0.0 | AR77: 0.0 | AS77: 10.0 | AT77: 17:51:40 | AV77: 7.0 | AW77: 1.0 | AX77: 5.0 | AZ77: 46295 | BC77: 0.0 | BE77: 0:00:00 | BF77: 0.0 | BJ77: 46302 | BK77: 24:00:00 | BL77: 24:00:00 | BM77: 1.0 | BR77: 46302 | BS77: 0:00:00 | BT77: 0:00:00 | BU77: 24:00:00 | BV77: 0.0 | BX77: 0 | CC77: PP-PC1 | CD77: 0.0 | CF77: 0.0 | CG77: PPP2 | CH77: PPP1 | CI77: 3000.0 | CM77: R5B ERBIUM SPOOL ASSEMBLY - E2A | CV77: 0.0 | DB77: 2013-01-01 | DD77: 46294 | DF77: 1.0 | DG77: P | DH77: 92RRA00548AAA | DI77: EA | DJ77: 50002963.0 | DK77: S | DL77: 99999999.0 | DM77: 0.0 | DN77: 8000.0 | DP77: 0:00:00 | DR77: 0:00:00 | DS77: 0.0 | DT77: 0.0 | DW77: 0.0 | EA77: % | EB77: 0.0 | EF77: 100880257.0 | EH77: 1.0 | EJ77: 0.0 | EK77: 153469824.0 | EM77: 0.0 | EN77: S9I00022645 | EP77: EA | EQ77: 1 | ER77: Production | ES77: 2026-03-01 | ET77: 1.0 | EU77: 1.0 | EV77: 1.0 | EX77: 0.0 | EY77: 0.0 | FC77: Z0000001 | FD77: 1.0 | FE77: 1.0 | FF77: 92RRA00548AAA | FG77: 107316.0 | FH77: 1.0 | FI77: M | FJ77: 0.0 | FL77: 2.0 | FM77: 2026-10-02 | FP77: 0.0 | FR77: 0.0 | FT77: 2.0 | FU77: 2.0 | FW77: GBP
A78: 100880269 | B78: REP | C78: 92RRA00548AAA | D78: R5B ERBIUM SPOOL ASSEMBLY - E2A | E78: 8000.0 | G78: 1 | H78: EA | I78: 46297 | J78: 0 | K78: 2026-10-02 | L78: TWRIGHT | O78: REL PRT PRC MANC SETC | Q78: 46297 | R78: 46303 | T78: ZSUBME | U78: 0.0 | Y78: 0:00:00 | AD78: 3.0 | AE78: 46294 | AF78: 10.0 | AG78: PP1 | AK78: 0.0 | AL78: 8000.0 | AO78: 0.0 | AR78: 0.0 | AS78: 10.0 | AT78: 17:51:43 | AV78: 7.0 | AW78: 1.0 | AX78: 5.0 | AZ78: 46295 | BC78: 0.0 | BE78: 0:00:00 | BF78: 0.0 | BJ78: 46302 | BK78: 24:00:00 | BL78: 24:00:00 | BM78: 1.0 | BR78: 46302 | BS78: 0:00:00 | BT78: 0:00:00 | BU78: 24:00:00 | BV78: 0.0 | BX78: 0 | CC78: PP-PC1 | CD78: 0.0 | CF78: 0.0 | CG78: PPP2 | CH78: PPP1 | CI78: 3000.0 | CM78: R5B ERBIUM SPOOL ASSEMBLY - E2A | CV78: 0.0 | DB78: 2013-01-01 | DD78: 46294 | DF78: 1.0 | DG78: P | DH78: 92RRA00548AAA | DI78: EA | DJ78: 50002963.0 | DK78: S | DL78: 99999999.0 | DM78: 0.0 | DN78: 8000.0 | DP78: 0:00:00 | DR78: 0:00:00 | DS78: 0.0 | DT78: 0.0 | DW78: 0.0 | EA78: % | EB78: 0.0 | EF78: 100880257.0 | EH78: 1.0 | EJ78: 0.0 | EK78: 153469825.0 | EM78: 0.0 | EN78: S9I00022645 | EP78: EA | EQ78: 1 | ER78: Production | ES78: 2026-03-01 | ET78: 1.0 | EU78: 1.0 | EV78: 1.0 | EX78: 0.0 | EY78: 0.0 | FC78: Z0000001 | FD78: 1.0 | FE78: 1.0 | FF78: 92RRA00548AAA | FG78: 107316.0 | FH78: 1.0 | FI78: M | FJ78: 0.0 | FL78: 2.0 | FM78: 2026-10-02 | FP78: 0.0 | FR78: 0.0 | FT78: 2.0 | FU78: 2.0 | FW78: GBP
... A89: 100880280 | B89: REP | C89: 92RRA00548AAA | D89: R5B ERBIUM SPOOL ASSEMBLY - E2A | E89: 8000.0 | G89: 1 | H89: EA | I89: 46297 | J89: 0 | K89: 2026-10-02 | L89: TWRIGHT | O89: REL PRT PRC MANC SETC | Q89: 46297 | R89: 46303 | T89: ZSUBME | U89: 0.0 | Y89: 0:00:00 | AD89: 3.0 | AE89: 46294 | AF89: 10.0 | AG89: PP1 | AK89: 0.0 | AL89: 8000.0 | AO89: 0.0 | AR89: 0.0 | AS89: 10.0 | AT89: 17:52:17 | AV89: 7.0 | AW89: 1.0 | AX89: 5.0 | AZ89: 46295 | BC89: 0.0 | BE89: 0:00:00 | BF89: 0.0 | BJ89: 46302 | BK89: 24:00:00 | BL89: 24:00:00 | BM89: 1.0 | BR89: 46302 | BS89: 0:00:00 | BT89: 0:00:00 | BU89: 24:00:00 | BV89: 0.0 | BX89: 0 | CC89: PP-PC1 | CD89: 0.0 | CF89: 0.0 | CG89: PPP2 | CH89: PPP1 | CI89: 3000.0 | CM89: R5B ERBIUM SPOOL ASSEMBLY - E2A | CV89: 0.0 | DB89: 2013-01-01 | DD89: 46294 | DF89: 1.0 | DG89: P | DH89: 92RRA00548AAA | DI89: EA | DJ89: 50002963.0 | DK89: S | DL89: 99999999.0 | DM89: 0.0 | DN89: 8000.0 | DP89: 0:00:00 | DR89: 0:00:00 | DS89: 0.0 | DT89: 0.0 | DW89: 0.0 | EA89: % | EB89: 0.0 | EF89: 100880257.0 | EH89: 1.0 | EJ89: 0.0 | EK89: 153469836.0 | EM89: 0.0 | EN89: S9I00022645 | EP89: EA | EQ89: 1 | ER89: Production | ES89: 2026-03-01 | ET89: 1.0 | EU89: 1.0 | EV89: 1.0 | EX89: 0.0 | EY89: 0.0 | FC89: Z0000001 | FD89: 1.0 | FE89: 1.0 | FF89: 92RRA00548AAA | FG89: 107316.0 | FH89: 1.0 | FI89: M | FJ89: 0.0 | FL89: 2.0 | FM89: 2026-10-02 | FP89: 0.0 | FR89: 0.0 | FT89: 2.0 | FU89: 2.0 | FW89: GBP
